Workbook

Sheet Pivot Table 5
A1: Archived User Email | B1: New Owner Email | C1: Status | D1: Details | E1: Last Updated
A2: =IFERROR(__xludf.DUMMYFUNCTION("{""Department 🔂""; ARRAYFORMULA( IFERROR( FILTER(UNIQUE('On-Boarding'!$D$2:$D1002), UNIQUE('On-Boarding'!$D$2:$D1002) <> """") , """") ); ""Grand Total""}"),"Department 🔂") -> Department 🔂 | B2: Active Accounts 🔂
A3: =IFERROR(__xludf.DUMMYFUNCTION("""COMPUTED_VALUE"""),"Strategy") -> Strategy | B3: =(IF(A2:A1002 = "", "", COUNTIFS('On-Boarding'!$D$2:$D1002, A2:A1002, 'On-Boarding'!$L$2:$L1002, ""))) -> 14 | D3: 7+HOD
A4: =IFERROR(__xludf.DUMMYFUNCTION("""COMPUTED_VALUE"""),"Legal") -> Legal | B4: =(IF(A3:A1002 = "", "", COUNTIFS('On-Boarding'!$D$2:$D1002, A3:A1002, 'On-Boarding'!$L$2:$L1002, ""))) -> 8 | D4: 7+HOD
A5: =IFERROR(__xludf.DUMMYFUNCTION("""COMPUTED_VALUE"""),"Org") -> Org | B5: =(IF(A4:A1002 = "", "", COUNTIFS('On-Boarding'!$D$2:$D1002, A4:A1002, 'On-Boarding'!$L$2:$L1002, ""))) -> 13 | D5: 7
A6: =IFERROR(__xludf.DUMMYFUNCTION("""COMPUTED_VALUE"""),"Brand Marketing") -> Brand Marketing | B6: =(IF(A5:A1002 = "", "", COUNTIFS('On-Boarding'!$D$2:$D1002, A5:A1002, 'On-Boarding'!$L$2:$L1002, ""))) -> 19 | D6: 7+HOD
A7: =IFERROR(__xludf.DUMMYFUNCTION("""COMPUTED_VALUE"""),"Technology") -> Technology | B7: =(IF(A6:A1002 = "", "", COUNTIFS('On-Boarding'!$D$2:$D1002, A6:A1002, 'On-Boarding'!$L$2:$L1002, ""))) -> 69 | D7: 7+HOD
A8: =IFERROR(__xludf.DUMMYFUNCTION("""COMPUTED_VALUE"""),"Digital Marketing") -> Digital Marketing | B8: =(IF(A7:A1002 = "", "", COUNTIFS('On-Boarding'!$D$2:$D1002, A7:A1002, 'On-Boarding'!$L$2:$L1002, ""))) -> 18 | D8: 7+HOD
A9: =IFERROR(__xludf.DUMMYFUNCTION("""COMPUTED_VALUE"""),"Customer Experience") -> Customer Experience | B9: =(IF(A8:A1002 = "", "", COUNTIFS('On-Boarding'!$D$2:$D1002, A8:A1002, 'On-Boarding'!$L$2:$L1002, ""))) -> 31 | D9: 7+HOD
A10: =IFERROR(__xludf.DUMMYFUNCTION("""COMPUTED_VALUE"""),"Data") -> Data | B10: =(IF(A9:A1002 = "", "", COUNTIFS('On-Boarding'!$D$2:$D1002, A9:A1002, 'On-Boarding'!$L$2:$L1002, ""))) -> 32 | D10: 7+HOD
A11: =IFERROR(__xludf.DUMMYFUNCTION("""COMPUTED_VALUE"""),"Human Resources") -> Human Resources | B11: =(IF(A10:A1002 = "", "", COUNTIFS('On-Boarding'!$D$2:$D1002, A10:A1002, 'On-Boarding'!$L$2:$L1002, ""))) -> 16 | D11: 7+HOD
A12: =IFERROR(__xludf.DUMMYFUNCTION("""COMPUTED_VALUE"""),"Product Design") -> Product Design | B12: =(IF(A11:A1002 = "", "", COUNTIFS('On-Boarding'!$D$2:$D1002, A11:A1002, 'On-Boarding'!$L$2:$L1002, ""))) -> 8 | D12: 7+HOD
A13: =IFERROR(__xludf.DUMMYFUNCTION("""COMPUTED_VALUE"""),"Finance") -> Finance | B13: =(IF(A12:A1002 = "", "", COUNTIFS('On-Boarding'!$D$2:$D1002, A12:A1002, 'On-Boarding'!$L$2:$L1002, ""))) -> 23 | D13: 7+HOD
A14: =IFERROR(__xludf.DUMMYFUNCTION("""COMPUTED_VALUE"""),"Product") -> Product | B14: =(IF(A13:A1002 = "", "", COUNTIFS('On-Boarding'!$D$2:$D1002, A13:A1002, 'On-Boarding'!$L$2:$L1002, ""))) -> 24 | D14: 7+HOD
A15: =IFERROR(__xludf.DUMMYFUNCTION("""COMPUTED_VALUE"""),"IT Infra") -> IT Infra | B15: =(IF(A14:A1002 = "", "", COUNTIFS('On-Boarding'!$D$2:$D1002, A14:A1002, 'On-Boarding'!$L$2:$L1002, ""))) -> 12 | D15: 7+HOD
A16: =IFERROR(__xludf.DUMMYFUNCTION("""COMPUTED_VALUE"""),"P R & Corporate Comms") -> P R & Corporate Comms | B16: =(IF(A15:A1002 = "", "", COUNTIFS('On-Boarding'!$D$2:$D1002, A15:A1002, 'On-Boarding'!$L$2:$L1002, ""))) -> 2 | D16: 7+HOD
A17: =IFERROR(__xludf.DUMMYFUNCTION("""COMPUTED_VALUE"""),"Public Policy") -> Public Policy | B17: =(IF(A16:A1002 = "", "", COUNTIFS('On-Boarding'!$D$2:$D1002, A16:A1002, 'On-Boarding'!$L$2:$L1002, ""))) -> 1 | D17: 7+HOD
A18: =IFERROR(__xludf.DUMMYFUNCTION("""COMPUTED_VALUE"""),"Founder's Office") -> Founder's Office | B18: =(IF(A17:A1002 = "", "", COUNTIFS('On-Boarding'!$D$2:$D1002, A17:A1002, 'On-Boarding'!$L$2:$L1002, ""))) -> 5 | D18: 7+HOD
A19: =IFERROR(__xludf.DUMMYFUNCTION("""COMPUTED_VALUE"""),"Administration") -> Administration | B19: =(IF(A18:A1002 = "", "", COUNTIFS('On-Boarding'!$D$2:$D1002, A18:A1002, 'On-Boarding'!$L$2:$L1002, ""))) -> 3 | D19: 7+HOD
A20: =IFERROR(__xludf.DUMMYFUNCTION("""COMPUTED_VALUE"""),"strategy") -> strategy | B20: =(IF(A19:A1002 = "", "", COUNTIFS('On-Boarding'!$D$2:$D1002, A19:A1002, 'On-Boarding'!$L$2:$L1002, ""))) -> 14 | D20: 7+HOD
A21: =IFERROR(__xludf.DUMMYFUNCTION("""COMPUTED_VALUE"""),"Vertical Tv") -> Vertical Tv | B21: =(IF(A20:A1002 = "", "", COUNTIFS('On-Boarding'!$D$2:$D1002, A20:A1002, 'On-Boarding'!$L$2:$L1002, ""))) -> 86 | D21: 7+HOD
A22: =IFERROR(__xludf.DUMMYFUNCTION("""COMPUTED_VALUE"""),"Nucanon") -> Nucanon | B22: =(IF(A21:A1002 = "", "", COUNTIFS('On-Boarding'!$D$2:$D1002, A21:A1002, 'On-Boarding'!$L$2:$L1002, ""))) -> 1 | D22: 7+HOD
A23: =IFERROR(__xludf.DUMMYFUNCTION("""COMPUTED_VALUE"""),"Grand Total") -> Grand Total | B23: =SUM(B4:B22) -> 385
A26: User Group_JumpCloud | B26: User Group ID_GWS | D26: New OU Recommendation | E26: Status
A27: Org | B27: jcorg@zupee.in | D27: Administration | E27: x
A28: Technology | B28: jctech@zupee.in | D28: Brand Marketing | E28: x
A29: Product Design | B29: jcproduct@zupee.in | D29: C-Suite | E29: x
A30: Administration | B30: jcadm@zupee.in | D30: Customer Experience | E30: x
A31: Data | B31: jcdata@zupee.in | D31: Chromebook VIP and Ticketing Team | E31: x
A32: Human Resources | B32: jchr@zupee.in | D32: ChromeBook OB Team | E32: x
A33: Strategy | B33: jcst@zupee.in | D33: Data | E33: x
A34: Digital Marketing | B34: jcdm@zupee.in | D34: Digital Marketing | E34: x
A35: Brand Marketing | B35: jcbm@zupee.in | D35: Finance | E35: x
A36: Finance | B36: jcfinance@zupee.in | D36: Founder's Office | E36: x
A37: IT Infra | B37: jcitinfra@zupee.in | D37: Head Of Department | E37: x
... A44: Vertical TV | B44: jc.vtv@zupee.in | D44: Public Policy | E44: x
A45: Nucanon | D45: Strategy | E45: x
D46: Technology | E46: x
D47: Vertical TV | E47: x
D48: Generic ID | E48: x
D49: No-2SV | E49: x
D50: TEST Environment | E50: x

Sheet On-Boarding
A1: Creation Date | B1: Full Name | C1: Office Email Address | D1: Department | E1: Acc Info | F1: Work Phone | G1: Employee Type | H1: Employee Title [Required] | I1: Manager Email [Required] | J1: Personal Email ID | K1: Remarks (If any) | L1: {={"No-Dues St"; IF(ISNA(VLOOKUP(C2:C1542, 'Off-Boarding'!B:B, 1, FALSE)), "", "No-Dues")}} -> No-Dues St
A2: 01-Jan-1111 | B2: Rohan Ray | C2: rohan.ray@zupee.in | D2: Strategy | E2: GWS | F2: 7022967608 | G2: Full Time | H2: Content Operations Associate | I2: chirag.sabhadiya@zupee.in | L2: No-Dues
A3: 01-Jan-1111 | B3: Aakash Pal | C3: aakash.pal@zupee.in | E3: GWS
A4: 01-Jan-1111 | B4: Aatmiy Tomar | C4: aatmiy.tomar@zupee.in | E4: GWS
A5: 01-Jan-1111 | B5: Aayushi Siddhi Bhatta | C5: aayushi.bhatta@zupee.in | E5: GWS
A6: 01-Jan-1111 | B6: Aayushi Sharma | C6: aayushi.sharma@zupee.in | E6: GWS
A7: 01-Jan-1111 | B7: Abhinav Magow | C7: abhinav.magow@zupee.in | E7: GWS
A8: 01-Jan-1111 | B8: Abhinav Srivastava | C8: abhinav.srivastava@zupee.in | E8: GWS
A9: 01-Jan-1111 | B9: Abhinav Venkat | C9: abhinav.venkat@zupee.in | E9: GWS
A10: 01-Jan-1111 | B10: Abhishek Aga | C10: abhishek.aga@zupee.in | E10: GWS
A11: 01-Jan-1111 | B11: Abhishek Anand | C11: abhishek.anand@zupee.in | E11: GWS
A12: 01-Jan-1111 | B12: Abhishek Chaudhary | C12: abhishek.chaudhary@zupee.in | E12: GWS
A13: 01-Jan-1111 | B13: Abhishek Kumar | C13: abhishek.kumar@zupee.in | E13: GWS
A14: 01-Jan-1111 | B14: Abhishek Maheshwari | C14: abhishek.maheshwari@zupee.in | E14: GWS
... A17: 01-Jan-1111 | B17: Abhishek Raj | C17: abhishek.raj@zupee.in | E17: GWS
A18: 01-Jan-1111 | B18: Abhishek Singh | C18: abhishek.singh@zupee.in | E18: GWS | L18: No-Dues
A19: 01-Jan-1111 | B19: Achla Vatsa | C19: achla.vatsa@zupee.in | E19: GWS
A20: 01-Jan-1111 | B20: Adesh Sharma | C20: adesh.sharma@zupee.in | E20: GWS | L20: No-Dues
A21: 01-Jan-1111 | B21: Aditya Ganguly | C21: aditya.ganguly@zupee.in | E21: GWS
A22: 01-Jan-1111 | B22: Aditya Garg | C22: aditya.garg@zupee.in | E22: GWS | L22: No-Dues
A23: 01-Jan-1111 | B23: Aditya Marda | C23: aditya.marda@zupee.in | E23: GWS | L23: No-Dues
A24: 01-Jan-1111 | B24: Advait Mulay - Intern | C24: advait.mulay@zupee.in | E24: GWS
A25: 01-Jan-1111 | B25: Afshan Akram | C25: afshan.akram@zupee.in | E25: GWS
A26: 01-Jan-1111 | B26: Ajayraj Singh - Intern | C26: ajayraj.singh@zupee.in | E26: GWS
A27: 01-Jan-1111 | B27: Ajinkya Sirohi | C27: ajinkya.sirohi@zupee.in | E27: GWS
A28: 01-Jan-1111 | B28: Ajitesh Mohanta | C28: ajitesh.mohanta@zupee.in | E28: GWS
A29: 01-Jan-1111 | B29: Akanksha Bhatia | C29: akanksha.bhatia@zupee.in | E29: GWS
A30: 01-Jan-1111 | B30: Akash Bisht | C30: akash.bisht@zupee.in | E30: GWS | L30: No-Dues
A31: 01-Jan-1111 | B31: Akash Chauhan | C31: akash.chauhan@zupee.in | E31: GWS
A32: 01-Jan-1111 | B32: Akhilesh Boppana | C32: akhilesh.boppana@zupee.in | E32: GWS
A33: 01-Jan-1111 | B33: Akshay Kumar | C33: akshay.kumar@zupee.in | E33: GWS
A34: 01-Jan-1111 | B34: Akshit Kumar | C34: akshit.kumar@zupee.in | E34: GWS | L34: No-Dues
A35: 01-Jan-1111 | B35: Aksshay Malaviya | C35: aksshay.malaviya@zupee.in | E35: GWS
A36: 01-Jan-1111 | B36: Alankrita Sharma | C36: alankrita.sharma@zupee.in | E36: GWS | L36: No-Dues
A37: 01-Jan-1111 | B37: Alok | C37: alok.mahor@zupee.in | E37: GWS
A38: 01-Jan-1111 | B38: Alok Singh | C38: alok.singh@zupee.in | E38: GWS
A39: 01-Jan-1111 | B39: Alpika Singh | C39: alpika.singh@zupee.in | E39: GWS | L39: No-Dues
A40: 01-Jan-1111 | B40: Aman Choudhury | C40: aman.choudhury@zupee.in | E40: GWS
A41: 01-Jan-1111 | B41: Aman Ludhwani | C41: aman.ludhwani@zupee.in | E41: GWS | L41: No-Dues
A42: 01-Jan-1111 | B42: Amit Arora | C42: amit.arora@zupee.in | E42: GWS
A43: 01-Jan-1111 | B43: Amit K | C43: amit.k@zupee.in | E43: GWS
A44: 01-Jan-1111 | B44: Amit Kumar | C44: amit.kumar@zupee.in | E44: GWS
A45: 01-Jan-1111 | B45: Amit Shukla | C45: amit.shukla@zupee.in | E45: GWS
A46: 01-Jan-1111 | B46: Amiya Panda | C46: amiya.panda@zupee.in | E46: GWS
A47: 01-Jan-1111 | B47: Amul | C47: amul.singh@zupee.in | E47: GWS
A48: 01-Jan-1111 | B48: Anais Kumar | C48: anais.kumar@zupee.in | E48: GWS
A49: 01-Jan-1111 | B49: Aneesh Garg | C49: aneesh.garg@zupee.in | E49: GWS
A50: 01-Jan-1111 | B50: Anil Meher | C50: anil.meher@zupee.in | E50: GWS
A51: 01-Jan-1111 | B51: Aniruddh Sharma | C51: aniruddha.sharma@zupee.in | E51: GWS
A52: 01-Jan-1111 | B52: Anish Choudhary | C52: anish.choudhary@zupee.in | E52: GWS | L52: No-Dues
A53: 01-Jan-1111 | B53: Anita Rane | C53: anita.rane@zupee.in | E53: GWS | L53: No-Dues
A54: 01-Jan-1111 | B54: Anjali | C54: anjali.rai@zupee.in | E54: GWS | L54: No-Dues
A55: 01-Jan-1111 | B55: Ankita Pradhan | C55: ankita.pradhan@zupee.in | E55: GWS
A56: 01-Jan-1111 | B56: Ankur Agarwal | C56: ankur.agarwal@zupee.in | E56: GWS
A57: 01-Jan-1111 | B57: Ankur Sharma | C57: ankur.sharma@zupee.in | E57: GWS | L57: No-Dues
A58: 01-Jan-1111 | B58: Anshu Satheesh | C58: anshu.satheesh@zupee.in | E58: GWS | L58: No-Dues
A59: 01-Jan-1111 | B59: Anubhav Mishra | C59: anubhav.mishra@zupee.in | E59: GWS
A60: 01-Jan-1111 | B60: Anuj Singh | C60: anuj.singh@zupee.in | E60: GWS
A61: 01-Jan-1111 | B61: anupam.‚Äãkushwah | C61: anupam.kushwah@zupee.in | E61: GWS | L61: No-Dues
A62: 01-Jan-1111 | B62: Anurag Dhandhi | C62: anurag.dhandhi@zupee.in | E62: GWS
A63: 01-Jan-1111 | B63: Anurag Shukla | C63: anurag.shukla@zupee.in | E63: GWS
A64: 01-Jan-1111 | B64: Anurag Pratap Singh | C64: anurag.singh@zupee.in | E64: GWS | L64: No-Dues
A65: 01-Jan-1111 | B65: Apoorv Bhargava | C65: apoorv.bhargava@zupee.in | E65: GWS
A66: 01-Jan-1111 | B66: Apoorv Kalia | C66: apoorv.kalia@zupee.in | E66: GWS
A67: 01-Jan-1111 | B67: Apurav Garg | C67: apurav.garg@zupee.in | E67: GWS
A68: 01-Jan-1111 | B68: Ara Avasthi | C68: ara.avasthi@zupee.in | E68: GWS
A69: 01-Jan-1111 | B69: Aral Avasthi | C69: aral.avasthi@zupee.in | E69: GWS
A70: 01-Jan-1111 | B70: Archit Kumar | C70: archit.kumar@zupee.in | E70: GWS
A71: 01-Jan-1111 | B71: Arjun Sankhala | C71: arjun.sankhala@zupee.in | E71: GWS
A72: 01-Jan-1111 | B72: Arpan Khosla | C72: arpan.khosla@zupee.in | E72: GWS
A73: 01-Jan-1111 | B73: Arpit Gulati | C73: arpit.gulati@zupee.in | E73: GWS
A74: 01-Jan-1111 | B74: Arpit Jain | C74: arpit.jain@zupee.in | E74: GWS
A75: 01-Jan-1111 | B75: Arshad Iqbal | C75: arshad.iqbal@zupee.in | E75: GWS | L75: No-Dues
A76: 01-Jan-1111 | B76: Arun Kumar | C76: arun.kumar2@zupee.in | E76: GWS
A77: 01-Jan-1111 | B77: Arun Rajaram | C77: arun.rajaram@zupee.in | E77: GWS | L77: No-Dues
A78: 01-Jan-1111 | B78: Arun Singh | C78: arun.singh@zupee.in | E78: GWS
A79: 01-Jan-1111 | B79: arvinder singla | C79: arvinder.singla@zupee.in | E79: GWS
A80: 01-Jan-1111 | B80: Arya Soni | C80: arya.soni@zupee.in | E80: GWS | L80: No-Dues
A81: 01-Jan-1111 | B81: aryan.bahl | C81: aryan.bahl@zupee.in | E81: GWS | L81: No-Dues
A82: 01-Jan-1111 | B82: Aryan Gupta | C82: aryan.gupta@zupee.in | E82: GWS | L82: No-Dues
A83: 01-Jan-1111 | B83: Aryan Mehta | C83: aryan.mehta@zupee.in | E83: GWS
A84: 01-Jan-1111 | B84: Ashish Chandra | C84: ashish.chandra@zupee.in | E84: GWS
A85: 01-Jan-1111 | B85: Ashmita Dwivedi | C85: ashmita.dwivedi@zupee.in | E85: GWS | L85: No-Dues
A86: 01-Jan-1111 | B86: Ashmita Jain | C86: ashmita.jain@zupee.in | E86: GWS
A87: 01-Jan-1111 | B87: Ashutosh Barthwal | C87: ashutosh.barthwal@zupee.in | E87: GWS
A88: 01-Jan-1111 | B88: Ashutosh Bharatwal | C88: ashutosh.bharatwal@zupee.in | E88: GWS
A89: 01-Jan-1111 | B89: Ashvani Kumar Yadav | C89: ashvani.kumar@zupee.in | E89: GWS | L89: No-Dues
A90: 01-Jan-1111 | B90: Ashwani Goyal | C90: ashwani.goyal@zupee.in | E90: GWS
A91: 01-Jan-1111 | B91: Ashwani Raja | C91: ashwani.raja@zupee.in | E91: GWS | L91: No-Dues
A92: 01-Jan-1111 | B92: Ashwani Rana | C92: ashwani.rana@zupee.in | E92: GWS | L92: No-Dues
A93: 01-Jan-1111 | B93: Ashwini Rana | C93: Ashwini.Rana@Zupee.in | E93: GWS
A94: 01-Jan-1111 | B94: Astha Yadav | C94: astha.yadav@zupee.in | E94: GWS
A95: 01-Jan-1111 | B95: Atique Firoz | C95: atique.firoz@zupee.in | E95: GWS | L95: No-Dues
A96: 01-Jan-1111 | B96: Avijit Sharma | C96: avijit.sharma@zupee.in | D96: Legal | E96: GWS | L96: No-Dues
A97: 01-Jan-1111 | B97: Avinash Srivastava | C97: avinash.srivastava@zupee.in | E97: GWS
A98: 01-Jan-1111 | B98: Aviral | C98: aviral.rastogi@zupee.in | E98: GWS | L98: No-Dues
A99: 01-Jan-1111 | B99: Avisha Singh | C99: avisha.singh@zupee.in | E99: GWS
A100: 01-Jan-1111 | B100: Ayasha Swain | C100: ayasha.swain@zupee.in | E100: GWS
A101: 01-Jan-1111 | B101: Ayush Gupta | C101: ayush.gupta@zupee.in | E101: GWS
A102: 01-Jan-1111 | B102: Ayush Kumar | C102: ayush.kumar@zupee.in | E102: GWS
...

Sheet Off-Boarding
A1: Accounts Info | C1: Last Working Info | E1: Users Access Info
A2: Full Name | B2: Email ID | C2: IT LWD Date | D2: Frm Keka LWD | E2: IT GWS St | F2: {={" Department"; IF(ISNA(VLOOKUP(B3:B829, 'On-Boarding'!C2:D829, 2, FALSE)), "", VLOOKUP(B3:B829, 'On-Boarding'!C2:D829, 2, FALSE))}} -> #REF! | G2: Acc & Mail's St | H2: GWS Status Details | I2: Slack | J2: O365 | K2: Jira | L2: New Rlc | M2: Adobe | N2: Bitbkt | O2: CRM DB | P2: Mtrx DB | Q2: Clvr Tap | R2: Assets | S2: Remarks | T2: {={"Days Overdue"; IF(C3:C829="", "", IF(TODAY() - C3:C829 > 30, "> 30 Days", "≤ 30 Days"))}} -> Days Overdue
A3: {=IFERROR(VLOOKUP(B3,{Lists!$H$4:$H829,Lists!$G$4:$G829},2,0),"")} -> Aditya Pawar | B3: aditya.pawar@zupee.in | C3: 1-Jan-1111 | D3: 1-Jan-1111 | E3: Suspend | G3: NOT_FOUND | H3: Mail does not exist in GWS | I3: ❌ | J3: ❌ | K3: ❌ | L3: ❌ | M3: ❌ | N3: ❌ | O3: ❌ | P3: ❌ | Q3: ❌ | T3: > 30 Days
A4: {=IFERROR(VLOOKUP(B4,{Lists!$H$4:$H829,Lists!$G$4:$G829},2,0),"")} -> Rohit Chhabra | B4: rohit.chhabra@zupee.in | C4: 1-Jan-1111 | D4: 1-Jan-1111 | E4: =VLOOKUP(B4,AT_Data!A:D,4,0) -> Revoked | G4: NOT_FOUND | H4: Mail does not exist in GWS | I4: ❌ | J4: ❌ | K4: ❌ | L4: ❌ | M4: ❌ | N4: ❌ | O4: ❌ | P4: ❌ | Q4: ❌ | S4: using By Hitesh Vats, appv by Raj on Slack | T4: > 30 Days
A5: Shristi Agrawal | B5: shristi.agrawal@zupee.in | C5: 45392 | E5: Suspend | G5: NOT_FOUND | H5: Mail does not exist in GWS | I5: ✅ | J5: ❌ | K5: ✅ | L5: ✅ | M5: ❌ | N5: ❌ | O5: ✅ | P5: ✅ | Q5: ✅ | T5: > 30 Days
A6: Abhishek Singh | B6: abhishek.singh@zupee.in | C6: 45393 | E6: Suspend | G6: NOT_FOUND | H6: Mail does not exist in GWS | I6: ✅ | J6: ✅ | K6: ❌ | L6: ❌ | M6: ❌ | N6: ❌ | O6: ✅ | P6: ❌ | Q6: ❌ | T6: > 30 Days
A7: Khushboo kushwah | B7: khushboo.kushwah@zupee.in | C7: 45394 | E7: Suspend | G7: NOT_FOUND | H7: Mail does not exist in GWS | I7: ❌ | J7: ❌ | K7: ❌ | L7: ❌ | M7: ❌ | N7: ❌ | O7: ✅ | P7: ✅ | Q7: ❌ | T7: > 30 Days
A8: Divya Wangoo | B8: divya.wangoo@zupee.in | C8: 45455 | E8: Suspend | G8: NOT_FOUND | H8: Mail does not exist in GWS | I8: ✅ | J8: ❌ | K8: ✅ | L8: ✅ | M8: ❌ | N8: ❌ | O8: ✅ | P8: ✅ | Q8: ✅ | T8: > 30 Days
A9: Soumyadip Deb | B9: soumyadip.deb@zupee.in | C9: 45484 | E9: Suspend | G9: NOT_FOUND | H9: Mail does not exist in GWS | I9: ✅ | J9: ✅ | K9: ✅ | L9: ❌ | M9: ❌ | N9: ❌ | O9: ❌ | P9: ❌ | Q9: ❌ | T9: > 30 Days
A10: Pankaj Sharma | B10: pankaj.sharma@zupee.in | C10: 45515 | E10: Suspend | G10: NOT_FOUND | H10: Mail does not exist in GWS | I10: ✅ | J10: ✅ | K10: ❌ | L10: ❌ | M10: ❌ | N10: ❌ | O10: ❌ | P10: ❌ | Q10: ❌ | T10: > 30 Days
A11: Anshu Satheesh | B11: anshu.satheesh@zupee.in | C11: 45515 | E11: Suspend | G11: NOT_FOUND | H11: Mail does not exist in GWS | I11: ✅ | J11: ✅ | K11: ❌ | L11: ❌ | M11: ❌ | N11: ❌ | O11: ❌ | P11: ❌ | Q11: ❌ | T11: > 30 Days
A12: Mehul Shah | B12: mehul.shah@zupee.in | C12: 45515 | E12: Suspend | G12: NOT_FOUND | H12: Mail does not exist in GWS | I12: ✅ | J12: ❌ | K12: ✅ | L12: ❌ | M12: ❌ | N12: ❌ | O12: ❌ | P12: ❌ | Q12: ❌ | T12: > 30 Days
A13: Rajashekhar Nari | B13: rajashekhar.nari@zupee.in | C13: 45554 | E13: Suspend | G13: NOT_FOUND | H13: Mail does not exist in GWS | I13: ✅ | J13: ❌ | K13: ✅ | L13: ❌ | M13: ❌ | N13: ❌ | O13: ❌ | P13: ❌ | Q13: ❌ | T13: > 30 Days
A14: Chandan Dwivedi | B14: chandan.dwivedi@zupee.in | C14: 45562 | E14: Suspend | G14: NOT_FOUND | H14: Mail does not exist in GWS | I14: ✅ | J14: ✅ | K14: ✅ | L14: ❌ | M14: ❌ | N14: ❌ | O14: ❌ | P14: ❌ | Q14: ❌ | T14: > 30 Days
A15: Mohit Bakshi | B15: Mohit.bakshi@zupee.in | C15: 45562 | E15: Suspend | G15: NOT_FOUND | H15: Mail does not exist in GWS | I15: ✅ | J15: ❌ | K15: ✅ | L15: ❌ | M15: ❌ | N15: ❌ | O15: ❌ | P15: ✅ | Q15: ❌ | T15: > 30 Days
A16: Ashmita Dwivedi | B16: Ashmita.Dwivedi@zupee.in | C16: 45565 | E16: Suspend | G16: NOT_FOUND | H16: Mail does not exist in GWS | I16: ✅ | J16: ❌ | K16: ✅ | L16: ❌ | M16: ❌ | N16: ❌ | O16: ✅ | P16: ❌ | Q16: ❌ | T16: > 30 Days
A17: Nidhi agarwal | B17: Nidhi.agarwal@zupee.in | C17: 45565 | E17: Suspend | G17: NOT_FOUND | H17: Mail does not exist in GWS | I17: ✅ | J17: ❌ | K17: #️⃣ | L17: ❌ | M17: ❌ | N17: ❌ | O17: ✅ | P17: ✅ | Q17: ❌ | S17: Jira, due to Admin Access | T17: > 30 Days
A18: Sundeep Sharma | B18: sundeep.sharma@zupee.in | C18: 45582 | E18: Suspend | G18: NOT_FOUND | H18: Mail does not exist in GWS | I18: ✅ | J18: ❌ | K18: ✅ | L18: ✅ | M18: ❌ | N18: ❌ | O18: ✅ | P18: ✅ | Q18: ✅ | T18: > 30 Days
A19: Samir Halder External | B19: samir.halder@zupee.in | C19: 45582 | E19: Suspend | G19: NOT_FOUND | H19: Mail does not exist in GWS | I19: ❌ | J19: ❌ | K19: ❌ | L19: ❌ | M19: ✅ | N19: ❌ | O19: ❌ | P19: ❌ | Q19: ❌ | T19: > 30 Days
A20: Prakash Vedvyas Acharya | B20: prakash.acharya@zupee.in | C20: 45586 | E20: Suspend | G20: NOT_FOUND | H20: Mail does not exist in GWS | I20: ✅ | J20: ❌ | K20: ❌ | L20: ❌ | M20: ❌ | N20: ❌ | O20: ❌ | P20: ❌ | Q20: ❌ | T20: > 30 Days
A21: Shubham Vishwakarma | B21: shubham.vishwakarma@zupee.in | C21: 45590 | E21: Suspend | G21: NOT_FOUND | H21: Mail does not exist in GWS | I21: ✅ | J21: ✅ | K21: ✅ | L21: ❌ | M21: ❌ | N21: ❌ | O21: ❌ | P21: ✅ | Q21: ❌ | T21: > 30 Days
A22: Harsh Mehta | B22: harsh.mehta@zupee.in | C22: 45591 | E22: Suspend | G22: NOT_FOUND | H22: Mail does not exist in GWS | I22: ✅ | J22: ✅ | K22: ❌ | L22: ❌ | M22: ❌ | N22: ❌ | O22: ❌ | P22: ❌ | Q22: ❌ | T22: > 30 Days
A23: Shreyansh Bengani | B23: shreyansh.bengani@zupee.in | C23: 45593 | E23: Suspend | G23: NOT_FOUND | H23: Mail does not exist in GWS | I23: ✅ | J23: ✅ | K23: ✅ | L23: ❌ | M23: ❌ | N23: ❌ | O23: ❌ | P23: ✅ | Q23: ❌ | T23: > 30 Days
A24: Nitin Kumar | B24: nitin.kumar@zupee.in | C24: 45594 | E24: Suspend | G24: NOT_FOUND | H24: Mail does not exist in GWS | I24: ❌ | J24: ❌ | K24: ❌ | L24: ❌ | M24: ❌ | N24: ❌ | O24: ❌ | P24: ❌ | Q24: ❌ | T24: > 30 Days
A25: Deepak Dahiya | B25: deepak.dahiya@zupee.in | C25: 45606 | E25: Suspend | G25: NOT_FOUND | H25: Mail does not exist in GWS | I25: ✅ | J25: ✅ | K25: ❌ | L25: ❌ | M25: ❌ | N25: ❌ | O25: ❌ | P25: ❌ | Q25: ❌ | T25: > 30 Days
A26: Shivangi | B26: shivangi.shivangi@zupee.in | C26: 45607 | E26: Suspend | G26: NOT_FOUND | H26: Mail does not exist in GWS | I26: ✅ | J26: ❌ | K26: ❌ | L26: ❌ | M26: ❌ | N26: ❌ | O26: ❌ | P26: ❌ | Q26: ✅ | T26: > 30 Days
A27: Anita Rane | B27: anita.rane@zupee.in | C27: 45610 | E27: Suspend | G27: NOT_FOUND | H27: Mail does not exist in GWS | I27: ✅ | J27: ❌ | K27: ❌ | L27: ❌ | M27: ❌ | N27: ❌ | O27: ❌ | P27: ❌ | Q27: ❌ | T27: > 30 Days
A28: Nikhil Jha | B28: nikhil.jha@zupee.in | C28: 45610 | E28: Suspend | G28: NOT_FOUND | H28: Mail does not exist in GWS | I28: ✅ | J28: ❌ | K28: ✅ | L28: ✅ | M28: ✅ | N28: ❌ | O28: ❌ | P28: ❌ | Q28: ❌ | T28: > 30 Days
A29: Anjali Rai | B29: anjali.rai@zupee.in | C29: 45614 | E29: Suspend | G29: NOT_FOUND | H29: Mail does not exist in GWS | I29: ✅ | J29: ✅ | K29: ❌ | L29: ❌ | M29: ❌ | N29: ❌ | O29: ✅ | P29: ❌ | Q29: ❌ | T29: > 30 Days
... A34: Sonam Rathore | B34: sonam.rathore@zupee.in | C34: 45625 | E34: Suspend | G34: NOT_FOUND | H34: Mail does not exist in GWS | I34: ✅ | J34: ✅ | K34: ✅ | L34: ✅ | M34: ❌ | N34: ❌ | O34: ❌ | P34: ✅ | Q34: ✅ | T34: > 30 Days
A35: Manav Mukesh Jain | B35: manav.jain@zupee.in | C35: 45625 | E35: =VLOOKUP(B35,AT_Data!A:D,4,0) -> Hold | F35: =VLOOKUP(B35,'On-Boarding'!C:D,2,0) -> Org | G35: SUSPENDED | H35: User is SUSPENDED | I35: ✅ | J35: ✅ | K35: ❌ | L35: ❌ | M35: ❌ | N35: ❌ | O35: ❌ | P35: ❌ | Q35: ✅ | T35: > 30 Days
A36: Varsha SK | B36: varsha.sk@zupee.in | C36: 45628 | E36: Suspend | G36: NOT_FOUND | H36: Mail does not exist in GWS | I36: ✅ | J36: ❌ | K36: ❌ | L36: ❌ | M36: ❌ | N36: ❌ | O36: ✅ | P36: ❌ | Q36: ❌ | T36: > 30 Days
A37: Akshit kumar | B37: Akshit.Kumar@zupee.in | C37: 45629 | E37: Suspend | G37: NOT_FOUND | H37: Mail does not exist in GWS | I37: ✅ | J37: ❌ | K37: ✅ | L37: ❌ | M37: ❌ | N37: ❌ | O37: ❌ | P37: ❌ | Q37: ❌ | T37: > 30 Days
A38: Rupam Das | B38: rupam.das@zupee.in | C38: 45630 | E38: Suspend | G38: NOT_FOUND | H38: Mail does not exist in GWS | I38: ✅ | J38: ✅ | K38: ✅ | L38: ❌ | M38: ❌ | N38: ❌ | O38: ❌ | P38: ✅ | Q38: ✅ | T38: > 30 Days
A39: Sonam Gupta | B39: sonam.gupta@zupee.in | C39: 45635 | E39: Suspend | G39: NOT_FOUND | H39: Mail does not exist in GWS | I39: ✅ | J39: ❌ | K39: ❌ | L39: ❌ | M39: ❌ | N39: ❌ | O39: ❌ | P39: ✅ | Q39: ✅ | T39: > 30 Days
A40: Neha Sharma | B40: neha.sharma@zupee.in | C40: 45639 | E40: Suspend | G40: NOT_FOUND | H40: Mail does not exist in GWS | I40: ✅ | J40: ❌ | K40: ✅ | L40: ❌ | M40: ❌ | N40: ❌ | O40: ❌ | P40: ❌ | Q40: ❌ | T40: > 30 Days
A41: Nishchay Singh | B41: nishchay.singh@zupee.in | C41: 45642 | E41: Suspend | G41: NOT_FOUND | H41: Mail does not exist in GWS | I41: ✅ | J41: ❌ | K41: ✅ | L41: ❌ | M41: ❌ | N41: ❌ | O41: ❌ | P41: ✅ | Q41: ✅ | T41: > 30 Days
A42: Aryan Gupta | B42: aryan.gupta@zupee.in | C42: 45646 | E42: Suspend | G42: NOT_FOUND | H42: Mail does not exist in GWS | I42: ✅ | J42: ❌ | K42: ✅ | L42: ❌ | M42: ❌ | N42: ❌ | O42: ❌ | P42: ❌ | Q42: ✅ | T42: > 30 Days
A43: Himanshu Grover | B43: himanshu.grover@zupee.in | C43: 45650 | E43: Suspend | G43: NOT_FOUND | H43: Mail does not exist in GWS | I43: ✅ | J43: ❌ | K43: ✅ | L43: ❌ | M43: ❌ | N43: ❌ | O43: ❌ | P43: ❌ | Q43: ✅ | T43: > 30 Days
A44: Yash Anand | B44: yash.anand@zupee.in | C44: 45650 | E44: Suspend | G44: NOT_FOUND | H44: Mail does not exist in GWS | I44: ✅ | J44: ❌ | K44: ✅ | L44: ❌ | M44: ❌ | N44: ❌ | O44: ❌ | P44: ❌ | Q44: ❌ | T44: > 30 Days
A45: Vasudev Yadav | B45: vasudev.yadav@zupee.in | C45: 45656 | E45: Suspend | G45: NOT_FOUND | H45: Mail does not exist in GWS | I45: ✅ | J45: ❌ | K45: ✅ | L45: ❌ | M45: ❌ | N45: ❌ | O45: ✅ | P45: ❌ | Q45: ❌ | T45: > 30 Days
A46: Ashwani Rana | B46: ashwani.rana@zupee.in | C46: 45657 | E46: Suspend | G46: NOT_FOUND | H46: Mail does not exist in GWS | I46: ✅ | J46: ✅ | K46: ❌ | L46: ❌ | M46: ❌ | N46: ❌ | O46: ❌ | P46: ❌ | Q46: ❌ | T46: > 30 Days
A47: Karan Bhyana | B47: Karan.Bhyana@zupee.in | C47: 45660 | E47: Suspend | G47: NOT_FOUND | H47: Mail does not exist in GWS | I47: ✅ | J47: ✅ | K47: ✅ | L47: ❌ | M47: ❌ | N47: ❌ | O47: ✅ | P47: ✅ | Q47: ❌ | T47: > 30 Days
... A52: Rajkumar Varier | B52: raj.varier@zupee.in | C52: 45670 | E52: Suspend | G52: NOT_FOUND | H52: Mail does not exist in GWS | I52: ✅ | J52: ❌ | K52: ❌ | L52: ❌ | M52: ❌ | N52: ❌ | O52: ❌ | P52: ❌ | Q52: ❌ | T52: > 30 Days
A53: Avijit Sharma | B53: avijit.sharma@zupee.in | C53: 45674 | E53: =VLOOKUP(B53,AT_Data!A:D,4,0) -> Hold | F53: =VLOOKUP(B53,'On-Boarding'!C:D,2,0) -> Legal | G53: SUSPENDED | H53: User is SUSPENDED | I53: ✅ | J53: ✅ | K53: ❌ | L53: ❌ | M53: ✅ | N53: ❌ | O53: ❌ | P53: ❌ | Q53: ❌ | T53: > 30 Days
A54: Alpika Singh | B54: alpika.singh@zupee.in | C54: 45674 | E54: Suspend | G54: NOT_FOUND | H54: Mail does not exist in GWS | I54: ✅ | J54: ❌ | K54: ✅ | L54: ❌ | M54: ✅ | N54: ❌ | O54: ❌ | P54: ❌ | Q54: ✅ | T54: > 30 Days
A55: Hemant Kumar | B55: hemant.kumar@zupee.in | C55: 45674 | E55: Suspend | G55: NOT_FOUND | H55: Mail does not exist in GWS | I55: ✅ | J55: ❌ | K55: ✅ | L55: ❌ | M55: ✅ | N55: ❌ | O55: ❌ | P55: ❌ | Q55: ❌ | T55: > 30 Days
A56: Samarth Udasin | B56: Samarth.Udasin@zupee.in | C56: 45688 | E56: Suspend | G56: NOT_FOUND | H56: Mail does not exist in GWS | I56: ✅ | J56: ✅ | K56: ❌ | L56: ❌ | M56: ❌ | N56: ❌ | O56: ❌ | P56: ❌ | Q56: ❌ | T56: > 30 Days
A57: saneesh maheshwari | B57: saneesh.maheshwari@zupee.in | C57: 45694 | E57: Suspend | G57: NOT_FOUND | H57: Mail does not exist in GWS | I57: ✅ | J57: ❌ | K57: ✅ | L57: ❌ | M57: ❌ | N57: ❌ | O57: ❌ | P57: ❌ | Q57: ❌ | T57: > 30 Days
A58: Ashvani kumar | B58: ashvani.kumar@zupee.in | C58: 45701 | E58: Suspend | G58: NOT_FOUND | H58: Mail does not exist in GWS | I58: ✅ | J58: ✅ | K58: ❌ | L58: ❌ | M58: ❌ | N58: ❌ | O58: ✅ | P58: ❌ | Q58: ❌ | T58: > 30 Days
A59: Saurabh Singh Yadav | B59: saurabh.yadav@zupee.in | C59: 45701 | E59: Suspend | G59: NOT_FOUND | H59: Mail does not exist in GWS | I59: ✅ | J59: ❌ | K59: ✅ | L59: ❌ | M59: ❌ | N59: ❌ | O59: ✅ | P59: ❌ | Q59: ❌ | T59: > 30 Days
A60: Aviral rastogi | B60: aviral.rastogi@zupee.in | C60: 45709 | E60: Suspend | G60: NOT_FOUND | H60: Mail does not exist in GWS | I60: ✅ | J60: ❌ | K60: ✅ | L60: ❌ | M60: ✅ | N60: ❌ | O60: ❌ | P60: ❌ | Q60: ❌ | T60: > 30 Days
A61: anish houdhary | B61: anish.choudhary@zupee.in | C61: 45714 | E61: Suspend | G61: NOT_FOUND | H61: Mail does not exist in GWS | I61: ✅ | J61: ❌ | K61: ✅ | L61: ❌ | M61: ❌ | N61: ❌ | O61: ❌ | P61: ❌ | Q61: ❌ | T61: > 30 Days
A62: Arun Rajaram | B62: arun.rajaram@zupee.in | C62: 45715 | E62: Suspend | G62: NOT_FOUND | H62: Mail does not exist in GWS | I62: ✅ | J62: ✅ | K62: ✅ | L62: ❌ | M62: ❌ | N62: ❌ | O62: ✅ | P62: ❌ | Q62: ✅ | T62: > 30 Days
A63: Yash Lamba | B63: Yash.lamba@zupee.in | C63: 45716 | E63: Suspend | G63: NOT_FOUND | H63: Mail does not exist in GWS | I63: ✅ | J63: ✅ | K63: ❌ | L63: ❌ | M63: ❌ | N63: ❌ | O63: ❌ | P63: ❌ | Q63: ❌ | T63: > 30 Days
A64: Anurag Pratap Singh | B64: Anurag.singh@zupee.in | C64: 45716 | E64: Suspend | G64: NOT_FOUND | H64: Mail does not exist in GWS | I64: ✅ | J64: ✅ | K64: ❌ | L64: ❌ | M64: ❌ | N64: ❌ | O64: ❌ | P64: ❌ | Q64: ❌ | T64: > 30 Days
A65: Hritik Wadhwa | B65: hritik.wadhwa@zupee.in | C65: 45716 | E65: Suspend | G65: NOT_FOUND | H65: Mail does not exist in GWS | I65: ✅ | J65: ✅ | K65: ✅ | L65: ✅ | M65: ❌ | N65: ❌ | O65: ❌ | P65: ✅ | Q65: ❌ | T65: > 30 Days
... A67: NIdhi kumari | B67: nidhi.kumari@zupee.in | C67: 45718 | E67: Suspend | G67: NOT_FOUND | H67: Mail does not exist in GWS | I67: ✅ | J67: ❌ | K67: ✅ | L67: ❌ | M67: ❌ | N67: ❌ | O67: ❌ | P67: ❌ | Q67: ❌ | T67: > 30 Days
A68: Prathamesh Gitesh Kurambhatti | B68: prathamesh.kurambhatti@zupee.in | C68: 45719 | E68: =VLOOKUP(B68,AT_Data!A:D,4,0) -> Hold | F68: =VLOOKUP(B68,'On-Boarding'!C:D,2,0) -> Org | G68: SUSPENDED | H68: User is SUSPENDED | I68: ✅ | J68: ✅ | K68: ❌ | L68: ❌ | M68: ❌ | N68: ❌ | O68: ❌ | P68: ❌ | Q68: ❌ | T68: > 30 Days
A69: Aditya Marda | B69: aditya.marda@zupee.in | C69: 45721 | E69: Suspend | G69: NOT_FOUND | H69: Mail does not exist in GWS | I69: ✅ | J69: ✅ | K69: ❌ | L69: ✅ | M69: ❌ | N69: ❌ | O69: ❌ | P69: ❌ | Q69: ❌ | T69: > 30 Days
A70: Robin Achankunju | B70: robin.achankunju@zupee.in | C70: 45723 | E70: Suspend | G70: NOT_FOUND | H70: Mail does not exist in GWS | I70: ✅ | J70: ❌ | K70: ❌ | L70: ❌ | M70: ❌ | N70: ❌ | O70: ✅ | P70: ✅ | Q70: ❌ | T70: > 30 Days
A71: Garima Prakash | B71: garima.prakash@zupee.in | C71: 45727 | E71: Suspend | G71: NOT_FOUND | H71: Mail does not exist in GWS | I71: ✅ | J71: ✅ | K71: ❌ | L71: ❌ | M71: ❌ | N71: ❌ | O71: ❌ | P71: ❌ | Q71: ❌ | T71: > 30 Days
A72: anupam kushwah | B72: anupam.kushwah@zupee.in | C72: 45733 | E72: Suspend | G72: NOT_FOUND | H72: Mail does not exist in GWS | I72: ✅ | J72: ❌ | K72: ❌ | L72: ❌ | M72: ❌ | N72: ❌ | O72: ❌ | P72: ❌ | Q72: ❌ | T72: > 30 Days
A73: Hemail askary | B73: hemail.askary@zupee.in | C73: 45736 | E73: Suspend | G73: NOT_FOUND | H73: Mail does not exist in GWS | I73: ✅ | J73: ✅ | K73: ✅ | L73: ❌ | M73: ❌ | N73: ❌ | O73: ❌ | P73: ❌ | Q73: ❌ | T73: > 30 Days
A74: Sumit Kumar | B74: sumit.k@zupee.in | C74: 45736 | E74: Suspend | G74: NOT_FOUND | H74: Mail does not exist in GWS | I74: ✅ | J74: ❌ | K74: ✅ | L74: ❌ | M74: ❌ | N74: ❌ | O74: ✅ | P74: ❌ | Q74: ❌ | T74: > 30 Days
A75: Vinoth R | B75: vinoth.r@zupee.in | C75: 45737 | E75: Suspend | G75: NOT_FOUND | H75: Mail does not exist in GWS | I75: ✅ | J75: ✅ | K75: ✅ | L75: ✅ | M75: ❌ | N75: ❌ | O75: ✅ | P75: ✅ | Q75: ✅ | T75: > 30 Days
A76: pushpushkar mourya | B76: pushkar.mourya@zupee.in | C76: 45741 | E76: Suspend | G76: NOT_FOUND | H76: Mail does not exist in GWS | I76: ✅ | J76: ❌ | K76: ✅ | L76: ❌ | M76: ❌ | N76: ❌ | O76: ❌ | P76: ❌ | Q76: ❌ | T76: > 30 Days
A77: Arya Soni | B77: arya.soni@zupee.in | C77: 45744 | E77: Suspend | G77: NOT_FOUND | H77: Mail does not exist in GWS | I77: ✅ | J77: ❌ | K77: ✅ | L77: ❌ | M77: ❌ | N77: ❌ | O77: ❌ | P77: ❌ | Q77: ❌ | T77: > 30 Days
A78: prashant pundir | B78: prashant.pundir@zupee.in | C78: 45748 | E78: Suspend | G78: NOT_FOUND | H78: Mail does not exist in GWS | I78: ✅ | J78: ❌ | K78: ✅ | L78: ❌ | M78: ❌ | N78: ❌ | O78: ❌ | P78: ❌ | Q78: ❌ | T78: > 30 Days
A79: puneet dhiman | B79: puneet.dhiman@zupee.in | C79: 45754 | E79: Suspend | G79: NOT_FOUND | H79: Mail does not exist in GWS | I79: ✅ | J79: ✅ | K79: ✅ | L79: ❌ | M79: ❌ | N79: ❌ | O79: ❌ | P79: ❌ | Q79: ❌ | T79: > 30 Days
A80: Dakshita Sharma | B80: dakshita.sharma@zupee.in | C80: 45758 | E80: Suspend | G80: NOT_FOUND | H80: Mail does not exist in GWS | I80: ✅ | J80: ❌ | K80: ❌ | L80: ❌ | M80: ✅ | N80: ❌ | O80: ❌ | P80: ❌ | Q80: ❌ | T80: > 30 Days
... A151: Preeti Singh | B151: preeti.singh@zupee.in | C151: 45879 | E151: Suspend | G151: NOT_FOUND | H151: Mail does not exist in GWS | I151: ✅ | J151: ❌ | K151: ❌ | L151: ❌ | M151: ❌ | N151: ❌ | O151: ❌ | P151: ❌ | Q151: ❌ | T151: > 30 Days
A152: Nishant Tripathi | B152: nishant.tripathi@zupee.in | C152: 45880 | E152: =VLOOKUP(B152,AT_Data!A:D,4,0) -> Hold | F152: =VLOOKUP(B152,'On-Boarding'!C:D,2,0) -> Org | G152: SUSPENDED | H152: User is SUSPENDED | I152: ✅ | J152: ❌ | K152: ✅ | L152: ❌ | M152: ❌ | N152: ❌ | O152: ❌ | P152: ❌ | Q152: ❌ | T152: > 30 Days
A153: Vedant Sharma | B153: vedant.sharma@zupee.in | C153: 45883 | E153: Suspend | G153: NOT_FOUND | H153: Mail does not exist in GWS | I153: ✅ | J153: ✅ | K153: ❌ | L153: ❌ | M153: ❌ | N153: ❌ | O153: ❌ | P153: ✅ | Q153: ❌ | T153: > 30 Days
A154: Manjot Juyal | B154: manjot.juyal@zupee.in | C154: 45883 | E154: Suspend | G154: NOT_FOUND | H154: Mail does not exist in GWS | I154: ✅ | J154: ✅ | K154: ❌ | L154: ❌ | M154: ❌ | N154: ❌ | O154: ❌ | P154: ❌ | Q154: ❌ | T154: > 30 Days
A155: Nikita Mantri | B155: nikita.mantri@zupee.in | C155: 45883 | E155: Suspend | G155: NOT_FOUND | H155: Mail does not exist in GWS | I155: ✅ | J155: ✅ | K155: ✅ | L155: ❌ | M155: ❌ | N155: ❌ | O155: ❌ | P155: ✅ | Q155: ❌ | T155: > 30 Days
A156: Vedaant Magow | B156: vedaant.magow@zupee.in | C156: 45883 | E156: Suspend | G156: NOT_FOUND | H156: Mail does not exist in GWS | I156: ✅ | J156: ❌ | K156: ✅ | L156: ❌ | M156: ❌ | N156: ❌ | O156: ❌ | P156: ❌ | Q156: ❌ | T156: > 30 Days
A157: Deepankar Rao | B157: deepankar.rao@zupee.in | C157: 45891 | E157: Suspend | G157: NOT_FOUND | H157: Mail does not exist in GWS | I157: ✅ | J157: ✅ | K157: ✅ | L157: ❌ | M157: ❌ | N157: ❌ | O157: ❌ | P157: ❌ | Q157: ❌ | T157: > 30 Days
A158: Ashutosh Wadhwani | B158: ashutosh.wadhwani@zupee.in | C158: 45891 | E158: Suspend | G158: NOT_FOUND | H158: Mail does not exist in GWS | I158: ✅ | J158: ❌ | K158: ❌ | L158: ❌ | M158: ❌ | N158: ❌ | O158: ❌ | P158: ❌ | Q158: ❌ | S158: Exit date delay shared by HR | T158: > 30 Days
A159: Pritesh Kumar | B159: pritesh.kumar@zupee.in | C159: 45891 | E159: Suspend | G159: NOT_FOUND | H159: Mail does not exist in GWS | I159: ✅ | J159: ❌ | K159: ✅ | L159: ❌ | M159: ❌ | N159: ❌ | O159: ❌ | P159: ❌ | Q159: ❌ | S159: Exit date delay shared by HR | T159: > 30 Days
A160: Suraj Negi | B160: suraj.negi@zupee.in | C160: 45891 | E160: Suspend | G160: NOT_FOUND | H160: Mail does not exist in GWS | I160: ✅ | J160: ❌ | K160: ✅ | L160: ❌ | M160: ❌ | N160: ❌ | O160: ❌ | P160: ❌ | Q160: ❌ | S160: Exit date delay shared by HR | T160: > 30 Days
A161: Pankaj Rana | B161: pankaj.rana@zupee.in | C161: 45891 | E161: Suspend | G161: NOT_FOUND | H161: Mail does not exist in GWS | I161: ✅ | J161: ❌ | K161: ✅ | L161: ❌ | M161: ❌ | N161: ❌ | O161: ❌ | P161: ❌ | Q161: ❌ | S161: Exit date delay shared by HR | T161: > 30 Days
A162: Srishty Gagneja | B162: srishty.gagneja@zupee.in | C162: 45894 | E162: Suspend | G162: NOT_FOUND | H162: Mail does not exist in GWS | I162: ✅ | J162: ❌ | K162: ❌ | L162: ❌ | M162: ❌ | N162: ❌ | O162: ❌ | P162: ❌ | Q162: ❌ | T162: > 30 Days
A163: Rashmi Navle | B163: rashmi.navale@zupee.in | C163: 45894 | E163: Suspend | G163: NOT_FOUND | H163: Mail does not exist in GWS | I163: ✅ | J163: ❌ | K163: ✅ | L163: ❌ | M163: ❌ | N163: ❌ | O163: ❌ | P163: ❌ | Q163: ❌ | T163: > 30 Days
A164: MD Neyaz | B164: md.neyaz@zupee.in | C164: 45894 | E164: Suspend | G164: NOT_FOUND | H164: Mail does not exist in GWS | I164: ✅ | J164: ❌ | K164: ✅ | L164: ❌ | M164: ❌ | N164: ❌ | O164: ❌ | P164: ❌ | Q164: ❌ | T164: > 30 Days
A165: Shivani Patni | B165: shivani.patil@zupee.in | C165: 45894 | E165: Suspend | G165: NOT_FOUND | H165: Mail does not exist in GWS | I165: ✅ | J165: ❌ | K165: ✅ | L165: ❌ | M165: ❌ | N165: ❌ | O165: ❌ | P165: ❌ | Q165: ❌ | T165: > 30 Days
A166: Mohit Kumar | B166: mohit.kumar@zupee.in | C166: 45894 | E166: Suspend | G166: NOT_FOUND | H166: Mail does not exist in GWS | I166: ✅ | J166: ❌ | K166: ✅ | L166: ❌ | M166: ❌ | N166: ❌ | O166: ❌ | P166: ✅ | Q166: ❌ | T166: > 30 Days
A167: Deepak Kumar | B167: deepak.kumar@zupee.in | C167: 45894 | E167: Suspend | G167: NOT_FOUND | H167: Mail does not exist in GWS | I167: ✅ | J167: ❌ | K167: ❌ | L167: ❌ | M167: ❌ | N167: ❌ | O167: ❌ | P167: ❌ | Q167: ❌ | T167: > 30 Days
A168: Abhishek Dharmman | B168: abhishek.dharmman@zupee.in | C168: 45894 | E168: Suspend | G168: NOT_FOUND | H168: Mail does not exist in GWS | I168: ✅ | J168: ❌ | K168: ✅ | L168: ❌ | M168: ❌ | N168: ❌ | O168: ✅ | P168: ✅ | Q168: ❌ | T168: > 30 Days
A169: Vivek Sharma | B169: vivek.sharma1@zupee.in | C169: 45894 | E169: Suspend | G169: NOT_FOUND | H169: Mail does not exist in GWS | I169: ✅ | J169: ❌ | K169: ✅ | L169: ❌ | M169: ❌ | N169: ❌ | O169: ❌ | P169: ❌ | Q169: ❌ | T169: > 30 Days
A170: KS Chetan | B170: ks.chetan@zupee.in | C170: 45894 | E170: Suspend | G170: NOT_FOUND | H170: Mail does not exist in GWS | I170: ✅ | J170: ❌ | K170: ✅ | L170: ❌ | M170: ❌ | N170: ❌ | O170: ❌ | P170: ❌ | Q170: ❌ | T170: > 30 Days
A171: Sheshant Sinha | B171: sheshant.sinha@zupee.in | C171: 45894 | E171: Suspend | G171: NOT_FOUND | H171: Mail does not exist in GWS | I171: ✅ | J171: ❌ | K171: ✅ | L171: ✅ | M171: ❌ | N171: ❌ | O171: ✅ | P171: ✅ | Q171: ❌ | T171: > 30 Days
A172: Pragya Singh | B172: pragya.singh@zupee.in | C172: 45894 | E172: Suspend | G172: NOT_FOUND | H172: Mail does not exist in GWS | I172: ✅ | J172: ❌ | K172: ✅ | L172: ❌ | M172: ❌ | N172: ❌ | O172: ❌ | P172: ❌ | Q172: ❌ | S172: Exit date delay shared by HR | T172: > 30 Days
A173: Shubham Khosla | B173: shubham.khosla@zupee.in | C173: 45894 | E173: Suspend | G173: NOT_FOUND | H173: Mail does not exist in GWS | I173: ✅ | J173: ❌ | K173: ✅ | L173: ❌ | M173: ❌ | N173: ❌ | O173: ❌ | P173: ✅ | Q173: ✅ | T173: > 30 Days
A174: Baljinder Kaur | B174: baljinder.kaur@zupee.in | C174: 45895 | E174: Suspend | G174: NOT_FOUND | H174: Mail does not exist in GWS | I174: ✅ | J174: ❌ | K174: ✅ | L174: ✅ | M174: ❌ | N174: ❌ | O174: ✅ | P174: ❌ | Q174: ✅ | T174: > 30 Days
A175: Vipin Kumar | B175: Vipin.Yadav@zupee.in | C175: 45895 | E175: Suspend | G175: NOT_FOUND | H175: Mail does not exist in GWS | I175: ✅ | J175: ❌ | K175: ✅ | L175: ❌ | M175: ❌ | N175: ❌ | O175: ❌ | P175: ❌ | Q175: ❌ | S175: Exit date delay shared by HR | T175: > 30 Days
A176: Rishav Bansal | B176: rishav.bansal@zupee.in | C176: 45896 | E176: Suspend | G176: NOT_FOUND | H176: Mail does not exist in GWS | I176: ✅ | J176: ❌ | K176: ✅ | L176: ❌ | M176: ❌ | N176: ❌ | O176: ❌ | P176: ❌ | Q176: ❌ | T176: > 30 Days
A177: Abhishek Saxena | B177: abhishek.saxena@zupee.in | C177: 45898 | E177: Suspend | G177: NOT_FOUND | H177: Mail does not exist in GWS | I177: ✅ | J177: ❌ | K177: ✅ | L177: ❌ | M177: ❌ | N177: ❌ | O177: ❌ | P177: ❌ | Q177: ❌ | T177: > 30 Days
A178: Sushmita Kannadi | B178: sushmita.kannadi@zupee.in | C178: 45898 | E178: Suspend | G178: NOT_FOUND | H178: Mail does not exist in GWS | I178: ✅ | J178: ❌ | K178: ❌ | L178: ❌ | M178: ❌ | N178: ❌ | O178: ✅ | P178: ❌ | Q178: ❌ | T178: > 30 Days
A179: Khushank Tayal | B179: khushank.tayal@zupee.in | C179: 45898 | E179: Suspend | G179: NOT_FOUND | H179: Mail does not exist in GWS | I179: ✅ | J179: ❌ | K179: ✅ | L179: ❌ | M179: ❌ | N179: ❌ | O179: ❌ | P179: ❌ | Q179: ❌ | T179: > 30 Days
...

Sheet Join & Induc By HR
B1: CANDIDATE DETAILS
A2: =IFERROR(__xludf.DUMMYFUNCTION("QUERY(IMPORTRANGE(""1xFrklApkRqApw6hS49w9Le1ELcHrQ5f2FJdiVs8ztHg"", ""Joining & Induction Tracker!A:Z""), ""SELECT Col10, Col1, Col3, Col5, Col2, Col4, Col6, Col7, Col9, Col12, Col13, Col14, Col25, Col26"") ")," Probable Date of Joining") -> Probable Date of Joining | B2: =IFERROR(__xludf.DUMMYFUNCTION("""COMPUTED_VALUE""")," Name") -> Name | C2: =IFERROR(__xludf.DUMMYFUNCTION("""COMPUTED_VALUE""")," Department") -> Department | D2: =IFERROR(__xludf.DUMMYFUNCTION("""COMPUTED_VALUE""")," Contact Number") -> Contact Number | E2: =IFERROR(__xludf.DUMMYFUNCTION("""COMPUTED_VALUE"""),"CANDIDATE DETAILS Designation") -> CANDIDATE DETAILS Designation | F2: =IFERROR(__xludf.DUMMYFUNCTION("""COMPUTED_VALUE""")," Sub Department ") -> Sub Department | G2: =IFERROR(__xludf.DUMMYFUNCTION("""COMPUTED_VALUE""")," Personal Email ID") -> Personal Email ID | H2: =IFERROR(__xludf.DUMMYFUNCTION("""COMPUTED_VALUE""")," Reporting Manager") -> Reporting Manager | I2: =IFERROR(__xludf.DUMMYFUNCTION("""COMPUTED_VALUE""")," Date of Offer Release") -> Date of Offer Release | J2: =IFERROR(__xludf.DUMMYFUNCTION("""COMPUTED_VALUE""")," Recruiter Name") -> Recruiter Name | K2: =IFERROR(__xludf.DUMMYFUNCTION("""COMPUTED_VALUE""")," Offer Status") -> Offer Status | L2: =IFERROR(__xludf.DUMMYFUNCTION("""COMPUTED_VALUE""")," Induction Type") -> Induction Type | M2: =IFERROR(__xludf.DUMMYFUNCTION("""COMPUTED_VALUE"""),"To be Filled by IT Team Email ID") -> To be Filled by IT Team Email ID | N2: =IFERROR(__xludf.DUMMYFUNCTION("""COMPUTED_VALUE""")," Laptop Allocated Serial Number") -> Laptop Allocated Serial Number
A3: =IFERROR(__xludf.DUMMYFUNCTION("""COMPUTED_VALUE"""),45170.0) -> 45170 | B3: =IFERROR(__xludf.DUMMYFUNCTION("""COMPUTED_VALUE"""),"Shikhar Varshney") -> Shikhar Varshney | C3: =IFERROR(__xludf.DUMMYFUNCTION("""COMPUTED_VALUE"""),"Corporate") -> Corporate | D3: =IFERROR(__xludf.DUMMYFUNCTION("""COMPUTED_VALUE"""),8.449159038E9) -> 8449159038 | E3: =IFERROR(__xludf.DUMMYFUNCTION("""COMPUTED_VALUE"""),"Market Research Intern") -> Market Research Intern | F3: =IFERROR(__xludf.DUMMYFUNCTION("""COMPUTED_VALUE"""),"Strategy") -> Strategy | G3: =IFERROR(__xludf.DUMMYFUNCTION("""COMPUTED_VALUE""")," shikharvarshney03@gmail.com") -> shikharvarshney03@gmail.com | H3: =IFERROR(__xludf.DUMMYFUNCTION("""COMPUTED_VALUE"""),"Nishchay Singh ") -> Nishchay Singh | I3: =IFERROR(__xludf.DUMMYFUNCTION("""COMPUTED_VALUE"""),45167.0) -> 45167 | J3: =IFERROR(__xludf.DUMMYFUNCTION("""COMPUTED_VALUE"""),"Naina") -> Naina | K3: =IFERROR(__xludf.DUMMYFUNCTION("""COMPUTED_VALUE"""),"Joined") -> Joined | L3: =IFERROR(__xludf.DUMMYFUNCTION("""COMPUTED_VALUE"""),"In Office") -> In Office | M3: =IFERROR(__xludf.DUMMYFUNCTION("""COMPUTED_VALUE"""),"shikhar.varshney@zupee.in") -> shikhar.varshney@zupee.in
A4: =IFERROR(__xludf.DUMMYFUNCTION("""COMPUTED_VALUE"""),45173.0) -> 45173 | B4: =IFERROR(__xludf.DUMMYFUNCTION("""COMPUTED_VALUE"""),"Shaurya Upadhyay") -> Shaurya Upadhyay | C4: =IFERROR(__xludf.DUMMYFUNCTION("""COMPUTED_VALUE"""),"Technology") -> Technology | D4: =IFERROR(__xludf.DUMMYFUNCTION("""COMPUTED_VALUE"""),9.818418781E9) -> 9818418781 | E4: =IFERROR(__xludf.DUMMYFUNCTION("""COMPUTED_VALUE"""),"Security Engineer Trainee") -> Security Engineer Trainee | F4: =IFERROR(__xludf.DUMMYFUNCTION("""COMPUTED_VALUE"""),"Engineering") -> Engineering | G4: =IFERROR(__xludf.DUMMYFUNCTION("""COMPUTED_VALUE"""),"shauryaupadhyay59@gmail.com ") -> shauryaupadhyay59@gmail.com | H4: =IFERROR(__xludf.DUMMYFUNCTION("""COMPUTED_VALUE"""),"Shreyansh Bengani") -> Shreyansh Bengani | J4: =IFERROR(__xludf.DUMMYFUNCTION("""COMPUTED_VALUE"""),"Mamta Pandey") -> Mamta Pandey | K4: =IFERROR(__xludf.DUMMYFUNCTION("""COMPUTED_VALUE"""),"Joined") -> Joined | L4: =IFERROR(__xludf.DUMMYFUNCTION("""COMPUTED_VALUE"""),"In Office") -> In Office | M4: =IFERROR(__xludf.DUMMYFUNCTION("""COMPUTED_VALUE"""),"shaurya.upadhyay@zupee.in") -> shaurya.upadhyay@zupee.in
A5: =IFERROR(__xludf.DUMMYFUNCTION("""COMPUTED_VALUE"""),45174.0) -> 45174 | B5: =IFERROR(__xludf.DUMMYFUNCTION("""COMPUTED_VALUE"""),"Nikunj Aggarwal") -> Nikunj Aggarwal | C5: =IFERROR(__xludf.DUMMYFUNCTION("""COMPUTED_VALUE"""),"Technology") -> Technology | D5: =IFERROR(__xludf.DUMMYFUNCTION("""COMPUTED_VALUE"""),9.810210616E9) -> 9810210616 | E5: =IFERROR(__xludf.DUMMYFUNCTION("""COMPUTED_VALUE"""),"Software Engineer - Android") -> Software Engineer - Android | F5: =IFERROR(__xludf.DUMMYFUNCTION("""COMPUTED_VALUE"""),"Engineering") -> Engineering | G5: =IFERROR(__xludf.DUMMYFUNCTION("""COMPUTED_VALUE"""),"annikunjagg@gmail.com") -> annikunjagg@gmail.com | H5: =IFERROR(__xludf.DUMMYFUNCTION("""COMPUTED_VALUE"""),"Anshul Mittal") -> Anshul Mittal | I5: =IFERROR(__xludf.DUMMYFUNCTION("""COMPUTED_VALUE"""),45163.0) -> 45163 | J5: =IFERROR(__xludf.DUMMYFUNCTION("""COMPUTED_VALUE"""),"Naina") -> Naina | K5: =IFERROR(__xludf.DUMMYFUNCTION("""COMPUTED_VALUE"""),"Joined") -> Joined | L5: =IFERROR(__xludf.DUMMYFUNCTION("""COMPUTED_VALUE"""),"In Office") -> In Office | M5: =IFERROR(__xludf.DUMMYFUNCTION("""COMPUTED_VALUE"""),"nikunj.aggarwal@zupee.in") -> nikunj.aggarwal@zupee.in
A6: =IFERROR(__xludf.DUMMYFUNCTION("""COMPUTED_VALUE"""),45182.0) -> 45182 | B6: =IFERROR(__xludf.DUMMYFUNCTION("""COMPUTED_VALUE"""),"Rakesh Kumar") -> Rakesh Kumar | C6: =IFERROR(__xludf.DUMMYFUNCTION("""COMPUTED_VALUE"""),"Corporate") -> Corporate | D6: =IFERROR(__xludf.DUMMYFUNCTION("""COMPUTED_VALUE"""),7.999002836E9) -> 7999002836 | E6: =IFERROR(__xludf.DUMMYFUNCTION("""COMPUTED_VALUE"""),"IT Executive") -> IT Executive | F6: =IFERROR(__xludf.DUMMYFUNCTION("""COMPUTED_VALUE"""),"Administration") -> Administration | G6: =IFERROR(__xludf.DUMMYFUNCTION("""COMPUTED_VALUE"""),"rakeshkumarrk35386@gmail.com") -> rakeshkumarrk35386@gmail.com | H6: =IFERROR(__xludf.DUMMYFUNCTION("""COMPUTED_VALUE"""),"Naveen Kumar") -> Naveen Kumar | J6: =IFERROR(__xludf.DUMMYFUNCTION("""COMPUTED_VALUE"""),"Mamta Pandey") -> Mamta Pandey | K6: =IFERROR(__xludf.DUMMYFUNCTION("""COMPUTED_VALUE"""),"Joined") -> Joined | L6: =IFERROR(__xludf.DUMMYFUNCTION("""COMPUTED_VALUE"""),"In Office") -> In Office | M6: =IFERROR(__xludf.DUMMYFUNCTION("""COMPUTED_VALUE"""),"rakesh.kumar@zupee.in") -> rakesh.kumar@zupee.in | N6: =IFERROR(__xludf.DUMMYFUNCTION("""COMPUTED_VALUE"""),"JZV7VQ3") -> JZV7VQ3
A7: =IFERROR(__xludf.DUMMYFUNCTION("""COMPUTED_VALUE"""),45189.0) -> 45189 | B7: =IFERROR(__xludf.DUMMYFUNCTION("""COMPUTED_VALUE"""),"Tushar Sharma") -> Tushar Sharma | C7: =IFERROR(__xludf.DUMMYFUNCTION("""COMPUTED_VALUE"""),"Corporate") -> Corporate | D7: =IFERROR(__xludf.DUMMYFUNCTION("""COMPUTED_VALUE"""),8.851799414E9) -> 8851799414 | E7: =IFERROR(__xludf.DUMMYFUNCTION("""COMPUTED_VALUE"""),"Senior Finance Executive") -> Senior Finance Executive | F7: =IFERROR(__xludf.DUMMYFUNCTION("""COMPUTED_VALUE"""),"Finance") -> Finance | G7: =IFERROR(__xludf.DUMMYFUNCTION("""COMPUTED_VALUE"""),"Tushar2419@yahoo.com") -> Tushar2419@yahoo.com | H7: =IFERROR(__xludf.DUMMYFUNCTION("""COMPUTED_VALUE"""),"Hitesh Vats") -> Hitesh Vats | J7: =IFERROR(__xludf.DUMMYFUNCTION("""COMPUTED_VALUE"""),"Nidhi Khedekar") -> Nidhi Khedekar | K7: =IFERROR(__xludf.DUMMYFUNCTION("""COMPUTED_VALUE"""),"Joined") -> Joined | L7: =IFERROR(__xludf.DUMMYFUNCTION("""COMPUTED_VALUE"""),"In Office") -> In Office | M7: =IFERROR(__xludf.DUMMYFUNCTION("""COMPUTED_VALUE"""),"tushar.sharma@zupee.in") -> tushar.sharma@zupee.in
A8: =IFERROR(__xludf.DUMMYFUNCTION("""COMPUTED_VALUE"""),45202.0) -> 45202 | B8: =IFERROR(__xludf.DUMMYFUNCTION("""COMPUTED_VALUE"""),"Ashvani Kumar") -> Ashvani Kumar | C8: =IFERROR(__xludf.DUMMYFUNCTION("""COMPUTED_VALUE"""),"Customer Experience") -> Customer Experience | D8: =IFERROR(__xludf.DUMMYFUNCTION("""COMPUTED_VALUE"""),9.149230623E9) -> 9149230623 | E8: =IFERROR(__xludf.DUMMYFUNCTION("""COMPUTED_VALUE"""),"Fraud Analyst") -> Fraud Analyst | F8: =IFERROR(__xludf.DUMMYFUNCTION("""COMPUTED_VALUE"""),"Fraud Risk Management ") -> Fraud Risk Management | G8: =IFERROR(__xludf.DUMMYFUNCTION("""COMPUTED_VALUE"""),"ashvanikumar180210@gmail.com") -> ashvanikumar180210@gmail.com | H8: =IFERROR(__xludf.DUMMYFUNCTION("""COMPUTED_VALUE"""),"Aman Khare") -> Aman Khare | J8: =IFERROR(__xludf.DUMMYFUNCTION("""COMPUTED_VALUE"""),"Nidhi Khedekar") -> Nidhi Khedekar | K8: =IFERROR(__xludf.DUMMYFUNCTION("""COMPUTED_VALUE"""),"Joined") -> Joined | L8: =IFERROR(__xludf.DUMMYFUNCTION("""COMPUTED_VALUE"""),"In Office") -> In Office
A9: =IFERROR(__xludf.DUMMYFUNCTION("""COMPUTED_VALUE"""),45203.0) -> 45203 | B9: =IFERROR(__xludf.DUMMYFUNCTION("""COMPUTED_VALUE"""),"Rahul Bhatia") -> Rahul Bhatia | C9: =IFERROR(__xludf.DUMMYFUNCTION("""COMPUTED_VALUE"""),"Corporate") -> Corporate | D9: =IFERROR(__xludf.DUMMYFUNCTION("""COMPUTED_VALUE"""),9.2682085E9) -> 9268208500 | E9: =IFERROR(__xludf.DUMMYFUNCTION("""COMPUTED_VALUE"""),"Senior Finance Executive") -> Senior Finance Executive | F9: =IFERROR(__xludf.DUMMYFUNCTION("""COMPUTED_VALUE"""),"Finance") -> Finance | G9: =IFERROR(__xludf.DUMMYFUNCTION("""COMPUTED_VALUE"""),"rahul13bhatia@gmail.com") -> rahul13bhatia@gmail.com | H9: =IFERROR(__xludf.DUMMYFUNCTION("""COMPUTED_VALUE"""),"Sunil Gupta") -> Sunil Gupta | I9: =IFERROR(__xludf.DUMMYFUNCTION("""COMPUTED_VALUE"""),45147.0) -> 45147 | J9: =IFERROR(__xludf.DUMMYFUNCTION("""COMPUTED_VALUE"""),"Nidhi Khedekar") -> Nidhi Khedekar | K9: =IFERROR(__xludf.DUMMYFUNCTION("""COMPUTED_VALUE"""),"Offer Revoked") -> Offer Revoked | L9: =IFERROR(__xludf.DUMMYFUNCTION("""COMPUTED_VALUE"""),"Drop Out") -> Drop Out
A10: =IFERROR(__xludf.DUMMYFUNCTION("""COMPUTED_VALUE"""),45215.0) -> 45215 | B10: =IFERROR(__xludf.DUMMYFUNCTION("""COMPUTED_VALUE"""),"Amit Singh") -> Amit Singh | C10: =IFERROR(__xludf.DUMMYFUNCTION("""COMPUTED_VALUE"""),"Technology") -> Technology | D10: =IFERROR(__xludf.DUMMYFUNCTION("""COMPUTED_VALUE"""),9.711112881E9) -> 9711112881 | E10: =IFERROR(__xludf.DUMMYFUNCTION("""COMPUTED_VALUE"""),"Senior Staff Engineer") -> Senior Staff Engineer | F10: =IFERROR(__xludf.DUMMYFUNCTION("""COMPUTED_VALUE"""),"Engineering") -> Engineering | G10: =IFERROR(__xludf.DUMMYFUNCTION("""COMPUTED_VALUE"""),"amitabesit@gmail.com") -> amitabesit@gmail.com | H10: =IFERROR(__xludf.DUMMYFUNCTION("""COMPUTED_VALUE"""),"Ranjeet Kumar") -> Ranjeet Kumar | I10: =IFERROR(__xludf.DUMMYFUNCTION("""COMPUTED_VALUE"""),45211.0) -> 45211 | J10: =IFERROR(__xludf.DUMMYFUNCTION("""COMPUTED_VALUE"""),"Rajneesh Yadav") -> Rajneesh Yadav | K10: =IFERROR(__xludf.DUMMYFUNCTION("""COMPUTED_VALUE"""),"Joined") -> Joined | L10: =IFERROR(__xludf.DUMMYFUNCTION("""COMPUTED_VALUE"""),"In Office") -> In Office | M10: =IFERROR(__xludf.DUMMYFUNCTION("""COMPUTED_VALUE"""),"amit.singh@zupee.in") -> amit.singh@zupee.in | N10: =IFERROR(__xludf.DUMMYFUNCTION("""COMPUTED_VALUE"""),"VYCVM29T75") -> VYCVM29T75
A11: =IFERROR(__xludf.DUMMYFUNCTION("""COMPUTED_VALUE"""),45215.0) -> 45215 | B11: =IFERROR(__xludf.DUMMYFUNCTION("""COMPUTED_VALUE"""),"Manmohan Sagar") -> Manmohan Sagar | C11: =IFERROR(__xludf.DUMMYFUNCTION("""COMPUTED_VALUE"""),"Finance") -> Finance | D11: =IFERROR(__xludf.DUMMYFUNCTION("""COMPUTED_VALUE"""),8.800739621E9) -> 8800739621 | E11: =IFERROR(__xludf.DUMMYFUNCTION("""COMPUTED_VALUE"""),"Senior Executive- Finance") -> Senior Executive- Finance | F11: =IFERROR(__xludf.DUMMYFUNCTION("""COMPUTED_VALUE"""),"Finance") -> Finance | G11: =IFERROR(__xludf.DUMMYFUNCTION("""COMPUTED_VALUE"""),"Manmohansagar97@gmail.com") -> Manmohansagar97@gmail.com | H11: =IFERROR(__xludf.DUMMYFUNCTION("""COMPUTED_VALUE"""),"Vikas Gupta") -> Vikas Gupta | J11: =IFERROR(__xludf.DUMMYFUNCTION("""COMPUTED_VALUE"""),"Nidhi Khedekar") -> Nidhi Khedekar | K11: =IFERROR(__xludf.DUMMYFUNCTION("""COMPUTED_VALUE"""),"Joined") -> Joined | L11: =IFERROR(__xludf.DUMMYFUNCTION("""COMPUTED_VALUE"""),"In Office") -> In Office | M11: =IFERROR(__xludf.DUMMYFUNCTION("""COMPUTED_VALUE"""),"manmohan.sagar@zupee.in") -> manmohan.sagar@zupee.in | N11: =IFERROR(__xludf.DUMMYFUNCTION("""COMPUTED_VALUE"""),"8J9FCY3") -> 8J9FCY3
A12: =IFERROR(__xludf.DUMMYFUNCTION("""COMPUTED_VALUE"""),45217.0) -> 45217 | B12: =IFERROR(__xludf.DUMMYFUNCTION("""COMPUTED_VALUE"""),"Pratik Taltia") -> Pratik Taltia | C12: =IFERROR(__xludf.DUMMYFUNCTION("""COMPUTED_VALUE"""),"Marketing") -> Marketing | D12: =IFERROR(__xludf.DUMMYFUNCTION("""COMPUTED_VALUE"""),7.358433457E9) -> 7358433457 | E12: =IFERROR(__xludf.DUMMYFUNCTION("""COMPUTED_VALUE"""),"Product Marketing Executive") -> Product Marketing Executive | F12: =IFERROR(__xludf.DUMMYFUNCTION("""COMPUTED_VALUE"""),"Digital Marketing") -> Digital Marketing | G12: =IFERROR(__xludf.DUMMYFUNCTION("""COMPUTED_VALUE"""),"pratiktaltia.a@gmail.com") -> pratiktaltia.a@gmail.com | H12: =IFERROR(__xludf.DUMMYFUNCTION("""COMPUTED_VALUE"""),"Aditya Jha") -> Aditya Jha | J12: =IFERROR(__xludf.DUMMYFUNCTION("""COMPUTED_VALUE"""),"Nidhi Khedekar") -> Nidhi Khedekar | K12: =IFERROR(__xludf.DUMMYFUNCTION("""COMPUTED_VALUE"""),"Joined") -> Joined | L12: =IFERROR(__xludf.DUMMYFUNCTION("""COMPUTED_VALUE"""),"In Office") -> In Office | M12: =IFERROR(__xludf.DUMMYFUNCTION("""COMPUTED_VALUE"""),"pratik.taltia@zupee.in") -> pratik.taltia@zupee.in | N12: =IFERROR(__xludf.DUMMYFUNCTION("""COMPUTED_VALUE"""),"KG667421QL") -> KG667421QL
A13: =IFERROR(__xludf.DUMMYFUNCTION("""COMPUTED_VALUE"""),45222.0) -> 45222 | B13: =IFERROR(__xludf.DUMMYFUNCTION("""COMPUTED_VALUE"""),"Awadhesh Singh Tanwar") -> Awadhesh Singh Tanwar | C13: =IFERROR(__xludf.DUMMYFUNCTION("""COMPUTED_VALUE"""),"Technology") -> Technology | D13: =IFERROR(__xludf.DUMMYFUNCTION("""COMPUTED_VALUE"""),9.479456993E9) -> 9479456993 | E13: =IFERROR(__xludf.DUMMYFUNCTION("""COMPUTED_VALUE"""),"Senior Data Engineer") -> Senior Data Engineer | F13: =IFERROR(__xludf.DUMMYFUNCTION("""COMPUTED_VALUE"""),"Data Engineering") -> Data Engineering | G13: =IFERROR(__xludf.DUMMYFUNCTION("""COMPUTED_VALUE"""),"dapst8@gmail.com") -> dapst8@gmail.com | H13: =IFERROR(__xludf.DUMMYFUNCTION("""COMPUTED_VALUE"""),"Aman Bahl") -> Aman Bahl | I13: =IFERROR(__xludf.DUMMYFUNCTION("""COMPUTED_VALUE"""),45129.0) -> 45129 | J13: =IFERROR(__xludf.DUMMYFUNCTION("""COMPUTED_VALUE"""),"Nidhi Khedekar") -> Nidhi Khedekar | K13: =IFERROR(__xludf.DUMMYFUNCTION("""COMPUTED_VALUE"""),"Offer Declined") -> Offer Declined | L13: =IFERROR(__xludf.DUMMYFUNCTION("""COMPUTED_VALUE"""),"In Office") -> In Office
A14: =IFERROR(__xludf.DUMMYFUNCTION("""COMPUTED_VALUE"""),45237.0) -> 45237 | B14: =IFERROR(__xludf.DUMMYFUNCTION("""COMPUTED_VALUE"""),"Pradeep Agrawal") -> Pradeep Agrawal | C14: =IFERROR(__xludf.DUMMYFUNCTION("""COMPUTED_VALUE"""),"Technology") -> Technology | D14: =IFERROR(__xludf.DUMMYFUNCTION("""COMPUTED_VALUE"""),9.782015101E9) -> 9782015101 | E14: =IFERROR(__xludf.DUMMYFUNCTION("""COMPUTED_VALUE"""),"Lead Data Engineer") -> Lead Data Engineer | F14: =IFERROR(__xludf.DUMMYFUNCTION("""COMPUTED_VALUE"""),"Data Engineering") -> Data Engineering | G14: =IFERROR(__xludf.DUMMYFUNCTION("""COMPUTED_VALUE"""),"pradeepagrawalan1994@gmail.com") -> pradeepagrawalan1994@gmail.com | H14: =IFERROR(__xludf.DUMMYFUNCTION("""COMPUTED_VALUE"""),"Aman Bahl") -> Aman Bahl | J14: =IFERROR(__xludf.DUMMYFUNCTION("""COMPUTED_VALUE"""),"Naina") -> Naina | K14: =IFERROR(__xludf.DUMMYFUNCTION("""COMPUTED_VALUE"""),"Joined") -> Joined | L14: =IFERROR(__xludf.DUMMYFUNCTION("""COMPUTED_VALUE"""),"In Office") -> In Office | M14: =IFERROR(__xludf.DUMMYFUNCTION("""COMPUTED_VALUE"""),"pradeep.agrawal@zupee.in") -> pradeep.agrawal@zupee.in
A15: =IFERROR(__xludf.DUMMYFUNCTION("""COMPUTED_VALUE"""),45265.0) -> 45265 | B15: =IFERROR(__xludf.DUMMYFUNCTION("""COMPUTED_VALUE"""),"Abhishek Goyal") -> Abhishek Goyal | C15: =IFERROR(__xludf.DUMMYFUNCTION("""COMPUTED_VALUE"""),"Product") -> Product | D15: =IFERROR(__xludf.DUMMYFUNCTION("""COMPUTED_VALUE"""),7.974831301E9) -> 7974831301 | E15: =IFERROR(__xludf.DUMMYFUNCTION("""COMPUTED_VALUE"""),"Manager - Strategy") -> Manager - Strategy | F15: =IFERROR(__xludf.DUMMYFUNCTION("""COMPUTED_VALUE"""),"Strategy") -> Strategy | G15: =IFERROR(__xludf.DUMMYFUNCTION("""COMPUTED_VALUE"""),"goyal.abhishek28@gmail.com") -> goyal.abhishek28@gmail.com | H15: =IFERROR(__xludf.DUMMYFUNCTION("""COMPUTED_VALUE"""),"Ishank Mehta") -> Ishank Mehta | J15: =IFERROR(__xludf.DUMMYFUNCTION("""COMPUTED_VALUE"""),"Naina") -> Naina | K15: =IFERROR(__xludf.DUMMYFUNCTION("""COMPUTED_VALUE"""),"Joined") -> Joined | L15: =IFERROR(__xludf.DUMMYFUNCTION("""COMPUTED_VALUE"""),"In Office") -> In Office | M15: =IFERROR(__xludf.DUMMYFUNCTION("""COMPUTED_VALUE"""),"abhishek.goyal@zupee.in") -> abhishek.goyal@zupee.in | N15: =IFERROR(__xludf.DUMMYFUNCTION("""COMPUTED_VALUE"""),"GY1HHJ5H96") -> GY1HHJ5H96
A16: =IFERROR(__xludf.DUMMYFUNCTION("""COMPUTED_VALUE"""),45236.0) -> 45236 | B16: =IFERROR(__xludf.DUMMYFUNCTION("""COMPUTED_VALUE"""),"Sujoy Ghosh") -> Sujoy Ghosh | C16: =IFERROR(__xludf.DUMMYFUNCTION("""COMPUTED_VALUE"""),"Product") -> Product | D16: =IFERROR(__xludf.DUMMYFUNCTION("""COMPUTED_VALUE"""),9.739922559E9) -> 9739922559 | E16: =IFERROR(__xludf.DUMMYFUNCTION("""COMPUTED_VALUE"""),"Associate Director- Products") -> Associate Director- Products | F16: =IFERROR(__xludf.DUMMYFUNCTION("""COMPUTED_VALUE"""),"Product") -> Product | G16: =IFERROR(__xludf.DUMMYFUNCTION("""COMPUTED_VALUE"""),"suzoyy@gmail.com") -> suzoyy@gmail.com | H16: =IFERROR(__xludf.DUMMYFUNCTION("""COMPUTED_VALUE"""),"Naveen Kadyan") -> Naveen Kadyan | I16: =IFERROR(__xludf.DUMMYFUNCTION("""COMPUTED_VALUE"""),45218.0) -> 45218 | J16: =IFERROR(__xludf.DUMMYFUNCTION("""COMPUTED_VALUE"""),"M Sangeetha") -> M Sangeetha | K16: =IFERROR(__xludf.DUMMYFUNCTION("""COMPUTED_VALUE"""),"Joined") -> Joined | L16: =IFERROR(__xludf.DUMMYFUNCTION("""COMPUTED_VALUE"""),"In Office") -> In Office | M16: =IFERROR(__xludf.DUMMYFUNCTION("""COMPUTED_VALUE"""),"sujoy.ghosh@zupee.in") -> sujoy.ghosh@zupee.in
A17: =IFERROR(__xludf.DUMMYFUNCTION("""COMPUTED_VALUE"""),45236.0) -> 45236 | B17: =IFERROR(__xludf.DUMMYFUNCTION("""COMPUTED_VALUE"""),"Sanket Jain") -> Sanket Jain | C17: =IFERROR(__xludf.DUMMYFUNCTION("""COMPUTED_VALUE"""),"Product") -> Product | D17: =IFERROR(__xludf.DUMMYFUNCTION("""COMPUTED_VALUE"""),9.818953844E9) -> 9818953844 | E17: =IFERROR(__xludf.DUMMYFUNCTION("""COMPUTED_VALUE"""),"Manager - Strategy") -> Manager - Strategy | F17: =IFERROR(__xludf.DUMMYFUNCTION("""COMPUTED_VALUE"""),"Strategy") -> Strategy | G17: =IFERROR(__xludf.DUMMYFUNCTION("""COMPUTED_VALUE"""),"jain.sanket93@gmail.com") -> jain.sanket93@gmail.com | H17: =IFERROR(__xludf.DUMMYFUNCTION("""COMPUTED_VALUE"""),"Ishank Mehta") -> Ishank Mehta | J17: =IFERROR(__xludf.DUMMYFUNCTION("""COMPUTED_VALUE"""),"Naina") -> Naina | K17: =IFERROR(__xludf.DUMMYFUNCTION("""COMPUTED_VALUE"""),"Joined") -> Joined | L17: =IFERROR(__xludf.DUMMYFUNCTION("""COMPUTED_VALUE"""),"In Office") -> In Office | M17: =IFERROR(__xludf.DUMMYFUNCTION("""COMPUTED_VALUE"""),"sanket.jain@zupee.in") -> sanket.jain@zupee.in
A18: =IFERROR(__xludf.DUMMYFUNCTION("""COMPUTED_VALUE"""),45268.0) -> 45268 | B18: =IFERROR(__xludf.DUMMYFUNCTION("""COMPUTED_VALUE"""),"Mohit Singh Rathore") -> Mohit Singh Rathore | C18: =IFERROR(__xludf.DUMMYFUNCTION("""COMPUTED_VALUE"""),"Technology") -> Technology | D18: =IFERROR(__xludf.DUMMYFUNCTION("""COMPUTED_VALUE"""),7.410851411E9) -> 7410851411 | E18: =IFERROR(__xludf.DUMMYFUNCTION("""COMPUTED_VALUE"""),"Software Engineer") -> Software Engineer | F18: =IFERROR(__xludf.DUMMYFUNCTION("""COMPUTED_VALUE"""),"Backend") -> Backend | G18: =IFERROR(__xludf.DUMMYFUNCTION("""COMPUTED_VALUE"""),"singhrathoremohit@gmail.com") -> singhrathoremohit@gmail.com | H18: =IFERROR(__xludf.DUMMYFUNCTION("""COMPUTED_VALUE"""),"Piyush Shukla") -> Piyush Shukla | I18: =IFERROR(__xludf.DUMMYFUNCTION("""COMPUTED_VALUE"""),45222.0) -> 45222 | J18: =IFERROR(__xludf.DUMMYFUNCTION("""COMPUTED_VALUE"""),"Nidhi Khedekar") -> Nidhi Khedekar | K18: =IFERROR(__xludf.DUMMYFUNCTION("""COMPUTED_VALUE"""),"Joined") -> Joined | L18: =IFERROR(__xludf.DUMMYFUNCTION("""COMPUTED_VALUE"""),"In Office") -> In Office | M18: =IFERROR(__xludf.DUMMYFUNCTION("""COMPUTED_VALUE"""),"mohit.rathore@zupee.in") -> mohit.rathore@zupee.in | N18: =IFERROR(__xludf.DUMMYFUNCTION("""COMPUTED_VALUE"""),"D44FP97T0W") -> D44FP97T0W
A19: =IFERROR(__xludf.DUMMYFUNCTION("""COMPUTED_VALUE"""),45246.0) -> 45246 | B19: =IFERROR(__xludf.DUMMYFUNCTION("""COMPUTED_VALUE"""),"Shrasti Tomar") -> Shrasti Tomar | C19: =IFERROR(__xludf.DUMMYFUNCTION("""COMPUTED_VALUE"""),"Technology") -> Technology | D19: =IFERROR(__xludf.DUMMYFUNCTION("""COMPUTED_VALUE"""),9.71171279E9) -> 9711712790 | E19: =IFERROR(__xludf.DUMMYFUNCTION("""COMPUTED_VALUE"""),"Data Engineer") -> Data Engineer | F19: =IFERROR(__xludf.DUMMYFUNCTION("""COMPUTED_VALUE"""),"Data Engineering") -> Data Engineering | G19: =IFERROR(__xludf.DUMMYFUNCTION("""COMPUTED_VALUE"""),"shrastitomar123@gmail.com") -> shrastitomar123@gmail.com | H19: =IFERROR(__xludf.DUMMYFUNCTION("""COMPUTED_VALUE"""),"Aman Bahl") -> Aman Bahl | I19: =IFERROR(__xludf.DUMMYFUNCTION("""COMPUTED_VALUE"""),45229.0) -> 45229 | J19: =IFERROR(__xludf.DUMMYFUNCTION("""COMPUTED_VALUE"""),"Nidhi Khedekar") -> Nidhi Khedekar | K19: =IFERROR(__xludf.DUMMYFUNCTION("""COMPUTED_VALUE"""),"Joined") -> Joined | L19: =IFERROR(__xludf.DUMMYFUNCTION("""COMPUTED_VALUE"""),"In Office") -> In Office | M19: =IFERROR(__xludf.DUMMYFUNCTION("""COMPUTED_VALUE"""),"shrasti.tomar@zupee.in") -> shrasti.tomar@zupee.in | N19: =IFERROR(__xludf.DUMMYFUNCTION("""COMPUTED_VALUE"""),"M99FNLWVCF") -> M99FNLWVCF
A20: =IFERROR(__xludf.DUMMYFUNCTION("""COMPUTED_VALUE"""),45316.0) -> 45316 | B20: =IFERROR(__xludf.DUMMYFUNCTION("""COMPUTED_VALUE"""),"Sumit Chugh") -> Sumit Chugh | C20: =IFERROR(__xludf.DUMMYFUNCTION("""COMPUTED_VALUE"""),"Finance") -> Finance | D20: =IFERROR(__xludf.DUMMYFUNCTION("""COMPUTED_VALUE"""),9.811538749E9) -> 9811538749 | E20: =IFERROR(__xludf.DUMMYFUNCTION("""COMPUTED_VALUE"""),"Head of Finance") -> Head of Finance | F20: =IFERROR(__xludf.DUMMYFUNCTION("""COMPUTED_VALUE"""),"Finance") -> Finance | G20: =IFERROR(__xludf.DUMMYFUNCTION("""COMPUTED_VALUE"""),"sumitchugh81@gmail.com") -> sumitchugh81@gmail.com | H20: =IFERROR(__xludf.DUMMYFUNCTION("""COMPUTED_VALUE"""),"Dilsher Malhi") -> Dilsher Malhi | I20: =IFERROR(__xludf.DUMMYFUNCTION("""COMPUTED_VALUE"""),45224.0) -> 45224 | J20: =IFERROR(__xludf.DUMMYFUNCTION("""COMPUTED_VALUE"""),"M Sangeetha") -> M Sangeetha | K20: =IFERROR(__xludf.DUMMYFUNCTION("""COMPUTED_VALUE"""),"Joined") -> Joined | L20: =IFERROR(__xludf.DUMMYFUNCTION("""COMPUTED_VALUE"""),"In Office") -> In Office
A21: =IFERROR(__xludf.DUMMYFUNCTION("""COMPUTED_VALUE"""),45252.0) -> 45252 | B21: =IFERROR(__xludf.DUMMYFUNCTION("""COMPUTED_VALUE"""),"Kumar Shivam") -> Kumar Shivam | C21: =IFERROR(__xludf.DUMMYFUNCTION("""COMPUTED_VALUE"""),"Analytics") -> Analytics | D21: =IFERROR(__xludf.DUMMYFUNCTION("""COMPUTED_VALUE"""),9.471621193E9) -> 9471621193 | E21: =IFERROR(__xludf.DUMMYFUNCTION("""COMPUTED_VALUE"""),"Data Analyst") -> Data Analyst | F21: =IFERROR(__xludf.DUMMYFUNCTION("""COMPUTED_VALUE"""),"Product Analytics") -> Product Analytics | G21: =IFERROR(__xludf.DUMMYFUNCTION("""COMPUTED_VALUE"""),"kumarshivamdsdl@gmail.com") -> kumarshivamdsdl@gmail.com | H21: =IFERROR(__xludf.DUMMYFUNCTION("""COMPUTED_VALUE"""),"Shwetank Anand") -> Shwetank Anand | I21: =IFERROR(__xludf.DUMMYFUNCTION("""COMPUTED_VALUE"""),45222.0) -> 45222 | J21: =IFERROR(__xludf.DUMMYFUNCTION("""COMPUTED_VALUE"""),"Mamta Pandey") -> Mamta Pandey | K21: =IFERROR(__xludf.DUMMYFUNCTION("""COMPUTED_VALUE"""),"Offer Declined") -> Offer Declined | L21: =IFERROR(__xludf.DUMMYFUNCTION("""COMPUTED_VALUE"""),"In Office") -> In Office
A22: =IFERROR(__xludf.DUMMYFUNCTION("""COMPUTED_VALUE"""),45272.0) -> 45272 | B22: =IFERROR(__xludf.DUMMYFUNCTION("""COMPUTED_VALUE"""),"Rajkumar Singh") -> Rajkumar Singh | C22: =IFERROR(__xludf.DUMMYFUNCTION("""COMPUTED_VALUE"""),"Corporate") -> Corporate | D22: =IFERROR(__xludf.DUMMYFUNCTION("""COMPUTED_VALUE"""),8.285299131E9) -> 8285299131 | E22: =IFERROR(__xludf.DUMMYFUNCTION("""COMPUTED_VALUE"""),"Manager- IT Administration") -> Manager- IT Administration | F22: =IFERROR(__xludf.DUMMYFUNCTION("""COMPUTED_VALUE"""),"Administration") -> Administration | G22: =IFERROR(__xludf.DUMMYFUNCTION("""COMPUTED_VALUE"""),"rajdainy@gmail.com") -> rajdainy@gmail.com | H22: =IFERROR(__xludf.DUMMYFUNCTION("""COMPUTED_VALUE"""),"Gaurav Sharma") -> Gaurav Sharma | I22: =IFERROR(__xludf.DUMMYFUNCTION("""COMPUTED_VALUE"""),45210.0) -> 45210 | J22: =IFERROR(__xludf.DUMMYFUNCTION("""COMPUTED_VALUE"""),"Mamta Pandey") -> Mamta Pandey | K22: =IFERROR(__xludf.DUMMYFUNCTION("""COMPUTED_VALUE"""),"Joined") -> Joined | L22: =IFERROR(__xludf.DUMMYFUNCTION("""COMPUTED_VALUE"""),"In Office") -> In Office | M22: =IFERROR(__xludf.DUMMYFUNCTION("""COMPUTED_VALUE"""),"rajkumar.singh@zupee.in") -> rajkumar.singh@zupee.in | N22: =IFERROR(__xludf.DUMMYFUNCTION("""COMPUTED_VALUE"""),"DPMV3N3") -> DPMV3N3
A23: =IFERROR(__xludf.DUMMYFUNCTION("""COMPUTED_VALUE"""),45253.0) -> 45253 | B23: =IFERROR(__xludf.DUMMYFUNCTION("""COMPUTED_VALUE"""),"Prateek Jain") -> Prateek Jain | C23: =IFERROR(__xludf.DUMMYFUNCTION("""COMPUTED_VALUE"""),"Technology") -> Technology | D23: =IFERROR(__xludf.DUMMYFUNCTION("""COMPUTED_VALUE"""),9.910763107E9) -> 9910763107 | E23: =IFERROR(__xludf.DUMMYFUNCTION("""COMPUTED_VALUE"""),"Staff Engineer") -> Staff Engineer | F23: =IFERROR(__xludf.DUMMYFUNCTION("""COMPUTED_VALUE"""),"Engineering") -> Engineering | G23: =IFERROR(__xludf.DUMMYFUNCTION("""COMPUTED_VALUE"""),"prateekj201@gmail.com") -> prateekj201@gmail.com | H23: =IFERROR(__xludf.DUMMYFUNCTION("""COMPUTED_VALUE"""),"Saurav Yadav") -> Saurav Yadav | I23: =IFERROR(__xludf.DUMMYFUNCTION("""COMPUTED_VALUE"""),45240.0) -> 45240 | J23: =IFERROR(__xludf.DUMMYFUNCTION("""COMPUTED_VALUE"""),"Rajneesh Yadav") -> Rajneesh Yadav | K23: =IFERROR(__xludf.DUMMYFUNCTION("""COMPUTED_VALUE"""),"Joined") -> Joined | L23: =IFERROR(__xludf.DUMMYFUNCTION("""COMPUTED_VALUE"""),"In Office") -> In Office | M23: =IFERROR(__xludf.DUMMYFUNCTION("""COMPUTED_VALUE"""),"prateek.jain@zupee.in") -> prateek.jain@zupee.in
A24: =IFERROR(__xludf.DUMMYFUNCTION("""COMPUTED_VALUE"""),45258.0) -> 45258 | B24: =IFERROR(__xludf.DUMMYFUNCTION("""COMPUTED_VALUE"""),"Satyam Jaiswal") -> Satyam Jaiswal | C24: =IFERROR(__xludf.DUMMYFUNCTION("""COMPUTED_VALUE"""),"Technology") -> Technology | D24: =IFERROR(__xludf.DUMMYFUNCTION("""COMPUTED_VALUE"""),7.318358838E9) -> 7318358838 | E24: =IFERROR(__xludf.DUMMYFUNCTION("""COMPUTED_VALUE"""),"Quality Assurance Engineer- 1") -> Quality Assurance Engineer- 1 | F24: =IFERROR(__xludf.DUMMYFUNCTION("""COMPUTED_VALUE"""),"Quality") -> Quality | G24: =IFERROR(__xludf.DUMMYFUNCTION("""COMPUTED_VALUE"""),"satyamjaiswal8828@gmail.com") -> satyamjaiswal8828@gmail.com | H24: =IFERROR(__xludf.DUMMYFUNCTION("""COMPUTED_VALUE"""),"Sahil Puri") -> Sahil Puri | I24: =IFERROR(__xludf.DUMMYFUNCTION("""COMPUTED_VALUE"""),45251.0) -> 45251 | J24: =IFERROR(__xludf.DUMMYFUNCTION("""COMPUTED_VALUE"""),"Mamta Pandey") -> Mamta Pandey | K24: =IFERROR(__xludf.DUMMYFUNCTION("""COMPUTED_VALUE"""),"Joined") -> Joined | L24: =IFERROR(__xludf.DUMMYFUNCTION("""COMPUTED_VALUE"""),"In Office") -> In Office | M24: =IFERROR(__xludf.DUMMYFUNCTION("""COMPUTED_VALUE"""),"satyam.jaiswal@zupee.in") -> satyam.jaiswal@zupee.in | N24: =IFERROR(__xludf.DUMMYFUNCTION("""COMPUTED_VALUE"""),"KD4V9Y5L9R") -> KD4V9Y5L9R
A25: =IFERROR(__xludf.DUMMYFUNCTION("""COMPUTED_VALUE"""),45261.0) -> 45261 | B25: =IFERROR(__xludf.DUMMYFUNCTION("""COMPUTED_VALUE"""),"Tushar Rajendra Patil") -> Tushar Rajendra Patil | C25: =IFERROR(__xludf.DUMMYFUNCTION("""COMPUTED_VALUE"""),"Technology") -> Technology | E25: =IFERROR(__xludf.DUMMYFUNCTION("""COMPUTED_VALUE"""),"Machine Learning Engineer") -> Machine Learning Engineer | F25: =IFERROR(__xludf.DUMMYFUNCTION("""COMPUTED_VALUE"""),"Data Science") -> Data Science | G25: =IFERROR(__xludf.DUMMYFUNCTION("""COMPUTED_VALUE"""),"tusharpatil487@gmail.com") -> tusharpatil487@gmail.com | H25: =IFERROR(__xludf.DUMMYFUNCTION("""COMPUTED_VALUE"""),"Sairam Mushyam") -> Sairam Mushyam | I25: =IFERROR(__xludf.DUMMYFUNCTION("""COMPUTED_VALUE"""),45204.0) -> 45204 | J25: =IFERROR(__xludf.DUMMYFUNCTION("""COMPUTED_VALUE"""),"Mamta Pandey") -> Mamta Pandey | K25: =IFERROR(__xludf.DUMMYFUNCTION("""COMPUTED_VALUE"""),"Joined") -> Joined | L25: =IFERROR(__xludf.DUMMYFUNCTION("""COMPUTED_VALUE"""),"In Office") -> In Office | M25: =IFERROR(__xludf.DUMMYFUNCTION("""COMPUTED_VALUE"""),"tushar.patil@zupee.in") -> tushar.patil@zupee.in | N25: =IFERROR(__xludf.DUMMYFUNCTION("""COMPUTED_VALUE"""),"JLQMHQ2K3P") -> JLQMHQ2K3P
A26: =IFERROR(__xludf.DUMMYFUNCTION("""COMPUTED_VALUE"""),45264.0) -> 45264 | B26: =IFERROR(__xludf.DUMMYFUNCTION("""COMPUTED_VALUE""")," Mukul Bhatt") -> Mukul Bhatt | C26: =IFERROR(__xludf.DUMMYFUNCTION("""COMPUTED_VALUE"""),"Technology") -> Technology | D26: =IFERROR(__xludf.DUMMYFUNCTION("""COMPUTED_VALUE"""),9.971757357E9) -> 9971757357 | E26: =IFERROR(__xludf.DUMMYFUNCTION("""COMPUTED_VALUE"""),"Quality Assurance Engineer- 1") -> Quality Assurance Engineer- 1 | F26: =IFERROR(__xludf.DUMMYFUNCTION("""COMPUTED_VALUE"""),"Quality") -> Quality | G26: =IFERROR(__xludf.DUMMYFUNCTION("""COMPUTED_VALUE"""),"mukulbhatt9@gmail.com") -> mukulbhatt9@gmail.com | H26: =IFERROR(__xludf.DUMMYFUNCTION("""COMPUTED_VALUE"""),"Sahil Puri") -> Sahil Puri | I26: =IFERROR(__xludf.DUMMYFUNCTION("""COMPUTED_VALUE"""),45261.0) -> 45261 | J26: =IFERROR(__xludf.DUMMYFUNCTION("""COMPUTED_VALUE"""),"Mamta Pandey") -> Mamta Pandey | K26: =IFERROR(__xludf.DUMMYFUNCTION("""COMPUTED_VALUE"""),"Joined") -> Joined | L26: =IFERROR(__xludf.DUMMYFUNCTION("""COMPUTED_VALUE"""),"In Office") -> In Office
A27: =IFERROR(__xludf.DUMMYFUNCTION("""COMPUTED_VALUE"""),45273.0) -> 45273 | B27: =IFERROR(__xludf.DUMMYFUNCTION("""COMPUTED_VALUE"""),"Adhip kushwaha") -> Adhip kushwaha | C27: =IFERROR(__xludf.DUMMYFUNCTION("""COMPUTED_VALUE"""),"Technology") -> Technology | D27: =IFERROR(__xludf.DUMMYFUNCTION("""COMPUTED_VALUE"""),9.899277132E9) -> 9899277132 | E27: =IFERROR(__xludf.DUMMYFUNCTION("""COMPUTED_VALUE"""),"Software Engineer- Android") -> Software Engineer- Android | F27: =IFERROR(__xludf.DUMMYFUNCTION("""COMPUTED_VALUE"""),"Product Analytics") -> Product Analytics | G27: =IFERROR(__xludf.DUMMYFUNCTION("""COMPUTED_VALUE"""),"adhipkushwaha@gmail.com") -> adhipkushwaha@gmail.com | H27: =IFERROR(__xludf.DUMMYFUNCTION("""COMPUTED_VALUE"""),"Anshul Mittal") -> Anshul Mittal | I27: =IFERROR(__xludf.DUMMYFUNCTION("""COMPUTED_VALUE"""),45272.0) -> 45272 | J27: =IFERROR(__xludf.DUMMYFUNCTION("""COMPUTED_VALUE"""),"Naina") -> Naina | K27: =IFERROR(__xludf.DUMMYFUNCTION("""COMPUTED_VALUE"""),"Joined") -> Joined | L27: =IFERROR(__xludf.DUMMYFUNCTION("""COMPUTED_VALUE"""),"In Office") -> In Office | M27: =IFERROR(__xludf.DUMMYFUNCTION("""COMPUTED_VALUE"""),"adhip.kushwaha@zupee.in") -> adhip.kushwaha@zupee.in | N27: =IFERROR(__xludf.DUMMYFUNCTION("""COMPUTED_VALUE"""),"W1JLFTH56T") -> W1JLFTH56T
A28: =IFERROR(__xludf.DUMMYFUNCTION("""COMPUTED_VALUE"""),45275.0) -> 45275 | B28: =IFERROR(__xludf.DUMMYFUNCTION("""COMPUTED_VALUE"""),"Sucheta Sharma") -> Sucheta Sharma | C28: =IFERROR(__xludf.DUMMYFUNCTION("""COMPUTED_VALUE"""),"Finance") -> Finance | D28: =IFERROR(__xludf.DUMMYFUNCTION("""COMPUTED_VALUE"""),7.89896444E9) -> 7898964440 | E28: =IFERROR(__xludf.DUMMYFUNCTION("""COMPUTED_VALUE"""),"Manager- Finance") -> Manager- Finance | F28: =IFERROR(__xludf.DUMMYFUNCTION("""COMPUTED_VALUE"""),"Finance") -> Finance | G28: =IFERROR(__xludf.DUMMYFUNCTION("""COMPUTED_VALUE"""),"sssuchetasharma@gmail.com") -> sssuchetasharma@gmail.com | H28: =IFERROR(__xludf.DUMMYFUNCTION("""COMPUTED_VALUE"""),"Hitesh Vats") -> Hitesh Vats | I28: =IFERROR(__xludf.DUMMYFUNCTION("""COMPUTED_VALUE"""),45247.0) -> 45247 | J28: =IFERROR(__xludf.DUMMYFUNCTION("""COMPUTED_VALUE"""),"Nidhi Khedekar") -> Nidhi Khedekar | K28: =IFERROR(__xludf.DUMMYFUNCTION("""COMPUTED_VALUE"""),"Joined") -> Joined | L28: =IFERROR(__xludf.DUMMYFUNCTION("""COMPUTED_VALUE"""),"In Office") -> In Office | M28: =IFERROR(__xludf.DUMMYFUNCTION("""COMPUTED_VALUE"""),"sucheta.sharma@zupee.in") -> sucheta.sharma@zupee.in
A29: =IFERROR(__xludf.DUMMYFUNCTION("""COMPUTED_VALUE"""),44944.0) -> 44944 | B29: =IFERROR(__xludf.DUMMYFUNCTION("""COMPUTED_VALUE"""),"Mohit Choudhary") -> Mohit Choudhary | C29: =IFERROR(__xludf.DUMMYFUNCTION("""COMPUTED_VALUE"""),"Analytics") -> Analytics | D29: =IFERROR(__xludf.DUMMYFUNCTION("""COMPUTED_VALUE"""),8.561946709E9) -> 8561946709 | E29: =IFERROR(__xludf.DUMMYFUNCTION("""COMPUTED_VALUE"""),"Senior Data Analyst") -> Senior Data Analyst | F29: =IFERROR(__xludf.DUMMYFUNCTION("""COMPUTED_VALUE"""),"Product Analytics") -> Product Analytics | G29: =IFERROR(__xludf.DUMMYFUNCTION("""COMPUTED_VALUE"""),"choudharymohit1907@gmail.com") -> choudharymohit1907@gmail.com | H29: =IFERROR(__xludf.DUMMYFUNCTION("""COMPUTED_VALUE"""),"Shwetank Anand") -> Shwetank Anand | I29: =IFERROR(__xludf.DUMMYFUNCTION("""COMPUTED_VALUE"""),45251.0) -> 45251 | J29: =IFERROR(__xludf.DUMMYFUNCTION("""COMPUTED_VALUE"""),"Mamta Pandey") -> Mamta Pandey | K29: =IFERROR(__xludf.DUMMYFUNCTION("""COMPUTED_VALUE"""),"Joined") -> Joined | L29: =IFERROR(__xludf.DUMMYFUNCTION("""COMPUTED_VALUE"""),"In Office") -> In Office | M29: =IFERROR(__xludf.DUMMYFUNCTION("""COMPUTED_VALUE"""),"mohit.choudhary@zupee.in") -> mohit.choudhary@zupee.in
A30: =IFERROR(__xludf.DUMMYFUNCTION("""COMPUTED_VALUE"""),45397.0) -> 45397 | B30: =IFERROR(__xludf.DUMMYFUNCTION("""COMPUTED_VALUE"""),"Eeshma Anand") -> Eeshma Anand | C30: =IFERROR(__xludf.DUMMYFUNCTION("""COMPUTED_VALUE"""),"Product") -> Product | D30: =IFERROR(__xludf.DUMMYFUNCTION("""COMPUTED_VALUE"""),7.982263396E9) -> 7982263396 | E30: =IFERROR(__xludf.DUMMYFUNCTION("""COMPUTED_VALUE"""),"Product Manager") -> Product Manager | F30: =IFERROR(__xludf.DUMMYFUNCTION("""COMPUTED_VALUE"""),"Product") -> Product | G30: =IFERROR(__xludf.DUMMYFUNCTION("""COMPUTED_VALUE"""),"eeshma.anand@gmail.com") -> eeshma.anand@gmail.com | H30: =IFERROR(__xludf.DUMMYFUNCTION("""COMPUTED_VALUE"""),"Naveen Kadyan") -> Naveen Kadyan | I30: =IFERROR(__xludf.DUMMYFUNCTION("""COMPUTED_VALUE"""),45260.0) -> 45260 | J30: =IFERROR(__xludf.DUMMYFUNCTION("""COMPUTED_VALUE"""),"M Sangeetha") -> M Sangeetha | K30: =IFERROR(__xludf.DUMMYFUNCTION("""COMPUTED_VALUE"""),"Joined") -> Joined | L30: =IFERROR(__xludf.DUMMYFUNCTION("""COMPUTED_VALUE"""),"In Office") -> In Office | M30: =IFERROR(__xludf.DUMMYFUNCTION("""COMPUTED_VALUE"""),"eeshma.anand@zupee.in") -> eeshma.anand@zupee.in | N30: =IFERROR(__xludf.DUMMYFUNCTION("""COMPUTED_VALUE"""),"JY9YR6J6HV") -> JY9YR6J6HV
A31: =IFERROR(__xludf.DUMMYFUNCTION("""COMPUTED_VALUE"""),45266.0) -> 45266 | B31: =IFERROR(__xludf.DUMMYFUNCTION("""COMPUTED_VALUE"""),"Anjali") -> Anjali | C31: =IFERROR(__xludf.DUMMYFUNCTION("""COMPUTED_VALUE"""),"Customer Experience") -> Customer Experience | D31: =IFERROR(__xludf.DUMMYFUNCTION("""COMPUTED_VALUE"""),9.540863058E9) -> 9540863058 | E31: =IFERROR(__xludf.DUMMYFUNCTION("""COMPUTED_VALUE"""),"Quality Auditor- Executive") -> Quality Auditor- Executive | F31: =IFERROR(__xludf.DUMMYFUNCTION("""COMPUTED_VALUE"""),"Customer Relation Management") -> Customer Relation Management | G31: =IFERROR(__xludf.DUMMYFUNCTION("""COMPUTED_VALUE"""),"annirai345@gmail.com") -> annirai345@gmail.com | H31: =IFERROR(__xludf.DUMMYFUNCTION("""COMPUTED_VALUE"""),"Suvra Das") -> Suvra Das | I31: =IFERROR(__xludf.DUMMYFUNCTION("""COMPUTED_VALUE"""),45264.0) -> 45264 | J31: =IFERROR(__xludf.DUMMYFUNCTION("""COMPUTED_VALUE"""),"Nidhi Khedekar") -> Nidhi Khedekar | K31: =IFERROR(__xludf.DUMMYFUNCTION("""COMPUTED_VALUE"""),"Joined") -> Joined | L31: =IFERROR(__xludf.DUMMYFUNCTION("""COMPUTED_VALUE"""),"In Office") -> In Office | M31: =IFERROR(__xludf.DUMMYFUNCTION("""COMPUTED_VALUE"""),"anjali.pal@zupee.in") -> anjali.pal@zupee.in | N31: =IFERROR(__xludf.DUMMYFUNCTION("""COMPUTED_VALUE"""),"PW03VMFN") -> PW03VMFN
A32: =IFERROR(__xludf.DUMMYFUNCTION("""COMPUTED_VALUE"""),45271.0) -> 45271 | B32: =IFERROR(__xludf.DUMMYFUNCTION("""COMPUTED_VALUE"""),"Gaurav Khanna") -> Gaurav Khanna | C32: =IFERROR(__xludf.DUMMYFUNCTION("""COMPUTED_VALUE"""),"Admin") -> Admin | D32: =IFERROR(__xludf.DUMMYFUNCTION("""COMPUTED_VALUE"""),8.826268269E9) -> 8826268269 | E32: =IFERROR(__xludf.DUMMYFUNCTION("""COMPUTED_VALUE"""),"AM-Administration") -> AM-Administration | F32: =IFERROR(__xludf.DUMMYFUNCTION("""COMPUTED_VALUE"""),"Administration") -> Administration | G32: =IFERROR(__xludf.DUMMYFUNCTION("""COMPUTED_VALUE"""),"g29.khanna@yahoo.co.in") -> g29.khanna@yahoo.co.in | H32: =IFERROR(__xludf.DUMMYFUNCTION("""COMPUTED_VALUE"""),"Vijay Singh") -> Vijay Singh | I32: =IFERROR(__xludf.DUMMYFUNCTION("""COMPUTED_VALUE"""),45264.0) -> 45264 | J32: =IFERROR(__xludf.DUMMYFUNCTION("""COMPUTED_VALUE"""),"Nidhi Khedekar") -> Nidhi Khedekar | K32: =IFERROR(__xludf.DUMMYFUNCTION("""COMPUTED_VALUE"""),"Joined") -> Joined | L32: =IFERROR(__xludf.DUMMYFUNCTION("""COMPUTED_VALUE"""),"In Office") -> In Office | M32: =IFERROR(__xludf.DUMMYFUNCTION("""COMPUTED_VALUE"""),"gaurav.khanna@zupee.in") -> gaurav.khanna@zupee.in | N32: =IFERROR(__xludf.DUMMYFUNCTION("""COMPUTED_VALUE"""),"FW9FFY3") -> FW9FFY3
A33: =IFERROR(__xludf.DUMMYFUNCTION("""COMPUTED_VALUE"""),45271.0) -> 45271 | B33: =IFERROR(__xludf.DUMMYFUNCTION("""COMPUTED_VALUE"""),"Mohit Bakshi") -> Mohit Bakshi | C33: =IFERROR(__xludf.DUMMYFUNCTION("""COMPUTED_VALUE"""),"Technology") -> Technology | D33: =IFERROR(__xludf.DUMMYFUNCTION("""COMPUTED_VALUE"""),6.003534136E9) -> 6003534136 | E33: =IFERROR(__xludf.DUMMYFUNCTION("""COMPUTED_VALUE"""),"Software Engineer Trainee") -> Software Engineer Trainee | F33: =IFERROR(__xludf.DUMMYFUNCTION("""COMPUTED_VALUE"""),"Backend") -> Backend | G33: =IFERROR(__xludf.DUMMYFUNCTION("""COMPUTED_VALUE"""),"mohit19bakshi@gmail.com") -> mohit19bakshi@gmail.com | H33: =IFERROR(__xludf.DUMMYFUNCTION("""COMPUTED_VALUE"""),"Atique Firoz") -> Atique Firoz | I33: =IFERROR(__xludf.DUMMYFUNCTION("""COMPUTED_VALUE"""),45268.0) -> 45268 | J33: =IFERROR(__xludf.DUMMYFUNCTION("""COMPUTED_VALUE"""),"Nidhi Khedekar") -> Nidhi Khedekar | K33: =IFERROR(__xludf.DUMMYFUNCTION("""COMPUTED_VALUE"""),"Joined") -> Joined | L33: =IFERROR(__xludf.DUMMYFUNCTION("""COMPUTED_VALUE"""),"In Office") -> In Office | M33: =IFERROR(__xludf.DUMMYFUNCTION("""COMPUTED_VALUE"""),"mohit.bakshi@zupee.in") -> mohit.bakshi@zupee.in
A34: =IFERROR(__xludf.DUMMYFUNCTION("""COMPUTED_VALUE"""),45287.0) -> 45287 | B34: =IFERROR(__xludf.DUMMYFUNCTION("""COMPUTED_VALUE"""),"Mehul Deep") -> Mehul Deep | C34: =IFERROR(__xludf.DUMMYFUNCTION("""COMPUTED_VALUE"""),"Analytics") -> Analytics | D34: =IFERROR(__xludf.DUMMYFUNCTION("""COMPUTED_VALUE"""),8.527423606E9) -> 8527423606 | E34: =IFERROR(__xludf.DUMMYFUNCTION("""COMPUTED_VALUE"""),"Senior Data Analyst") -> Senior Data Analyst | F34: =IFERROR(__xludf.DUMMYFUNCTION("""COMPUTED_VALUE"""),"Product Analytics") -> Product Analytics | G34: =IFERROR(__xludf.DUMMYFUNCTION("""COMPUTED_VALUE"""),"mdmaurya25@gmail.com") -> mdmaurya25@gmail.com | H34: =IFERROR(__xludf.DUMMYFUNCTION("""COMPUTED_VALUE"""),"Shwetank Anand") -> Shwetank Anand | I34: =IFERROR(__xludf.DUMMYFUNCTION("""COMPUTED_VALUE"""),45268.0) -> 45268 | J34: =IFERROR(__xludf.DUMMYFUNCTION("""COMPUTED_VALUE"""),"Mamta Pandey") -> Mamta Pandey | K34: =IFERROR(__xludf.DUMMYFUNCTION("""COMPUTED_VALUE"""),"Offer Declined") -> Offer Declined | L34: =IFERROR(__xludf.DUMMYFUNCTION("""COMPUTED_VALUE"""),"In Office") -> In Office
A35: =IFERROR(__xludf.DUMMYFUNCTION("""COMPUTED_VALUE"""),45313.0) -> 45313 | B35: =IFERROR(__xludf.DUMMYFUNCTION("""COMPUTED_VALUE"""),"Anurag Pratap Singh") -> Anurag Pratap Singh | C35: =IFERROR(__xludf.DUMMYFUNCTION("""COMPUTED_VALUE"""),"Marketing") -> Marketing | D35: =IFERROR(__xludf.DUMMYFUNCTION("""COMPUTED_VALUE"""),8.793109048E9) -> 8793109048 | E35: =IFERROR(__xludf.DUMMYFUNCTION("""COMPUTED_VALUE"""),"Senior Associate- Digital Marketing") -> Senior Associate- Digital Marketing | F35: =IFERROR(__xludf.DUMMYFUNCTION("""COMPUTED_VALUE"""),"Digital Marketing") -> Digital Marketing | G35: =IFERROR(__xludf.DUMMYFUNCTION("""COMPUTED_VALUE"""),"singhpratapanurag@gmail.com") -> singhpratapanurag@gmail.com | H35: =IFERROR(__xludf.DUMMYFUNCTION("""COMPUTED_VALUE"""),"Nitin Chauhan") -> Nitin Chauhan | I35: =IFERROR(__xludf.DUMMYFUNCTION("""COMPUTED_VALUE"""),45280.0) -> 45280 | J35: =IFERROR(__xludf.DUMMYFUNCTION("""COMPUTED_VALUE"""),"Nidhi Khedekar") -> Nidhi Khedekar | K35: =IFERROR(__xludf.DUMMYFUNCTION("""COMPUTED_VALUE"""),"Joined") -> Joined | L35: =IFERROR(__xludf.DUMMYFUNCTION("""COMPUTED_VALUE"""),"In Office") -> In Office
A36: =IFERROR(__xludf.DUMMYFUNCTION("""COMPUTED_VALUE"""),45294.0) -> 45294 | B36: =IFERROR(__xludf.DUMMYFUNCTION("""COMPUTED_VALUE"""),"Mohini Bhardwaj") -> Mohini Bhardwaj | C36: =IFERROR(__xludf.DUMMYFUNCTION("""COMPUTED_VALUE"""),"Customer Experience") -> Customer Experience | D36: =IFERROR(__xludf.DUMMYFUNCTION("""COMPUTED_VALUE"""),9.6500412E9) -> 9650041200 | E36: =IFERROR(__xludf.DUMMYFUNCTION("""COMPUTED_VALUE"""),"Senior Manager - Customer Experience") -> Senior Manager - Customer Experience | F36: =IFERROR(__xludf.DUMMYFUNCTION("""COMPUTED_VALUE"""),"Training") -> Training | G36: =IFERROR(__xludf.DUMMYFUNCTION("""COMPUTED_VALUE"""),"Bhardwajcm@gmail.com") -> Bhardwajcm@gmail.com | H36: =IFERROR(__xludf.DUMMYFUNCTION("""COMPUTED_VALUE"""),"Mohammaed Faheem") -> Mohammaed Faheem | I36: =IFERROR(__xludf.DUMMYFUNCTION("""COMPUTED_VALUE"""),45282.0) -> 45282 | J36: =IFERROR(__xludf.DUMMYFUNCTION("""COMPUTED_VALUE"""),"Nidhi Khedekar") -> Nidhi Khedekar | K36: =IFERROR(__xludf.DUMMYFUNCTION("""COMPUTED_VALUE"""),"Joined") -> Joined | L36: =IFERROR(__xludf.DUMMYFUNCTION("""COMPUTED_VALUE"""),"In Office") -> In Office | M36: =IFERROR(__xludf.DUMMYFUNCTION("""COMPUTED_VALUE"""),"mohini.bhardwaj@zupee.in") -> mohini.bhardwaj@zupee.in
A37: =IFERROR(__xludf.DUMMYFUNCTION("""COMPUTED_VALUE"""),45308.0) -> 45308 | B37: =IFERROR(__xludf.DUMMYFUNCTION("""COMPUTED_VALUE"""),"Abhishek Mishra") -> Abhishek Mishra | C37: =IFERROR(__xludf.DUMMYFUNCTION("""COMPUTED_VALUE"""),"Customer Experience") -> Customer Experience | D37: =IFERROR(__xludf.DUMMYFUNCTION("""COMPUTED_VALUE"""),9.140467339E9) -> 9140467339 | E37: =IFERROR(__xludf.DUMMYFUNCTION("""COMPUTED_VALUE"""),"Senior Fraud Analyst") -> Senior Fraud Analyst | F37: =IFERROR(__xludf.DUMMYFUNCTION("""COMPUTED_VALUE"""),"Fraud Risk Management ") -> Fraud Risk Management | G37: =IFERROR(__xludf.DUMMYFUNCTION("""COMPUTED_VALUE"""),"abhishekmishram1@gmail.com") -> abhishekmishram1@gmail.com | H37: =IFERROR(__xludf.DUMMYFUNCTION("""COMPUTED_VALUE"""),"Aman Khare") -> Aman Khare | I37: =IFERROR(__xludf.DUMMYFUNCTION("""COMPUTED_VALUE"""),45289.0) -> 45289 | J37: =IFERROR(__xludf.DUMMYFUNCTION("""COMPUTED_VALUE"""),"Nidhi Khedekar") -> Nidhi Khedekar | K37: =IFERROR(__xludf.DUMMYFUNCTION("""COMPUTED_VALUE"""),"Joined") -> Joined | L37: =IFERROR(__xludf.DUMMYFUNCTION("""COMPUTED_VALUE"""),"In Office") -> In Office | M37: =IFERROR(__xludf.DUMMYFUNCTION("""COMPUTED_VALUE"""),"abhishek.mishra@zupee.in") -> abhishek.mishra@zupee.in
A38: =IFERROR(__xludf.DUMMYFUNCTION("""COMPUTED_VALUE"""),45294.0) -> 45294 | B38: =IFERROR(__xludf.DUMMYFUNCTION("""COMPUTED_VALUE"""),"Jatin Kinra") -> Jatin Kinra | C38: =IFERROR(__xludf.DUMMYFUNCTION("""COMPUTED_VALUE"""),"Technology") -> Technology | D38: =IFERROR(__xludf.DUMMYFUNCTION("""COMPUTED_VALUE"""),9.557854494E9) -> 9557854494 | E38: =IFERROR(__xludf.DUMMYFUNCTION("""COMPUTED_VALUE"""),"Senior Software Engineer") -> Senior Software Engineer | F38: =IFERROR(__xludf.DUMMYFUNCTION("""COMPUTED_VALUE"""),"Backend") -> Backend | G38: =IFERROR(__xludf.DUMMYFUNCTION("""COMPUTED_VALUE""")," jatin.kinra95@gmail.com") -> jatin.kinra95@gmail.com | H38: =IFERROR(__xludf.DUMMYFUNCTION("""COMPUTED_VALUE"""),"Rahul Sharma") -> Rahul Sharma | I38: =IFERROR(__xludf.DUMMYFUNCTION("""COMPUTED_VALUE"""),45289.0) -> 45289 | J38: =IFERROR(__xludf.DUMMYFUNCTION("""COMPUTED_VALUE"""),"Nidhi Khedekar") -> Nidhi Khedekar | K38: =IFERROR(__xludf.DUMMYFUNCTION("""COMPUTED_VALUE"""),"Joined") -> Joined | L38: =IFERROR(__xludf.DUMMYFUNCTION("""COMPUTED_VALUE"""),"In Office") -> In Office | M38: =IFERROR(__xludf.DUMMYFUNCTION("""COMPUTED_VALUE"""),"jatin.kinra@zupee.in") -> jatin.kinra@zupee.in | N38: =IFERROR(__xludf.DUMMYFUNCTION("""COMPUTED_VALUE"""),"J44J2L2GQM") -> J44J2L2GQM
A39: =IFERROR(__xludf.DUMMYFUNCTION("""COMPUTED_VALUE"""),45294.0) -> 45294 | B39: =IFERROR(__xludf.DUMMYFUNCTION("""COMPUTED_VALUE"""),"Divyansh Goyal") -> Divyansh Goyal | C39: =IFERROR(__xludf.DUMMYFUNCTION("""COMPUTED_VALUE"""),"Analytics") -> Analytics | D39: =IFERROR(__xludf.DUMMYFUNCTION("""COMPUTED_VALUE"""),7.895357571E9) -> 7895357571 | E39: =IFERROR(__xludf.DUMMYFUNCTION("""COMPUTED_VALUE"""),"Senior Data Analyst") -> Senior Data Analyst | F39: =IFERROR(__xludf.DUMMYFUNCTION("""COMPUTED_VALUE"""),"Product Analytics") -> Product Analytics | G39: =IFERROR(__xludf.DUMMYFUNCTION("""COMPUTED_VALUE"""),"dgoyal@ch.iitr.ac.in") -> dgoyal@ch.iitr.ac.in | H39: =IFERROR(__xludf.DUMMYFUNCTION("""COMPUTED_VALUE"""),"Shwetank Anand") -> Shwetank Anand | I39: =IFERROR(__xludf.DUMMYFUNCTION("""COMPUTED_VALUE"""),45293.0) -> 45293 | J39: =IFERROR(__xludf.DUMMYFUNCTION("""COMPUTED_VALUE"""),"Mamta Pandey") -> Mamta Pandey | K39: =IFERROR(__xludf.DUMMYFUNCTION("""COMPUTED_VALUE"""),"Offer Declined") -> Offer Declined | L39: =IFERROR(__xludf.DUMMYFUNCTION("""COMPUTED_VALUE"""),"In Office") -> In Office
A40: =IFERROR(__xludf.DUMMYFUNCTION("""COMPUTED_VALUE"""),45299.0) -> 45299 | B40: =IFERROR(__xludf.DUMMYFUNCTION("""COMPUTED_VALUE"""),"Kailash") -> Kailash | C40: =IFERROR(__xludf.DUMMYFUNCTION("""COMPUTED_VALUE"""),"Customer Experience") -> Customer Experience | D40: =IFERROR(__xludf.DUMMYFUNCTION("""COMPUTED_VALUE"""),9.882223818E9) -> 9882223818 | E40: =IFERROR(__xludf.DUMMYFUNCTION("""COMPUTED_VALUE"""),"Customer Support Executive") -> Customer Support Executive | F40: =IFERROR(__xludf.DUMMYFUNCTION("""COMPUTED_VALUE"""),"Customer Relation Management") -> Customer Relation Management | G40: =IFERROR(__xludf.DUMMYFUNCTION("""COMPUTED_VALUE"""),"kailashlalta01@gmail.com") -> kailashlalta01@gmail.com | H40: =IFERROR(__xludf.DUMMYFUNCTION("""COMPUTED_VALUE"""),"Shivam Bali") -> Shivam Bali | I40: =IFERROR(__xludf.DUMMYFUNCTION("""COMPUTED_VALUE"""),45296.0) -> 45296 | J40: =IFERROR(__xludf.DUMMYFUNCTION("""COMPUTED_VALUE"""),"Nidhi Khedekar") -> Nidhi Khedekar | K40: =IFERROR(__xludf.DUMMYFUNCTION("""COMPUTED_VALUE"""),"Joined") -> Joined | L40: =IFERROR(__xludf.DUMMYFUNCTION("""COMPUTED_VALUE"""),"Virtual") -> Virtual
A41: =IFERROR(__xludf.DUMMYFUNCTION("""COMPUTED_VALUE"""),45299.0) -> 45299 | B41: =IFERROR(__xludf.DUMMYFUNCTION("""COMPUTED_VALUE"""),"Satish Chandra") -> Satish Chandra | C41: =IFERROR(__xludf.DUMMYFUNCTION("""COMPUTED_VALUE"""),"Technology") -> Technology | D41: =IFERROR(__xludf.DUMMYFUNCTION("""COMPUTED_VALUE"""),9.560488236E9) -> 9560488236 | E41: =IFERROR(__xludf.DUMMYFUNCTION("""COMPUTED_VALUE"""),"Staff Engineer") -> Staff Engineer | F41: =IFERROR(__xludf.DUMMYFUNCTION("""COMPUTED_VALUE"""),"Engineering") -> Engineering | G41: =IFERROR(__xludf.DUMMYFUNCTION("""COMPUTED_VALUE"""),"satishck1992@gmail.com") -> satishck1992@gmail.com | H41: =IFERROR(__xludf.DUMMYFUNCTION("""COMPUTED_VALUE"""),"Gaurav Sharma") -> Gaurav Sharma | I41: =IFERROR(__xludf.DUMMYFUNCTION("""COMPUTED_VALUE"""),45296.0) -> 45296 | J41: =IFERROR(__xludf.DUMMYFUNCTION("""COMPUTED_VALUE"""),"Rajneesh Yadav") -> Rajneesh Yadav | K41: =IFERROR(__xludf.DUMMYFUNCTION("""COMPUTED_VALUE"""),"Joined") -> Joined | L41: =IFERROR(__xludf.DUMMYFUNCTION("""COMPUTED_VALUE"""),"In Office") -> In Office | M41: =IFERROR(__xludf.DUMMYFUNCTION("""COMPUTED_VALUE"""),"satish.chandra@zupee.in") -> satish.chandra@zupee.in
A42: =IFERROR(__xludf.DUMMYFUNCTION("""COMPUTED_VALUE"""),45299.0) -> 45299 | B42: =IFERROR(__xludf.DUMMYFUNCTION("""COMPUTED_VALUE"""),"Himanshu Sharma") -> Himanshu Sharma | C42: =IFERROR(__xludf.DUMMYFUNCTION("""COMPUTED_VALUE"""),"Marketing") -> Marketing | D42: =IFERROR(__xludf.DUMMYFUNCTION("""COMPUTED_VALUE"""),9.65081829E9) -> 9650818290 | E42: =IFERROR(__xludf.DUMMYFUNCTION("""COMPUTED_VALUE"""),"Senior Associate - Graphic Design") -> Senior Associate - Graphic Design | F42: =IFERROR(__xludf.DUMMYFUNCTION("""COMPUTED_VALUE"""),"Design") -> Design | G42: =IFERROR(__xludf.DUMMYFUNCTION("""COMPUTED_VALUE"""),"12himanshusharma@gmail.com") -> 12himanshusharma@gmail.com | H42: =IFERROR(__xludf.DUMMYFUNCTION("""COMPUTED_VALUE"""),"Alpika Singh") -> Alpika Singh | I42: =IFERROR(__xludf.DUMMYFUNCTION("""COMPUTED_VALUE"""),45296.0) -> 45296 | J42: =IFERROR(__xludf.DUMMYFUNCTION("""COMPUTED_VALUE"""),"Naina") -> Naina | K42: =IFERROR(__xludf.DUMMYFUNCTION("""COMPUTED_VALUE"""),"Joined") -> Joined | L42: =IFERROR(__xludf.DUMMYFUNCTION("""COMPUTED_VALUE"""),"In Office") -> In Office | M42: =IFERROR(__xludf.DUMMYFUNCTION("""COMPUTED_VALUE"""),"himanshu.sharma@zupee.in") -> himanshu.sharma@zupee.in
A43: =IFERROR(__xludf.DUMMYFUNCTION("""COMPUTED_VALUE"""),45341.0) -> 45341 | B43: =IFERROR(__xludf.DUMMYFUNCTION("""COMPUTED_VALUE"""),"Rachit Madhukar") -> Rachit Madhukar | C43: =IFERROR(__xludf.DUMMYFUNCTION("""COMPUTED_VALUE"""),"Analytics") -> Analytics | D43: =IFERROR(__xludf.DUMMYFUNCTION("""COMPUTED_VALUE"""),9.800116277E9) -> 9800116277 | E43: =IFERROR(__xludf.DUMMYFUNCTION("""COMPUTED_VALUE"""),"Lead Data Analyst") -> Lead Data Analyst | F43: =IFERROR(__xludf.DUMMYFUNCTION("""COMPUTED_VALUE"""),"Product Analytics") -> Product Analytics | G43: =IFERROR(__xludf.DUMMYFUNCTION("""COMPUTED_VALUE"""),"rachitmadhukar@gmail.com") -> rachitmadhukar@gmail.com | H43: =IFERROR(__xludf.DUMMYFUNCTION("""COMPUTED_VALUE"""),"Shwetank Anand") -> Shwetank Anand | I43: =IFERROR(__xludf.DUMMYFUNCTION("""COMPUTED_VALUE"""),45293.0) -> 45293 | J43: =IFERROR(__xludf.DUMMYFUNCTION("""COMPUTED_VALUE"""),"Mamta Pandey") -> Mamta Pandey | K43: =IFERROR(__xludf.DUMMYFUNCTION("""COMPUTED_VALUE"""),"Offer Declined") -> Offer Declined | L43: =IFERROR(__xludf.DUMMYFUNCTION("""COMPUTED_VALUE"""),"In Office") -> In Office
A44: =IFERROR(__xludf.DUMMYFUNCTION("""COMPUTED_VALUE"""),45301.0) -> 45301 | B44: =IFERROR(__xludf.DUMMYFUNCTION("""COMPUTED_VALUE"""),"Mohit Singh") -> Mohit Singh | C44: =IFERROR(__xludf.DUMMYFUNCTION("""COMPUTED_VALUE"""),"Marketing") -> Marketing | D44: =IFERROR(__xludf.DUMMYFUNCTION("""COMPUTED_VALUE"""),9.971796816E9) -> 9971796816 | E44: =IFERROR(__xludf.DUMMYFUNCTION("""COMPUTED_VALUE"""),"SEO Content Writer") -> SEO Content Writer | F44: =IFERROR(__xludf.DUMMYFUNCTION("""COMPUTED_VALUE"""),"Digital Marketing") -> Digital Marketing | G44: =IFERROR(__xludf.DUMMYFUNCTION("""COMPUTED_VALUE"""),"mohitthearies@gmail.com") -> mohitthearies@gmail.com | H44: =IFERROR(__xludf.DUMMYFUNCTION("""COMPUTED_VALUE"""),"Lekhika Dhariyal ") -> Lekhika Dhariyal | I44: =IFERROR(__xludf.DUMMYFUNCTION("""COMPUTED_VALUE"""),45300.0) -> 45300 | J44: =IFERROR(__xludf.DUMMYFUNCTION("""COMPUTED_VALUE"""),"Naina") -> Naina | K44: =IFERROR(__xludf.DUMMYFUNCTION("""COMPUTED_VALUE"""),"Joined") -> Joined | L44: =IFERROR(__xludf.DUMMYFUNCTION("""COMPUTED_VALUE"""),"In Office") -> In Office | M44: =IFERROR(__xludf.DUMMYFUNCTION("""COMPUTED_VALUE"""),"mohit.singh@zupee.in") -> mohit.singh@zupee.in | N44: =IFERROR(__xludf.DUMMYFUNCTION("""COMPUTED_VALUE"""),"3CXR4B3") -> 3CXR4B3
A45: =IFERROR(__xludf.DUMMYFUNCTION("""COMPUTED_VALUE"""),45306.0) -> 45306 | B45: =IFERROR(__xludf.DUMMYFUNCTION("""COMPUTED_VALUE"""),"Tarun Talan") -> Tarun Talan | C45: =IFERROR(__xludf.DUMMYFUNCTION("""COMPUTED_VALUE"""),"Customer Experience") -> Customer Experience | D45: =IFERROR(__xludf.DUMMYFUNCTION("""COMPUTED_VALUE"""),8.92990042E9) -> 8929900420 | E45: =IFERROR(__xludf.DUMMYFUNCTION("""COMPUTED_VALUE"""),"Customer Support Executive") -> Customer Support Executive | F45: =IFERROR(__xludf.DUMMYFUNCTION("""COMPUTED_VALUE"""),"Customer Relation Management") -> Customer Relation Management | G45: =IFERROR(__xludf.DUMMYFUNCTION("""COMPUTED_VALUE"""),"tarun.talan007@gmail.com") -> tarun.talan007@gmail.com | H45: =IFERROR(__xludf.DUMMYFUNCTION("""COMPUTED_VALUE"""),"Shivam Bali") -> Shivam Bali | I45: =IFERROR(__xludf.DUMMYFUNCTION("""COMPUTED_VALUE"""),45303.0) -> 45303 | J45: =IFERROR(__xludf.DUMMYFUNCTION("""COMPUTED_VALUE"""),"Nidhi Khedekar") -> Nidhi Khedekar | K45: =IFERROR(__xludf.DUMMYFUNCTION("""COMPUTED_VALUE"""),"Joined") -> Joined | L45: =IFERROR(__xludf.DUMMYFUNCTION("""COMPUTED_VALUE"""),"In Office") -> In Office | M45: =IFERROR(__xludf.DUMMYFUNCTION("""COMPUTED_VALUE"""),"tarun.talan@zupee.in") -> tarun.talan@zupee.in
A46: =IFERROR(__xludf.DUMMYFUNCTION("""COMPUTED_VALUE"""),45334.0) -> 45334 | B46: =IFERROR(__xludf.DUMMYFUNCTION("""COMPUTED_VALUE"""),"Mukesh Kumar Maurya") -> Mukesh Kumar Maurya | C46: =IFERROR(__xludf.DUMMYFUNCTION("""COMPUTED_VALUE"""),"Marketing") -> Marketing | D46: =IFERROR(__xludf.DUMMYFUNCTION("""COMPUTED_VALUE"""),9.559001668E9) -> 9559001668 | E46: =IFERROR(__xludf.DUMMYFUNCTION("""COMPUTED_VALUE"""),"Senior Motion Graphic Designer") -> Senior Motion Graphic Designer | F46: =IFERROR(__xludf.DUMMYFUNCTION("""COMPUTED_VALUE"""),"Marketing Design") -> Marketing Design | G46: =IFERROR(__xludf.DUMMYFUNCTION("""COMPUTED_VALUE"""),"Mukeshkumar6577622@gmail.com ") -> Mukeshkumar6577622@gmail.com | H46: =IFERROR(__xludf.DUMMYFUNCTION("""COMPUTED_VALUE"""),"Manish Karnatak") -> Manish Karnatak | I46: =IFERROR(__xludf.DUMMYFUNCTION("""COMPUTED_VALUE"""),45303.0) -> 45303 | J46: =IFERROR(__xludf.DUMMYFUNCTION("""COMPUTED_VALUE"""),"Nidhi Khedekar") -> Nidhi Khedekar | K46: =IFERROR(__xludf.DUMMYFUNCTION("""COMPUTED_VALUE"""),"Joined") -> Joined | L46: =IFERROR(__xludf.DUMMYFUNCTION("""COMPUTED_VALUE"""),"In Office") -> In Office | M46: =IFERROR(__xludf.DUMMYFUNCTION("""COMPUTED_VALUE"""),"mukesh.maurya@zupee.in") -> mukesh.maurya@zupee.in | N46: =IFERROR(__xludf.DUMMYFUNCTION("""COMPUTED_VALUE"""),"KX2D79517D") -> KX2D79517D
A47: =IFERROR(__xludf.DUMMYFUNCTION("""COMPUTED_VALUE"""),45313.0) -> 45313 | B47: =IFERROR(__xludf.DUMMYFUNCTION("""COMPUTED_VALUE"""),"Saksham Kochhar") -> Saksham Kochhar | C47: =IFERROR(__xludf.DUMMYFUNCTION("""COMPUTED_VALUE"""),"Data Science") -> Data Science | D47: =IFERROR(__xludf.DUMMYFUNCTION("""COMPUTED_VALUE"""),9.711333881E9) -> 9711333881 | E47: =IFERROR(__xludf.DUMMYFUNCTION("""COMPUTED_VALUE"""),"Data Science Intern") -> Data Science Intern | F47: =IFERROR(__xludf.DUMMYFUNCTION("""COMPUTED_VALUE"""),"Data Science") -> Data Science | G47: =IFERROR(__xludf.DUMMYFUNCTION("""COMPUTED_VALUE"""),"21f3002170@ds.study.iitm.ac.in") -> 21f3002170@ds.study.iitm.ac.in | H47: =IFERROR(__xludf.DUMMYFUNCTION("""COMPUTED_VALUE"""),"Priyanshu Jain") -> Priyanshu Jain | I47: =IFERROR(__xludf.DUMMYFUNCTION("""COMPUTED_VALUE"""),45307.0) -> 45307 | J47: =IFERROR(__xludf.DUMMYFUNCTION("""COMPUTED_VALUE"""),"Rajneesh Yadav") -> Rajneesh Yadav | K47: =IFERROR(__xludf.DUMMYFUNCTION("""COMPUTED_VALUE"""),"Joined") -> Joined | L47: =IFERROR(__xludf.DUMMYFUNCTION("""COMPUTED_VALUE"""),"In Office") -> In Office
A48: =IFERROR(__xludf.DUMMYFUNCTION("""COMPUTED_VALUE"""),45313.0) -> 45313 | B48: =IFERROR(__xludf.DUMMYFUNCTION("""COMPUTED_VALUE"""),"Pawan Kumar Sarswat") -> Pawan Kumar Sarswat | C48: =IFERROR(__xludf.DUMMYFUNCTION("""COMPUTED_VALUE"""),"Customer Experience") -> Customer Experience | D48: =IFERROR(__xludf.DUMMYFUNCTION("""COMPUTED_VALUE"""),8.107829942E9) -> 8107829942 | E48: =IFERROR(__xludf.DUMMYFUNCTION("""COMPUTED_VALUE"""),"Customer Support Executive") -> Customer Support Executive | F48: =IFERROR(__xludf.DUMMYFUNCTION("""COMPUTED_VALUE"""),"Customer Relation Management") -> Customer Relation Management | G48: =IFERROR(__xludf.DUMMYFUNCTION("""COMPUTED_VALUE"""),"sarswatpwn@gmail.com") -> sarswatpwn@gmail.com | H48: =IFERROR(__xludf.DUMMYFUNCTION("""COMPUTED_VALUE"""),"Shivam Bali") -> Shivam Bali | I48: =IFERROR(__xludf.DUMMYFUNCTION("""COMPUTED_VALUE"""),45308.0) -> 45308 | J48: =IFERROR(__xludf.DUMMYFUNCTION("""COMPUTED_VALUE"""),"Nidhi Khedekar") -> Nidhi Khedekar | K48: =IFERROR(__xludf.DUMMYFUNCTION("""COMPUTED_VALUE"""),"Joined") -> Joined | L48: =IFERROR(__xludf.DUMMYFUNCTION("""COMPUTED_VALUE"""),"In Office") -> In Office | M48: =IFERROR(__xludf.DUMMYFUNCTION("""COMPUTED_VALUE"""),"pawan.sarswat@zupee.in") -> pawan.sarswat@zupee.in
A49: =IFERROR(__xludf.DUMMYFUNCTION("""COMPUTED_VALUE"""),45313.0) -> 45313 | B49: =IFERROR(__xludf.DUMMYFUNCTION("""COMPUTED_VALUE"""),"Shubham Kumar Thakur") -> Shubham Kumar Thakur | C49: =IFERROR(__xludf.DUMMYFUNCTION("""COMPUTED_VALUE"""),"Finance") -> Finance | D49: =IFERROR(__xludf.DUMMYFUNCTION("""COMPUTED_VALUE"""),7.717734659E9) -> 7717734659 | E49: =IFERROR(__xludf.DUMMYFUNCTION("""COMPUTED_VALUE"""),"Executive - Finance") -> Executive - Finance | F49: =IFERROR(__xludf.DUMMYFUNCTION("""COMPUTED_VALUE"""),"Finance") -> Finance | G49: =IFERROR(__xludf.DUMMYFUNCTION("""COMPUTED_VALUE"""),"shubhamkoilakh@gmail.com") -> shubhamkoilakh@gmail.com | H49: =IFERROR(__xludf.DUMMYFUNCTION("""COMPUTED_VALUE"""),"Sucheta Sharma") -> Sucheta Sharma | I49: =IFERROR(__xludf.DUMMYFUNCTION("""COMPUTED_VALUE"""),45308.0) -> 45308 | J49: =IFERROR(__xludf.DUMMYFUNCTION("""COMPUTED_VALUE"""),"Nidhi Khedekar") -> Nidhi Khedekar | K49: =IFERROR(__xludf.DUMMYFUNCTION("""COMPUTED_VALUE"""),"Joined") -> Joined | L49: =IFERROR(__xludf.DUMMYFUNCTION("""COMPUTED_VALUE"""),"In Office") -> In Office | M49: =IFERROR(__xludf.DUMMYFUNCTION("""COMPUTED_VALUE"""),"shubham.thakur@zupee.in") -> shubham.thakur@zupee.in
A50: =IFERROR(__xludf.DUMMYFUNCTION("""COMPUTED_VALUE"""),45313.0) -> 45313 | B50: =IFERROR(__xludf.DUMMYFUNCTION("""COMPUTED_VALUE"""),"Rajat Shah") -> Rajat Shah | C50: =IFERROR(__xludf.DUMMYFUNCTION("""COMPUTED_VALUE"""),"Analytics") -> Analytics | D50: =IFERROR(__xludf.DUMMYFUNCTION("""COMPUTED_VALUE"""),9.953254493E9) -> 9953254493 | E50: =IFERROR(__xludf.DUMMYFUNCTION("""COMPUTED_VALUE"""),"Senior Manager- Data Analytics") -> Senior Manager- Data Analytics | F50: =IFERROR(__xludf.DUMMYFUNCTION("""COMPUTED_VALUE"""),"Product Analytics") -> Product Analytics | G50: =IFERROR(__xludf.DUMMYFUNCTION("""COMPUTED_VALUE"""),"rajat.shah@hotmail.com") -> rajat.shah@hotmail.com | H50: =IFERROR(__xludf.DUMMYFUNCTION("""COMPUTED_VALUE"""),"Shwetank Anand") -> Shwetank Anand | I50: =IFERROR(__xludf.DUMMYFUNCTION("""COMPUTED_VALUE"""),45306.0) -> 45306 | J50: =IFERROR(__xludf.DUMMYFUNCTION("""COMPUTED_VALUE"""),"Mamta Pandey") -> Mamta Pandey | K50: =IFERROR(__xludf.DUMMYFUNCTION("""COMPUTED_VALUE"""),"Offer Declined") -> Offer Declined | L50: =IFERROR(__xludf.DUMMYFUNCTION("""COMPUTED_VALUE"""),"In Office") -> In Office
A51: =IFERROR(__xludf.DUMMYFUNCTION("""COMPUTED_VALUE"""),45323.0) -> 45323 | B51: =IFERROR(__xludf.DUMMYFUNCTION("""COMPUTED_VALUE"""),"Parth Kumar") -> Parth Kumar | C51: =IFERROR(__xludf.DUMMYFUNCTION("""COMPUTED_VALUE"""),"Technology") -> Technology | D51: =IFERROR(__xludf.DUMMYFUNCTION("""COMPUTED_VALUE"""),8.899889947E9) -> 8899889947 | E51: =IFERROR(__xludf.DUMMYFUNCTION("""COMPUTED_VALUE"""),"Devops Engineer Trainee") -> Devops Engineer Trainee | F51: =IFERROR(__xludf.DUMMYFUNCTION("""COMPUTED_VALUE"""),"DevOps") -> DevOps | G51: =IFERROR(__xludf.DUMMYFUNCTION("""COMPUTED_VALUE"""),"Parthkumarofficial@gmail.com ") -> Parthkumarofficial@gmail.com | H51: =IFERROR(__xludf.DUMMYFUNCTION("""COMPUTED_VALUE"""),"Puneet Dhiman") -> Puneet Dhiman | I51: =IFERROR(__xludf.DUMMYFUNCTION("""COMPUTED_VALUE"""),45310.0) -> 45310 | J51: =IFERROR(__xludf.DUMMYFUNCTION("""COMPUTED_VALUE"""),"Nidhi Khedekar") -> Nidhi Khedekar | K51: =IFERROR(__xludf.DUMMYFUNCTION("""COMPUTED_VALUE"""),"Joined") -> Joined | L51: =IFERROR(__xludf.DUMMYFUNCTION("""COMPUTED_VALUE"""),"In Office") -> In Office | M51: =IFERROR(__xludf.DUMMYFUNCTION("""COMPUTED_VALUE"""),"parth.kumar@zupee.in") -> parth.kumar@zupee.in
A52: =IFERROR(__xludf.DUMMYFUNCTION("""COMPUTED_VALUE"""),45313.0) -> 45313 | B52: =IFERROR(__xludf.DUMMYFUNCTION("""COMPUTED_VALUE"""),"Siddharth Rehani") -> Siddharth Rehani | C52: =IFERROR(__xludf.DUMMYFUNCTION("""COMPUTED_VALUE"""),"Marketing") -> Marketing | D52: =IFERROR(__xludf.DUMMYFUNCTION("""COMPUTED_VALUE"""),8.130435875E9) -> 8130435875 | E52: =IFERROR(__xludf.DUMMYFUNCTION("""COMPUTED_VALUE"""),"SEO Executive") -> SEO Executive | F52: =IFERROR(__xludf.DUMMYFUNCTION("""COMPUTED_VALUE"""),"Digital Marketing") -> Digital Marketing | G52: =IFERROR(__xludf.DUMMYFUNCTION("""COMPUTED_VALUE"""),"sidd.rehani1272@gmail.com") -> sidd.rehani1272@gmail.com | H52: =IFERROR(__xludf.DUMMYFUNCTION("""COMPUTED_VALUE"""),"Lekhika Dhariyal ") -> Lekhika Dhariyal | I52: =IFERROR(__xludf.DUMMYFUNCTION("""COMPUTED_VALUE"""),45309.0) -> 45309 | J52: =IFERROR(__xludf.DUMMYFUNCTION("""COMPUTED_VALUE"""),"Naina") -> Naina | K52: =IFERROR(__xludf.DUMMYFUNCTION("""COMPUTED_VALUE"""),"Joined") -> Joined | L52: =IFERROR(__xludf.DUMMYFUNCTION("""COMPUTED_VALUE"""),"In Office") -> In Office | M52: =IFERROR(__xludf.DUMMYFUNCTION("""COMPUTED_VALUE"""),"siddharth.rehani@zupee.in") -> siddharth.rehani@zupee.in
A53: =IFERROR(__xludf.DUMMYFUNCTION("""COMPUTED_VALUE"""),45315.0) -> 45315 | B53: =IFERROR(__xludf.DUMMYFUNCTION("""COMPUTED_VALUE"""),"Tushar Mehta") -> Tushar Mehta | C53: =IFERROR(__xludf.DUMMYFUNCTION("""COMPUTED_VALUE"""),"Technology") -> Technology | D53: =IFERROR(__xludf.DUMMYFUNCTION("""COMPUTED_VALUE"""),7.986314491E9) -> 7986314491 | E53: =IFERROR(__xludf.DUMMYFUNCTION("""COMPUTED_VALUE"""),"Senior Software Engineer - Android") -> Senior Software Engineer - Android | F53: =IFERROR(__xludf.DUMMYFUNCTION("""COMPUTED_VALUE"""),"Engineering") -> Engineering | G53: =IFERROR(__xludf.DUMMYFUNCTION("""COMPUTED_VALUE"""),"tushar.mehta466@gmail.com") -> tushar.mehta466@gmail.com | H53: =IFERROR(__xludf.DUMMYFUNCTION("""COMPUTED_VALUE"""),"Anshul Mittal") -> Anshul Mittal | I53: =IFERROR(__xludf.DUMMYFUNCTION("""COMPUTED_VALUE"""),45310.0) -> 45310 | J53: =IFERROR(__xludf.DUMMYFUNCTION("""COMPUTED_VALUE"""),"Naina") -> Naina | K53: =IFERROR(__xludf.DUMMYFUNCTION("""COMPUTED_VALUE"""),"Joined") -> Joined | L53: =IFERROR(__xludf.DUMMYFUNCTION("""COMPUTED_VALUE"""),"In Office") -> In Office | M53: =IFERROR(__xludf.DUMMYFUNCTION("""COMPUTED_VALUE"""),"tushar.mehta@zupee.in") -> tushar.mehta@zupee.in | N53: =IFERROR(__xludf.DUMMYFUNCTION("""COMPUTED_VALUE"""),"FC7XJ40MKQ") -> FC7XJ40MKQ
A54: =IFERROR(__xludf.DUMMYFUNCTION("""COMPUTED_VALUE"""),45315.0) -> 45315 | B54: =IFERROR(__xludf.DUMMYFUNCTION("""COMPUTED_VALUE"""),"Anwesha Raj") -> Anwesha Raj | C54: =IFERROR(__xludf.DUMMYFUNCTION("""COMPUTED_VALUE"""),"Product") -> Product | D54: =IFERROR(__xludf.DUMMYFUNCTION("""COMPUTED_VALUE"""),9.743808027E9) -> 9743808027 | E54: =IFERROR(__xludf.DUMMYFUNCTION("""COMPUTED_VALUE"""),"Product Manager") -> Product Manager | F54: =IFERROR(__xludf.DUMMYFUNCTION("""COMPUTED_VALUE"""),"Product") -> Product | G54: =IFERROR(__xludf.DUMMYFUNCTION("""COMPUTED_VALUE"""),"anwesha.raj16@gmail.com") -> anwesha.raj16@gmail.com | H54: =IFERROR(__xludf.DUMMYFUNCTION("""COMPUTED_VALUE"""),"Mayank Jain") -> Mayank Jain | I54: =IFERROR(__xludf.DUMMYFUNCTION("""COMPUTED_VALUE"""),45307.0) -> 45307 | J54: =IFERROR(__xludf.DUMMYFUNCTION("""COMPUTED_VALUE"""),"Naina") -> Naina | K54: =IFERROR(__xludf.DUMMYFUNCTION("""COMPUTED_VALUE"""),"Joined") -> Joined | L54: =IFERROR(__xludf.DUMMYFUNCTION("""COMPUTED_VALUE"""),"In Office") -> In Office | M54: =IFERROR(__xludf.DUMMYFUNCTION("""COMPUTED_VALUE"""),"anwesha.raj@zupee.in") -> anwesha.raj@zupee.in | N54: =IFERROR(__xludf.DUMMYFUNCTION("""COMPUTED_VALUE"""),"KVYCXDXWF6") -> KVYCXDXWF6
A55: =IFERROR(__xludf.DUMMYFUNCTION("""COMPUTED_VALUE"""),45370.0) -> 45370 | B55: =IFERROR(__xludf.DUMMYFUNCTION("""COMPUTED_VALUE"""),"Shabi") -> Shabi | C55: =IFERROR(__xludf.DUMMYFUNCTION("""COMPUTED_VALUE"""),"Analytics") -> Analytics | D55: =IFERROR(__xludf.DUMMYFUNCTION("""COMPUTED_VALUE"""),9.596967342E9) -> 9596967342 | E55: =IFERROR(__xludf.DUMMYFUNCTION("""COMPUTED_VALUE"""),"Senior Data Analyst") -> Senior Data Analyst | F55: =IFERROR(__xludf.DUMMYFUNCTION("""COMPUTED_VALUE"""),"Product Analytics") -> Product Analytics | G55: =IFERROR(__xludf.DUMMYFUNCTION("""COMPUTED_VALUE"""),"chhavimahajan.96@gmail.com") -> chhavimahajan.96@gmail.com | H55: =IFERROR(__xludf.DUMMYFUNCTION("""COMPUTED_VALUE"""),"Shwetank Anand") -> Shwetank Anand | I55: =IFERROR(__xludf.DUMMYFUNCTION("""COMPUTED_VALUE"""),44944.0) -> 44944 | J55: =IFERROR(__xludf.DUMMYFUNCTION("""COMPUTED_VALUE"""),"Mamta Pandey") -> Mamta Pandey | K55: =IFERROR(__xludf.DUMMYFUNCTION("""COMPUTED_VALUE"""),"Offer Declined") -> Offer Declined | L55: =IFERROR(__xludf.DUMMYFUNCTION("""COMPUTED_VALUE"""),"In Office") -> In Office
A56: =IFERROR(__xludf.DUMMYFUNCTION("""COMPUTED_VALUE"""),45341.0) -> 45341 | B56: =IFERROR(__xludf.DUMMYFUNCTION("""COMPUTED_VALUE"""),"Kanika Wadhwa") -> Kanika Wadhwa | C56: =IFERROR(__xludf.DUMMYFUNCTION("""COMPUTED_VALUE"""),"Customer Experience") -> Customer Experience | D56: =IFERROR(__xludf.DUMMYFUNCTION("""COMPUTED_VALUE"""),9.034340484E9) -> 9034340484 | E56: =IFERROR(__xludf.DUMMYFUNCTION("""COMPUTED_VALUE"""),"Senior Executive – Customer Experience") -> Senior Executive – Customer Experience | F56: =IFERROR(__xludf.DUMMYFUNCTION("""COMPUTED_VALUE"""),"Customer Relation Management") -> Customer Relation Management | G56: =IFERROR(__xludf.DUMMYFUNCTION("""COMPUTED_VALUE"""),"kanikav1993@gmail.com") -> kanikav1993@gmail.com | H56: =IFERROR(__xludf.DUMMYFUNCTION("""COMPUTED_VALUE"""),"Shivam Bali") -> Shivam Bali | I56: =IFERROR(__xludf.DUMMYFUNCTION("""COMPUTED_VALUE"""),45316.0) -> 45316 | J56: =IFERROR(__xludf.DUMMYFUNCTION("""COMPUTED_VALUE"""),"Nidhi Khedekar") -> Nidhi Khedekar | K56: =IFERROR(__xludf.DUMMYFUNCTION("""COMPUTED_VALUE"""),"Joined") -> Joined | L56: =IFERROR(__xludf.DUMMYFUNCTION("""COMPUTED_VALUE"""),"In Office") -> In Office | M56: =IFERROR(__xludf.DUMMYFUNCTION("""COMPUTED_VALUE"""),"kanika.wadhwa@zupee.in") -> kanika.wadhwa@zupee.in | N56: =IFERROR(__xludf.DUMMYFUNCTION("""COMPUTED_VALUE"""),"PW03VMKG") -> PW03VMKG
A57: =IFERROR(__xludf.DUMMYFUNCTION("""COMPUTED_VALUE"""),45323.0) -> 45323 | B57: =IFERROR(__xludf.DUMMYFUNCTION("""COMPUTED_VALUE"""),"Rijul Sharma") -> Rijul Sharma | C57: =IFERROR(__xludf.DUMMYFUNCTION("""COMPUTED_VALUE"""),"Technology") -> Technology | D57: =IFERROR(__xludf.DUMMYFUNCTION("""COMPUTED_VALUE"""),8.699972878E9) -> 8699972878 | E57: =IFERROR(__xludf.DUMMYFUNCTION("""COMPUTED_VALUE"""),"Software Engineer- DevOps") -> Software Engineer- DevOps | F57: =IFERROR(__xludf.DUMMYFUNCTION("""COMPUTED_VALUE"""),"DevOps") -> DevOps | G57: =IFERROR(__xludf.DUMMYFUNCTION("""COMPUTED_VALUE"""),"rijulsharma25@gmail.com") -> rijulsharma25@gmail.com | H57: =IFERROR(__xludf.DUMMYFUNCTION("""COMPUTED_VALUE"""),"Saurav Yadav") -> Saurav Yadav | I57: =IFERROR(__xludf.DUMMYFUNCTION("""COMPUTED_VALUE"""),45320.0) -> 45320 | J57: =IFERROR(__xludf.DUMMYFUNCTION("""COMPUTED_VALUE"""),"Nidhi Khedekar") -> Nidhi Khedekar | K57: =IFERROR(__xludf.DUMMYFUNCTION("""COMPUTED_VALUE"""),"Joined") -> Joined | L57: =IFERROR(__xludf.DUMMYFUNCTION("""COMPUTED_VALUE"""),"Virtual") -> Virtual | M57: =IFERROR(__xludf.DUMMYFUNCTION("""COMPUTED_VALUE"""),"rijul.sharma@zupee.in") -> rijul.sharma@zupee.in | N57: =IFERROR(__xludf.DUMMYFUNCTION("""COMPUTED_VALUE"""),"FVW399JXH1") -> FVW399JXH1
A58: =IFERROR(__xludf.DUMMYFUNCTION("""COMPUTED_VALUE"""),45323.0) -> 45323 | B58: =IFERROR(__xludf.DUMMYFUNCTION("""COMPUTED_VALUE"""),"Arya Soni") -> Arya Soni | C58: =IFERROR(__xludf.DUMMYFUNCTION("""COMPUTED_VALUE"""),"Technology") -> Technology | D58: =IFERROR(__xludf.DUMMYFUNCTION("""COMPUTED_VALUE"""),9.667475014E9) -> 9667475014 | E58: =IFERROR(__xludf.DUMMYFUNCTION("""COMPUTED_VALUE"""),"Software Engineer- DevOps") -> Software Engineer- DevOps | F58: =IFERROR(__xludf.DUMMYFUNCTION("""COMPUTED_VALUE"""),"DevOps") -> DevOps | G58: =IFERROR(__xludf.DUMMYFUNCTION("""COMPUTED_VALUE"""),"aryasoni98@gmail.com") -> aryasoni98@gmail.com | H58: =IFERROR(__xludf.DUMMYFUNCTION("""COMPUTED_VALUE"""),"Saurav Yadav") -> Saurav Yadav | I58: =IFERROR(__xludf.DUMMYFUNCTION("""COMPUTED_VALUE"""),45320.0) -> 45320 | J58: =IFERROR(__xludf.DUMMYFUNCTION("""COMPUTED_VALUE"""),"Nidhi Khedekar") -> Nidhi Khedekar | K58: =IFERROR(__xludf.DUMMYFUNCTION("""COMPUTED_VALUE"""),"Joined") -> Joined | L58: =IFERROR(__xludf.DUMMYFUNCTION("""COMPUTED_VALUE"""),"In Office") -> In Office | M58: =IFERROR(__xludf.DUMMYFUNCTION("""COMPUTED_VALUE"""),"arya.soni@zupee.in") -> arya.soni@zupee.in
A59: =IFERROR(__xludf.DUMMYFUNCTION("""COMPUTED_VALUE"""),45337.0) -> 45337 | B59: =IFERROR(__xludf.DUMMYFUNCTION("""COMPUTED_VALUE"""),"Akhil Sukhnani") -> Akhil Sukhnani | C59: =IFERROR(__xludf.DUMMYFUNCTION("""COMPUTED_VALUE"""),"Technology") -> Technology | D59: =IFERROR(__xludf.DUMMYFUNCTION("""COMPUTED_VALUE"""),7.877111933E9) -> 7877111933 | E59: =IFERROR(__xludf.DUMMYFUNCTION("""COMPUTED_VALUE"""),"Software Engineer- DevOps") -> Software Engineer- DevOps | F59: =IFERROR(__xludf.DUMMYFUNCTION("""COMPUTED_VALUE"""),"DevOps") -> DevOps | G59: =IFERROR(__xludf.DUMMYFUNCTION("""COMPUTED_VALUE"""),"akhilsukhnani@gmail.com") -> akhilsukhnani@gmail.com | H59: =IFERROR(__xludf.DUMMYFUNCTION("""COMPUTED_VALUE"""),"Saurav Yadav") -> Saurav Yadav | I59: =IFERROR(__xludf.DUMMYFUNCTION("""COMPUTED_VALUE"""),45315.0) -> 45315 | J59: =IFERROR(__xludf.DUMMYFUNCTION("""COMPUTED_VALUE"""),"Mamta Pandey") -> Mamta Pandey | K59: =IFERROR(__xludf.DUMMYFUNCTION("""COMPUTED_VALUE"""),"Offer Declined") -> Offer Declined | L59: =IFERROR(__xludf.DUMMYFUNCTION("""COMPUTED_VALUE"""),"In Office") -> In Office
A60: =IFERROR(__xludf.DUMMYFUNCTION("""COMPUTED_VALUE"""),45323.0) -> 45323 | B60: =IFERROR(__xludf.DUMMYFUNCTION("""COMPUTED_VALUE"""),"Abhinav Kaushik") -> Abhinav Kaushik | C60: =IFERROR(__xludf.DUMMYFUNCTION("""COMPUTED_VALUE"""),"Technology") -> Technology | D60: =IFERROR(__xludf.DUMMYFUNCTION("""COMPUTED_VALUE"""),8.44855597E9) -> 8448555970 | E60: =IFERROR(__xludf.DUMMYFUNCTION("""COMPUTED_VALUE"""),"Software Engineer") -> Software Engineer | F60: =IFERROR(__xludf.DUMMYFUNCTION("""COMPUTED_VALUE"""),"DevOps") -> DevOps | G60: =IFERROR(__xludf.DUMMYFUNCTION("""COMPUTED_VALUE""")," ") | H60: =IFERROR(__xludf.DUMMYFUNCTION("""COMPUTED_VALUE"""),"Saurav Yadav") -> Saurav Yadav | I60: =IFERROR(__xludf.DUMMYFUNCTION("""COMPUTED_VALUE"""),45321.0) -> 45321 | J60: =IFERROR(__xludf.DUMMYFUNCTION("""COMPUTED_VALUE"""),"Nidhi Khedekar") -> Nidhi Khedekar | K60: =IFERROR(__xludf.DUMMYFUNCTION("""COMPUTED_VALUE"""),"Offer Declined") -> Offer Declined | L60: =IFERROR(__xludf.DUMMYFUNCTION("""COMPUTED_VALUE"""),"In Office") -> In Office
A61: =IFERROR(__xludf.DUMMYFUNCTION("""COMPUTED_VALUE"""),45323.0) -> 45323 | B61: =IFERROR(__xludf.DUMMYFUNCTION("""COMPUTED_VALUE"""),"Pankaj Garg") -> Pankaj Garg | C61: =IFERROR(__xludf.DUMMYFUNCTION("""COMPUTED_VALUE"""),"Analytics") -> Analytics | D61: =IFERROR(__xludf.DUMMYFUNCTION("""COMPUTED_VALUE"""),7.888513264E9) -> 7888513264 | E61: =IFERROR(__xludf.DUMMYFUNCTION("""COMPUTED_VALUE"""),"Senior Data Analyst") -> Senior Data Analyst | F61: =IFERROR(__xludf.DUMMYFUNCTION("""COMPUTED_VALUE"""),"Product Analytics") -> Product Analytics | G61: =IFERROR(__xludf.DUMMYFUNCTION("""COMPUTED_VALUE"""),"pnkjg264@gmail.com") -> pnkjg264@gmail.com | H61: =IFERROR(__xludf.DUMMYFUNCTION("""COMPUTED_VALUE"""),"Shwetank Anand") -> Shwetank Anand | I61: =IFERROR(__xludf.DUMMYFUNCTION("""COMPUTED_VALUE"""),45321.0) -> 45321 | J61: =IFERROR(__xludf.DUMMYFUNCTION("""COMPUTED_VALUE"""),"Mamta Pandey") -> Mamta Pandey | K61: =IFERROR(__xludf.DUMMYFUNCTION("""COMPUTED_VALUE"""),"Joined") -> Joined | L61: =IFERROR(__xludf.DUMMYFUNCTION("""COMPUTED_VALUE"""),"In Office") -> In Office | M61: =IFERROR(__xludf.DUMMYFUNCTION("""COMPUTED_VALUE"""),"pankaj.garg@zupee.in") -> pankaj.garg@zupee.in
A62: =IFERROR(__xludf.DUMMYFUNCTION("""COMPUTED_VALUE"""),45327.0) -> 45327 | B62: =IFERROR(__xludf.DUMMYFUNCTION("""COMPUTED_VALUE"""),"Kalpana Singh") -> Kalpana Singh | C62: =IFERROR(__xludf.DUMMYFUNCTION("""COMPUTED_VALUE"""),"Customer Experience") -> Customer Experience | D62: =IFERROR(__xludf.DUMMYFUNCTION("""COMPUTED_VALUE"""),7.983234804E9) -> 7983234804 | E62: =IFERROR(__xludf.DUMMYFUNCTION("""COMPUTED_VALUE"""),"Customer Support Executive") -> Customer Support Executive | F62: =IFERROR(__xludf.DUMMYFUNCTION("""COMPUTED_VALUE"""),"Customer Relation Management") -> Customer Relation Management | G62: =IFERROR(__xludf.DUMMYFUNCTION("""COMPUTED_VALUE"""),"kskalpanasingh22@gmail.com") -> kskalpanasingh22@gmail.com | H62: =IFERROR(__xludf.DUMMYFUNCTION("""COMPUTED_VALUE"""),"Shivam Bali") -> Shivam Bali | I62: =IFERROR(__xludf.DUMMYFUNCTION("""COMPUTED_VALUE"""),45323.0) -> 45323 | J62: =IFERROR(__xludf.DUMMYFUNCTION("""COMPUTED_VALUE"""),"Nidhi Khedekar") -> Nidhi Khedekar | K62: =IFERROR(__xludf.DUMMYFUNCTION("""COMPUTED_VALUE"""),"Joined") -> Joined | L62: =IFERROR(__xludf.DUMMYFUNCTION("""COMPUTED_VALUE"""),"In Office") -> In Office | M62: =IFERROR(__xludf.DUMMYFUNCTION("""COMPUTED_VALUE"""),"kalpana.singh@zupee.in") -> kalpana.singh@zupee.in
A63: =IFERROR(__xludf.DUMMYFUNCTION("""COMPUTED_VALUE"""),45327.0) -> 45327 | B63: =IFERROR(__xludf.DUMMYFUNCTION("""COMPUTED_VALUE"""),"Saurabh Dandriyal") -> Saurabh Dandriyal | C63: =IFERROR(__xludf.DUMMYFUNCTION("""COMPUTED_VALUE"""),"Customer Experience") -> Customer Experience | D63: =IFERROR(__xludf.DUMMYFUNCTION("""COMPUTED_VALUE"""),8.130038575E9) -> 8130038575 | E63: =IFERROR(__xludf.DUMMYFUNCTION("""COMPUTED_VALUE"""),"Senior Executive- Customer Experience") -> Senior Executive- Customer Experience | F63: =IFERROR(__xludf.DUMMYFUNCTION("""COMPUTED_VALUE"""),"Customer Relation Management") -> Customer Relation Management | G63: =IFERROR(__xludf.DUMMYFUNCTION("""COMPUTED_VALUE"""),"dandriyalsaurabh007@gmail.com") -> dandriyalsaurabh007@gmail.com | H63: =IFERROR(__xludf.DUMMYFUNCTION("""COMPUTED_VALUE"""),"Shivam Bali") -> Shivam Bali | I63: =IFERROR(__xludf.DUMMYFUNCTION("""COMPUTED_VALUE"""),45323.0) -> 45323 | J63: =IFERROR(__xludf.DUMMYFUNCTION("""COMPUTED_VALUE"""),"Nidhi Khedekar") -> Nidhi Khedekar | K63: =IFERROR(__xludf.DUMMYFUNCTION("""COMPUTED_VALUE"""),"Joined") -> Joined | L63: =IFERROR(__xludf.DUMMYFUNCTION("""COMPUTED_VALUE"""),"In Office") -> In Office | M63: =IFERROR(__xludf.DUMMYFUNCTION("""COMPUTED_VALUE"""),"saurabh.dandriyal@zupee.in") -> saurabh.dandriyal@zupee.in
A64: =IFERROR(__xludf.DUMMYFUNCTION("""COMPUTED_VALUE"""),45327.0) -> 45327 | B64: =IFERROR(__xludf.DUMMYFUNCTION("""COMPUTED_VALUE"""),"Divyansh Singh") -> Divyansh Singh | C64: =IFERROR(__xludf.DUMMYFUNCTION("""COMPUTED_VALUE"""),"Technology") -> Technology | D64: =IFERROR(__xludf.DUMMYFUNCTION("""COMPUTED_VALUE"""),7.007397536E9) -> 7007397536 | E64: =IFERROR(__xludf.DUMMYFUNCTION("""COMPUTED_VALUE"""),"Software Engineer- DevOps") -> Software Engineer- DevOps | F64: =IFERROR(__xludf.DUMMYFUNCTION("""COMPUTED_VALUE"""),"DevOps") -> DevOps | G64: =IFERROR(__xludf.DUMMYFUNCTION("""COMPUTED_VALUE"""),"imdivyansh99@gmail.com") -> imdivyansh99@gmail.com | H64: =IFERROR(__xludf.DUMMYFUNCTION("""COMPUTED_VALUE"""),"Saurav Yadav") -> Saurav Yadav | I64: =IFERROR(__xludf.DUMMYFUNCTION("""COMPUTED_VALUE"""),45324.0) -> 45324 | J64: =IFERROR(__xludf.DUMMYFUNCTION("""COMPUTED_VALUE"""),"Nidhi Khedekar") -> Nidhi Khedekar | K64: =IFERROR(__xludf.DUMMYFUNCTION("""COMPUTED_VALUE"""),"Joined") -> Joined | L64: =IFERROR(__xludf.DUMMYFUNCTION("""COMPUTED_VALUE"""),"In Office") -> In Office | M64: =IFERROR(__xludf.DUMMYFUNCTION("""COMPUTED_VALUE"""),"divyansh.singh@zupee.in") -> divyansh.singh@zupee.in
A65: =IFERROR(__xludf.DUMMYFUNCTION("""COMPUTED_VALUE"""),45341.0) -> 45341 | B65: =IFERROR(__xludf.DUMMYFUNCTION("""COMPUTED_VALUE"""),"Yakshita Behl") -> Yakshita Behl | C65: =IFERROR(__xludf.DUMMYFUNCTION("""COMPUTED_VALUE"""),"Analytics") -> Analytics | D65: =IFERROR(__xludf.DUMMYFUNCTION("""COMPUTED_VALUE"""),9.311560404E9) -> 9311560404 | E65: =IFERROR(__xludf.DUMMYFUNCTION("""COMPUTED_VALUE"""),"Data Analyst") -> Data Analyst | F65: =IFERROR(__xludf.DUMMYFUNCTION("""COMPUTED_VALUE"""),"Product Analytics") -> Product Analytics | G65: =IFERROR(__xludf.DUMMYFUNCTION("""COMPUTED_VALUE"""),"yakshitabehl2000@gmail.com") -> yakshitabehl2000@gmail.com | H65: =IFERROR(__xludf.DUMMYFUNCTION("""COMPUTED_VALUE"""),"Shwetank Anand") -> Shwetank Anand | I65: =IFERROR(__xludf.DUMMYFUNCTION("""COMPUTED_VALUE"""),45324.0) -> 45324 | J65: =IFERROR(__xludf.DUMMYFUNCTION("""COMPUTED_VALUE"""),"Nidhi Khedekar") -> Nidhi Khedekar | K65: =IFERROR(__xludf.DUMMYFUNCTION("""COMPUTED_VALUE"""),"Joined") -> Joined | L65: =IFERROR(__xludf.DUMMYFUNCTION("""COMPUTED_VALUE"""),"In Office") -> In Office | M65: =IFERROR(__xludf.DUMMYFUNCTION("""COMPUTED_VALUE"""),"yakshita.behl@zupee.in") -> yakshita.behl@zupee.in
A66: =IFERROR(__xludf.DUMMYFUNCTION("""COMPUTED_VALUE"""),45329.0) -> 45329 | B66: =IFERROR(__xludf.DUMMYFUNCTION("""COMPUTED_VALUE"""),"Vimal Prajapati") -> Vimal Prajapati | C66: =IFERROR(__xludf.DUMMYFUNCTION("""COMPUTED_VALUE"""),"Analytics") -> Analytics | D66: =IFERROR(__xludf.DUMMYFUNCTION("""COMPUTED_VALUE"""),9.974477347E9) -> 9974477347 | E66: =IFERROR(__xludf.DUMMYFUNCTION("""COMPUTED_VALUE"""),"Lead Data Analyst") -> Lead Data Analyst | F66: =IFERROR(__xludf.DUMMYFUNCTION("""COMPUTED_VALUE"""),"Product Analytics") -> Product Analytics | G66: =IFERROR(__xludf.DUMMYFUNCTION("""COMPUTED_VALUE"""),"vimalcprajapati1995@gmail.com") -> vimalcprajapati1995@gmail.com | H66: =IFERROR(__xludf.DUMMYFUNCTION("""COMPUTED_VALUE"""),"Shwetank Anand") -> Shwetank Anand | I66: =IFERROR(__xludf.DUMMYFUNCTION("""COMPUTED_VALUE"""),45328.0) -> 45328 | J66: =IFERROR(__xludf.DUMMYFUNCTION("""COMPUTED_VALUE"""),"Mamta Pandey") -> Mamta Pandey | K66: =IFERROR(__xludf.DUMMYFUNCTION("""COMPUTED_VALUE"""),"Joined") -> Joined | L66: =IFERROR(__xludf.DUMMYFUNCTION("""COMPUTED_VALUE"""),"Virtual") -> Virtual | M66: =IFERROR(__xludf.DUMMYFUNCTION("""COMPUTED_VALUE"""),"vimal.prajapati@zupee.in") -> vimal.prajapati@zupee.in
A67: =IFERROR(__xludf.DUMMYFUNCTION("""COMPUTED_VALUE"""),45331.0) -> 45331 | B67: =IFERROR(__xludf.DUMMYFUNCTION("""COMPUTED_VALUE"""),"Himanshu Grover") -> Himanshu Grover | C67: =IFERROR(__xludf.DUMMYFUNCTION("""COMPUTED_VALUE"""),"Analytics") -> Analytics | D67: =IFERROR(__xludf.DUMMYFUNCTION("""COMPUTED_VALUE"""),9.996867358E9) -> 9996867358 | E67: =IFERROR(__xludf.DUMMYFUNCTION("""COMPUTED_VALUE"""),"Senior Manager- Data Analytics") -> Senior Manager- Data Analytics | F67: =IFERROR(__xludf.DUMMYFUNCTION("""COMPUTED_VALUE"""),"Product Analytics") -> Product Analytics | G67: =IFERROR(__xludf.DUMMYFUNCTION("""COMPUTED_VALUE"""),"groverh99@gmail.com") -> groverh99@gmail.com | H67: =IFERROR(__xludf.DUMMYFUNCTION("""COMPUTED_VALUE"""),"Shwetank Anand") -> Shwetank Anand | I67: =IFERROR(__xludf.DUMMYFUNCTION("""COMPUTED_VALUE"""),45330.0) -> 45330 | J67: =IFERROR(__xludf.DUMMYFUNCTION("""COMPUTED_VALUE"""),"M Sangeetha") -> M Sangeetha | K67: =IFERROR(__xludf.DUMMYFUNCTION("""COMPUTED_VALUE"""),"Joined") -> Joined | L67: =IFERROR(__xludf.DUMMYFUNCTION("""COMPUTED_VALUE"""),"In Office") -> In Office | M67: =IFERROR(__xludf.DUMMYFUNCTION("""COMPUTED_VALUE"""),"himanshu.grover@zupee.in") -> himanshu.grover@zupee.in
A68: =IFERROR(__xludf.DUMMYFUNCTION("""COMPUTED_VALUE"""),45362.0) -> 45362 | B68: =IFERROR(__xludf.DUMMYFUNCTION("""COMPUTED_VALUE"""),"Anil Meher") -> Anil Meher | C68: =IFERROR(__xludf.DUMMYFUNCTION("""COMPUTED_VALUE"""),"Finance") -> Finance | D68: =IFERROR(__xludf.DUMMYFUNCTION("""COMPUTED_VALUE"""),9.911013546E9) -> 9911013546 | E68: =IFERROR(__xludf.DUMMYFUNCTION("""COMPUTED_VALUE"""),"Assistant Manager- Finance") -> Assistant Manager- Finance | F68: =IFERROR(__xludf.DUMMYFUNCTION("""COMPUTED_VALUE"""),"Finance") -> Finance | G68: =IFERROR(__xludf.DUMMYFUNCTION("""COMPUTED_VALUE"""),"anilmeher1995@gmail.com") -> anilmeher1995@gmail.com | H68: =IFERROR(__xludf.DUMMYFUNCTION("""COMPUTED_VALUE"""),"Hitesh Vats") -> Hitesh Vats | I68: =IFERROR(__xludf.DUMMYFUNCTION("""COMPUTED_VALUE"""),45330.0) -> 45330 | J68: =IFERROR(__xludf.DUMMYFUNCTION("""COMPUTED_VALUE"""),"Nidhi Khedekar") -> Nidhi Khedekar | K68: =IFERROR(__xludf.DUMMYFUNCTION("""COMPUTED_VALUE"""),"Joined") -> Joined | L68: =IFERROR(__xludf.DUMMYFUNCTION("""COMPUTED_VALUE"""),"In Office") -> In Office | M68: =IFERROR(__xludf.DUMMYFUNCTION("""COMPUTED_VALUE"""),"anil.meher@zupee.in") -> anil.meher@zupee.in
A69: =IFERROR(__xludf.DUMMYFUNCTION("""COMPUTED_VALUE"""),45355.0) -> 45355 | B69: =IFERROR(__xludf.DUMMYFUNCTION("""COMPUTED_VALUE"""),"Priya Biswas") -> Priya Biswas | C69: =IFERROR(__xludf.DUMMYFUNCTION("""COMPUTED_VALUE"""),"Customer Experience") -> Customer Experience | D69: =IFERROR(__xludf.DUMMYFUNCTION("""COMPUTED_VALUE"""),8.810294269E9) -> 8810294269 | E69: =IFERROR(__xludf.DUMMYFUNCTION("""COMPUTED_VALUE"""),"Quality Auditor- Executive") -> Quality Auditor- Executive | F69: =IFERROR(__xludf.DUMMYFUNCTION("""COMPUTED_VALUE"""),"Customer Relation Management") -> Customer Relation Management | G69: =IFERROR(__xludf.DUMMYFUNCTION("""COMPUTED_VALUE"""),"priyabiswas2001rita@gmail.com") -> priyabiswas2001rita@gmail.com | H69: =IFERROR(__xludf.DUMMYFUNCTION("""COMPUTED_VALUE"""),"Alankrita Sharma") -> Alankrita Sharma | I69: =IFERROR(__xludf.DUMMYFUNCTION("""COMPUTED_VALUE"""),45331.0) -> 45331 | J69: =IFERROR(__xludf.DUMMYFUNCTION("""COMPUTED_VALUE"""),"Nidhi Khedekar") -> Nidhi Khedekar | K69: =IFERROR(__xludf.DUMMYFUNCTION("""COMPUTED_VALUE"""),"Offer Declined") -> Offer Declined | L69: =IFERROR(__xludf.DUMMYFUNCTION("""COMPUTED_VALUE"""),"In Office") -> In Office
A70: =IFERROR(__xludf.DUMMYFUNCTION("""COMPUTED_VALUE"""),45334.0) -> 45334 | B70: =IFERROR(__xludf.DUMMYFUNCTION("""COMPUTED_VALUE"""),"Shameek Data") -> Shameek Data | C70: =IFERROR(__xludf.DUMMYFUNCTION("""COMPUTED_VALUE"""),"Strategy") -> Strategy | D70: =IFERROR(__xludf.DUMMYFUNCTION("""COMPUTED_VALUE"""),7.827930396E9) -> 7827930396 | E70: =IFERROR(__xludf.DUMMYFUNCTION("""COMPUTED_VALUE"""),"Manager- Strategy") -> Manager- Strategy | F70: =IFERROR(__xludf.DUMMYFUNCTION("""COMPUTED_VALUE"""),"Strategy") -> Strategy | G70: =IFERROR(__xludf.DUMMYFUNCTION("""COMPUTED_VALUE"""),"p17shameekd@iima.ac.in") -> p17shameekd@iima.ac.in | H70: =IFERROR(__xludf.DUMMYFUNCTION("""COMPUTED_VALUE"""),"Akanksha Dhamija") -> Akanksha Dhamija | I70: =IFERROR(__xludf.DUMMYFUNCTION("""COMPUTED_VALUE"""),45327.0) -> 45327 | J70: =IFERROR(__xludf.DUMMYFUNCTION("""COMPUTED_VALUE"""),"Rajneesh Yadav") -> Rajneesh Yadav | K70: =IFERROR(__xludf.DUMMYFUNCTION("""COMPUTED_VALUE"""),"Joined") -> Joined | L70: =IFERROR(__xludf.DUMMYFUNCTION("""COMPUTED_VALUE"""),"In Office") -> In Office
A71: =IFERROR(__xludf.DUMMYFUNCTION("""COMPUTED_VALUE"""),45341.0) -> 45341 | B71: =IFERROR(__xludf.DUMMYFUNCTION("""COMPUTED_VALUE"""),"Sumit Yadav") -> Sumit Yadav | C71: =IFERROR(__xludf.DUMMYFUNCTION("""COMPUTED_VALUE"""),"Customer Experience") -> Customer Experience | D71: =IFERROR(__xludf.DUMMYFUNCTION("""COMPUTED_VALUE"""),9.990123068E9) -> 9990123068 | E71: =IFERROR(__xludf.DUMMYFUNCTION("""COMPUTED_VALUE"""),"Head- Customer Relationship Management") -> Head- Customer Relationship Management | F71: =IFERROR(__xludf.DUMMYFUNCTION("""COMPUTED_VALUE"""),"Customer Relation Management") -> Customer Relation Management | G71: =IFERROR(__xludf.DUMMYFUNCTION("""COMPUTED_VALUE"""),"sumit.magus@gmail.com") -> sumit.magus@gmail.com | H71: =IFERROR(__xludf.DUMMYFUNCTION("""COMPUTED_VALUE"""),"Shwetank Anand") -> Shwetank Anand | I71: =IFERROR(__xludf.DUMMYFUNCTION("""COMPUTED_VALUE"""),45331.0) -> 45331 | J71: =IFERROR(__xludf.DUMMYFUNCTION("""COMPUTED_VALUE"""),"Surabhi Sanchita") -> Surabhi Sanchita | K71: =IFERROR(__xludf.DUMMYFUNCTION("""COMPUTED_VALUE"""),"Joined") -> Joined | L71: =IFERROR(__xludf.DUMMYFUNCTION("""COMPUTED_VALUE"""),"In Office") -> In Office | M71: =IFERROR(__xludf.DUMMYFUNCTION("""COMPUTED_VALUE"""),"sumit.yadav@zupee.in") -> sumit.yadav@zupee.in | N71: =IFERROR(__xludf.DUMMYFUNCTION("""COMPUTED_VALUE"""),"DTGFCY3") -> DTGFCY3
A72: =IFERROR(__xludf.DUMMYFUNCTION("""COMPUTED_VALUE"""),45341.0) -> 45341 | B72: =IFERROR(__xludf.DUMMYFUNCTION("""COMPUTED_VALUE"""),"Vikram Singh Bhadoriya") -> Vikram Singh Bhadoriya | C72: =IFERROR(__xludf.DUMMYFUNCTION("""COMPUTED_VALUE"""),"Customer Experience") -> Customer Experience | D72: =IFERROR(__xludf.DUMMYFUNCTION("""COMPUTED_VALUE"""),8.448476405E9) -> 8448476405 | E72: =IFERROR(__xludf.DUMMYFUNCTION("""COMPUTED_VALUE"""),"Senior Executive- Customer Experience") -> Senior Executive- Customer Experience | F72: =IFERROR(__xludf.DUMMYFUNCTION("""COMPUTED_VALUE"""),"Customer Relation Management") -> Customer Relation Management | G72: =IFERROR(__xludf.DUMMYFUNCTION("""COMPUTED_VALUE""")," vikramsinghitmuniv@gmail.com") -> vikramsinghitmuniv@gmail.com | H72: =IFERROR(__xludf.DUMMYFUNCTION("""COMPUTED_VALUE"""),"Shivam Bali") -> Shivam Bali | I72: =IFERROR(__xludf.DUMMYFUNCTION("""COMPUTED_VALUE"""),45331.0) -> 45331 | J72: =IFERROR(__xludf.DUMMYFUNCTION("""COMPUTED_VALUE"""),"Nidhi Khedekar") -> Nidhi Khedekar | K72: =IFERROR(__xludf.DUMMYFUNCTION("""COMPUTED_VALUE"""),"Joined") -> Joined | L72: =IFERROR(__xludf.DUMMYFUNCTION("""COMPUTED_VALUE"""),"In Office") -> In Office
A73: =IFERROR(__xludf.DUMMYFUNCTION("""COMPUTED_VALUE"""),45343.0) -> 45343 | B73: =IFERROR(__xludf.DUMMYFUNCTION("""COMPUTED_VALUE"""),"Vikas Joshi") -> Vikas Joshi | C73: =IFERROR(__xludf.DUMMYFUNCTION("""COMPUTED_VALUE"""),"Customer Experience") -> Customer Experience | D73: =IFERROR(__xludf.DUMMYFUNCTION("""COMPUTED_VALUE"""),7.048938639E9) -> 7048938639 | E73: =IFERROR(__xludf.DUMMYFUNCTION("""COMPUTED_VALUE"""),"Senior Executive- Customer Experience") -> Senior Executive- Customer Experience | F73: =IFERROR(__xludf.DUMMYFUNCTION("""COMPUTED_VALUE"""),"Customer Relation Management") -> Customer Relation Management | G73: =IFERROR(__xludf.DUMMYFUNCTION("""COMPUTED_VALUE"""),"vikasjoshi970@gmail.com") -> vikasjoshi970@gmail.com | H73: =IFERROR(__xludf.DUMMYFUNCTION("""COMPUTED_VALUE"""),"Shivam Bali") -> Shivam Bali | I73: =IFERROR(__xludf.DUMMYFUNCTION("""COMPUTED_VALUE"""),45342.0) -> 45342 | J73: =IFERROR(__xludf.DUMMYFUNCTION("""COMPUTED_VALUE"""),"Nidhi Khedekar") -> Nidhi Khedekar | K73: =IFERROR(__xludf.DUMMYFUNCTION("""COMPUTED_VALUE"""),"Joined") -> Joined | L73: =IFERROR(__xludf.DUMMYFUNCTION("""COMPUTED_VALUE"""),"In Office") -> In Office | M73: =IFERROR(__xludf.DUMMYFUNCTION("""COMPUTED_VALUE"""),"vikas.joshi@zupee.in") -> vikas.joshi@zupee.in
A74: =IFERROR(__xludf.DUMMYFUNCTION("""COMPUTED_VALUE"""),45344.0) -> 45344 | B74: =IFERROR(__xludf.DUMMYFUNCTION("""COMPUTED_VALUE"""),"Anand Keshav") -> Anand Keshav | C74: =IFERROR(__xludf.DUMMYFUNCTION("""COMPUTED_VALUE"""),"Data Science") -> Data Science | D74: =IFERROR(__xludf.DUMMYFUNCTION("""COMPUTED_VALUE"""),9.798729457E9) -> 9798729457 | E74: =IFERROR(__xludf.DUMMYFUNCTION("""COMPUTED_VALUE"""),"Data Science Trainee") -> Data Science Trainee | F74: =IFERROR(__xludf.DUMMYFUNCTION("""COMPUTED_VALUE"""),"Data Science") -> Data Science | G74: =IFERROR(__xludf.DUMMYFUNCTION("""COMPUTED_VALUE"""),"anandkeshav5454@gmail.com") -> anandkeshav5454@gmail.com | H74: =IFERROR(__xludf.DUMMYFUNCTION("""COMPUTED_VALUE"""),"Priyanshu Jain") -> Priyanshu Jain | I74: =IFERROR(__xludf.DUMMYFUNCTION("""COMPUTED_VALUE"""),45342.0) -> 45342 | J74: =IFERROR(__xludf.DUMMYFUNCTION("""COMPUTED_VALUE"""),"Nidhi Khedekar") -> Nidhi Khedekar | K74: =IFERROR(__xludf.DUMMYFUNCTION("""COMPUTED_VALUE"""),"Joined") -> Joined | L74: =IFERROR(__xludf.DUMMYFUNCTION("""COMPUTED_VALUE"""),"In Office") -> In Office | M74: =IFERROR(__xludf.DUMMYFUNCTION("""COMPUTED_VALUE"""),"anand.keshav@zupee.in") -> anand.keshav@zupee.in | N74: =IFERROR(__xludf.DUMMYFUNCTION("""COMPUTED_VALUE"""),"DF7VFG3X74") -> DF7VFG3X74
A75: =IFERROR(__xludf.DUMMYFUNCTION("""COMPUTED_VALUE"""),45348.0) -> 45348 | B75: =IFERROR(__xludf.DUMMYFUNCTION("""COMPUTED_VALUE"""),"Rajat Garg") -> Rajat Garg | C75: =IFERROR(__xludf.DUMMYFUNCTION("""COMPUTED_VALUE"""),"Analytics") -> Analytics | D75: =IFERROR(__xludf.DUMMYFUNCTION("""COMPUTED_VALUE"""),8.209384565E9) -> 8209384565 | E75: =IFERROR(__xludf.DUMMYFUNCTION("""COMPUTED_VALUE"""),"Lead Data Analyst") -> Lead Data Analyst | F75: =IFERROR(__xludf.DUMMYFUNCTION("""COMPUTED_VALUE"""),"Product Analytics") -> Product Analytics | G75: =IFERROR(__xludf.DUMMYFUNCTION("""COMPUTED_VALUE"""),"rgargrajatgarg@gmail.com") -> rgargrajatgarg@gmail.com | H75: =IFERROR(__xludf.DUMMYFUNCTION("""COMPUTED_VALUE"""),"Shwetank Anand") -> Shwetank Anand | I75: =IFERROR(__xludf.DUMMYFUNCTION("""COMPUTED_VALUE"""),45343.0) -> 45343 | J75: =IFERROR(__xludf.DUMMYFUNCTION("""COMPUTED_VALUE"""),"Mamta Pandey") -> Mamta Pandey | K75: =IFERROR(__xludf.DUMMYFUNCTION("""COMPUTED_VALUE"""),"Joined") -> Joined | L75: =IFERROR(__xludf.DUMMYFUNCTION("""COMPUTED_VALUE"""),"In Office") -> In Office | M75: =IFERROR(__xludf.DUMMYFUNCTION("""COMPUTED_VALUE"""),"rajat.garg@zupee.in") -> rajat.garg@zupee.in | N75: =IFERROR(__xludf.DUMMYFUNCTION("""COMPUTED_VALUE"""),"CNXX7Y7TC9") -> CNXX7Y7TC9
A76: =IFERROR(__xludf.DUMMYFUNCTION("""COMPUTED_VALUE"""),45371.0) -> 45371 | B76: =IFERROR(__xludf.DUMMYFUNCTION("""COMPUTED_VALUE"""),"Ankur Agarwal") -> Ankur Agarwal | C76: =IFERROR(__xludf.DUMMYFUNCTION("""COMPUTED_VALUE"""),"Finance") -> Finance | D76: =IFERROR(__xludf.DUMMYFUNCTION("""COMPUTED_VALUE"""),8.800577791E9) -> 8800577791 | E76: =IFERROR(__xludf.DUMMYFUNCTION("""COMPUTED_VALUE"""),"Financial Controller") -> Financial Controller | F76: =IFERROR(__xludf.DUMMYFUNCTION("""COMPUTED_VALUE"""),"Finance") -> Finance | G76: =IFERROR(__xludf.DUMMYFUNCTION("""COMPUTED_VALUE"""),"agarwal.ankur1312@gmail.com") -> agarwal.ankur1312@gmail.com | H76: =IFERROR(__xludf.DUMMYFUNCTION("""COMPUTED_VALUE"""),"Sumit Chugh") -> Sumit Chugh | I76: =IFERROR(__xludf.DUMMYFUNCTION("""COMPUTED_VALUE"""),45342.0) -> 45342 | J76: =IFERROR(__xludf.DUMMYFUNCTION("""COMPUTED_VALUE"""),"Rajneesh Yadav") -> Rajneesh Yadav | K76: =IFERROR(__xludf.DUMMYFUNCTION("""COMPUTED_VALUE"""),"Joined") -> Joined | L76: =IFERROR(__xludf.DUMMYFUNCTION("""COMPUTED_VALUE"""),"In Office") -> In Office | M76: =IFERROR(__xludf.DUMMYFUNCTION("""COMPUTED_VALUE"""),"ankur.agarwal@zupee.in") -> ankur.agarwal@zupee.in
A77: =IFERROR(__xludf.DUMMYFUNCTION("""COMPUTED_VALUE"""),45387.0) -> 45387 | B77: =IFERROR(__xludf.DUMMYFUNCTION("""COMPUTED_VALUE"""),"Ayush Garg") -> Ayush Garg | C77: =IFERROR(__xludf.DUMMYFUNCTION("""COMPUTED_VALUE"""),"Finance") -> Finance | D77: =IFERROR(__xludf.DUMMYFUNCTION("""COMPUTED_VALUE"""),9.873858951E9) -> 9873858951 | E77: =IFERROR(__xludf.DUMMYFUNCTION("""COMPUTED_VALUE"""),"Manager - Taxation") -> Manager - Taxation | F77: =IFERROR(__xludf.DUMMYFUNCTION("""COMPUTED_VALUE"""),"Finance") -> Finance | G77: =IFERROR(__xludf.DUMMYFUNCTION("""COMPUTED_VALUE"""),"caayushgarg01@gmail.com") -> caayushgarg01@gmail.com | H77: =IFERROR(__xludf.DUMMYFUNCTION("""COMPUTED_VALUE"""),"Vijay MR") -> Vijay MR | I77: =IFERROR(__xludf.DUMMYFUNCTION("""COMPUTED_VALUE"""),45327.0) -> 45327 | J77: =IFERROR(__xludf.DUMMYFUNCTION("""COMPUTED_VALUE"""),"Naina") -> Naina | K77: =IFERROR(__xludf.DUMMYFUNCTION("""COMPUTED_VALUE"""),"Offer Declined") -> Offer Declined | L77: =IFERROR(__xludf.DUMMYFUNCTION("""COMPUTED_VALUE"""),"In Office") -> In Office
A78: =IFERROR(__xludf.DUMMYFUNCTION("""COMPUTED_VALUE"""),45383.0) -> 45383 | B78: =IFERROR(__xludf.DUMMYFUNCTION("""COMPUTED_VALUE"""),"Kritika Maheshwari") -> Kritika Maheshwari | C78: =IFERROR(__xludf.DUMMYFUNCTION("""COMPUTED_VALUE"""),"Finance") -> Finance | D78: =IFERROR(__xludf.DUMMYFUNCTION("""COMPUTED_VALUE"""),9.627634268E9) -> 9627634268 | E78: =IFERROR(__xludf.DUMMYFUNCTION("""COMPUTED_VALUE"""),"Manager- Business Finance") -> Manager- Business Finance | F78: =IFERROR(__xludf.DUMMYFUNCTION("""COMPUTED_VALUE"""),"Finance") -> Finance | G78: =IFERROR(__xludf.DUMMYFUNCTION("""COMPUTED_VALUE"""),"cakritikamaheshwari22@gmail.com") -> cakritikamaheshwari22@gmail.com | H78: =IFERROR(__xludf.DUMMYFUNCTION("""COMPUTED_VALUE"""),"Garima Bothra") -> Garima Bothra | I78: =IFERROR(__xludf.DUMMYFUNCTION("""COMPUTED_VALUE"""),45348.0) -> 45348 | J78: =IFERROR(__xludf.DUMMYFUNCTION("""COMPUTED_VALUE"""),"Nidhi Khedekar") -> Nidhi Khedekar | K78: =IFERROR(__xludf.DUMMYFUNCTION("""COMPUTED_VALUE"""),"Offer Declined") -> Offer Declined | L78: =IFERROR(__xludf.DUMMYFUNCTION("""COMPUTED_VALUE"""),"In Office") -> In Office
A79: =IFERROR(__xludf.DUMMYFUNCTION("""COMPUTED_VALUE"""),45357.0) -> 45357 | B79: =IFERROR(__xludf.DUMMYFUNCTION("""COMPUTED_VALUE"""),"Varun Pandey") -> Varun Pandey | C79: =IFERROR(__xludf.DUMMYFUNCTION("""COMPUTED_VALUE"""),"Product") -> Product | D79: =IFERROR(__xludf.DUMMYFUNCTION("""COMPUTED_VALUE"""),8.800909261E9) -> 8800909261 | E79: =IFERROR(__xludf.DUMMYFUNCTION("""COMPUTED_VALUE"""),"UX Researcher") -> UX Researcher | F79: =IFERROR(__xludf.DUMMYFUNCTION("""COMPUTED_VALUE"""),"Design") -> Design | G79: =IFERROR(__xludf.DUMMYFUNCTION("""COMPUTED_VALUE"""),"varun.pandey@outlook.in") -> varun.pandey@outlook.in | H79: =IFERROR(__xludf.DUMMYFUNCTION("""COMPUTED_VALUE"""),"Pareena Singh") -> Pareena Singh | I79: =IFERROR(__xludf.DUMMYFUNCTION("""COMPUTED_VALUE"""),45350.0) -> 45350 | J79: =IFERROR(__xludf.DUMMYFUNCTION("""COMPUTED_VALUE"""),"Naina") -> Naina | K79: =IFERROR(__xludf.DUMMYFUNCTION("""COMPUTED_VALUE"""),"Offer Declined") -> Offer Declined | L79: =IFERROR(__xludf.DUMMYFUNCTION("""COMPUTED_VALUE"""),"In Office") -> In Office
A80: =IFERROR(__xludf.DUMMYFUNCTION("""COMPUTED_VALUE"""),45357.0) -> 45357 | B80: =IFERROR(__xludf.DUMMYFUNCTION("""COMPUTED_VALUE"""),"Iqra Islam") -> Iqra Islam | C80: =IFERROR(__xludf.DUMMYFUNCTION("""COMPUTED_VALUE"""),"Customer Experience") -> Customer Experience | D80: =IFERROR(__xludf.DUMMYFUNCTION("""COMPUTED_VALUE"""),9.690255071E9) -> 9690255071 | E80: =IFERROR(__xludf.DUMMYFUNCTION("""COMPUTED_VALUE"""),"Customer Support Executive") -> Customer Support Executive | F80: =IFERROR(__xludf.DUMMYFUNCTION("""COMPUTED_VALUE"""),"Customer Relation Management") -> Customer Relation Management | G80: =IFERROR(__xludf.DUMMYFUNCTION("""COMPUTED_VALUE""")," islamiqra999@gmail.com") -> islamiqra999@gmail.com | H80: =IFERROR(__xludf.DUMMYFUNCTION("""COMPUTED_VALUE"""),"Shivam Bali") -> Shivam Bali | I80: =IFERROR(__xludf.DUMMYFUNCTION("""COMPUTED_VALUE"""),45350.0) -> 45350 | J80: =IFERROR(__xludf.DUMMYFUNCTION("""COMPUTED_VALUE"""),"Nidhi Khedekar") -> Nidhi Khedekar | K80: =IFERROR(__xludf.DUMMYFUNCTION("""COMPUTED_VALUE"""),"Joined") -> Joined | L80: =IFERROR(__xludf.DUMMYFUNCTION("""COMPUTED_VALUE"""),"In Office") -> In Office | M80: =IFERROR(__xludf.DUMMYFUNCTION("""COMPUTED_VALUE"""),"iqra.islam@zupee.in") -> iqra.islam@zupee.in
A81: =IFERROR(__xludf.DUMMYFUNCTION("""COMPUTED_VALUE"""),45355.0) -> 45355 | B81: =IFERROR(__xludf.DUMMYFUNCTION("""COMPUTED_VALUE"""),"Joel Jacob") -> Joel Jacob | C81: =IFERROR(__xludf.DUMMYFUNCTION("""COMPUTED_VALUE"""),"Analytics") -> Analytics | D81: =IFERROR(__xludf.DUMMYFUNCTION("""COMPUTED_VALUE"""),9.742048811E9) -> 9742048811 | E81: =IFERROR(__xludf.DUMMYFUNCTION("""COMPUTED_VALUE"""),"Lead Data Analyst") -> Lead Data Analyst | F81: =IFERROR(__xludf.DUMMYFUNCTION("""COMPUTED_VALUE"""),"Product Analytics") -> Product Analytics | G81: =IFERROR(__xludf.DUMMYFUNCTION("""COMPUTED_VALUE"""),"joel_modayil@yahoo.in ") -> joel_modayil@yahoo.in | H81: =IFERROR(__xludf.DUMMYFUNCTION("""COMPUTED_VALUE"""),"Shwetank Anand") -> Shwetank Anand | I81: =IFERROR(__xludf.DUMMYFUNCTION("""COMPUTED_VALUE"""),45350.0) -> 45350 | J81: =IFERROR(__xludf.DUMMYFUNCTION("""COMPUTED_VALUE"""),"Mamta Pandey") -> Mamta Pandey | K81: =IFERROR(__xludf.DUMMYFUNCTION("""COMPUTED_VALUE"""),"Offer Declined") -> Offer Declined | L81: =IFERROR(__xludf.DUMMYFUNCTION("""COMPUTED_VALUE"""),"In Office") -> In Office
A82: =IFERROR(__xludf.DUMMYFUNCTION("""COMPUTED_VALUE"""),45365.0) -> 45365 | B82: =IFERROR(__xludf.DUMMYFUNCTION("""COMPUTED_VALUE"""),"Shiv Kumar") -> Shiv Kumar | C82: =IFERROR(__xludf.DUMMYFUNCTION("""COMPUTED_VALUE"""),"Corporate") -> Corporate | D82: =IFERROR(__xludf.DUMMYFUNCTION("""COMPUTED_VALUE"""),9.306910581E9) -> 9306910581 | E82: =IFERROR(__xludf.DUMMYFUNCTION("""COMPUTED_VALUE"""),"IT Executive") -> IT Executive | F82: =IFERROR(__xludf.DUMMYFUNCTION("""COMPUTED_VALUE"""),"Administration") -> Administration | G82: =IFERROR(__xludf.DUMMYFUNCTION("""COMPUTED_VALUE"""),"Shivconiyal@gmail.com") -> Shivconiyal@gmail.com | H82: =IFERROR(__xludf.DUMMYFUNCTION("""COMPUTED_VALUE"""),"Rajkumar Singh") -> Rajkumar Singh | I82: =IFERROR(__xludf.DUMMYFUNCTION("""COMPUTED_VALUE"""),45350.0) -> 45350 | J82: =IFERROR(__xludf.DUMMYFUNCTION("""COMPUTED_VALUE"""),"Mamta Pandey") -> Mamta Pandey | K82: =IFERROR(__xludf.DUMMYFUNCTION("""COMPUTED_VALUE"""),"Joined") -> Joined | L82: =IFERROR(__xludf.DUMMYFUNCTION("""COMPUTED_VALUE"""),"In Office") -> In Office | M82: =IFERROR(__xludf.DUMMYFUNCTION("""COMPUTED_VALUE"""),"shiv.k@zupee.in") -> shiv.k@zupee.in | N82: =IFERROR(__xludf.DUMMYFUNCTION("""COMPUTED_VALUE"""),"PWLJ6J0F7C") -> PWLJ6J0F7C
A83: =IFERROR(__xludf.DUMMYFUNCTION("""COMPUTED_VALUE"""),45357.0) -> 45357 | B83: =IFERROR(__xludf.DUMMYFUNCTION("""COMPUTED_VALUE"""),"Vasudev Yadav") -> Vasudev Yadav | C83: =IFERROR(__xludf.DUMMYFUNCTION("""COMPUTED_VALUE"""),"Customer Experience") -> Customer Experience | D83: =IFERROR(__xludf.DUMMYFUNCTION("""COMPUTED_VALUE"""),8.882328557E9) -> 8882328557 | E83: =IFERROR(__xludf.DUMMYFUNCTION("""COMPUTED_VALUE"""),"Customer Support Executive") -> Customer Support Executive | F83: =IFERROR(__xludf.DUMMYFUNCTION("""COMPUTED_VALUE"""),"Customer Relation Management") -> Customer Relation Management | G83: =IFERROR(__xludf.DUMMYFUNCTION("""COMPUTED_VALUE""")," vasudevyadav304@gmail.com") -> vasudevyadav304@gmail.com | H83: =IFERROR(__xludf.DUMMYFUNCTION("""COMPUTED_VALUE"""),"Shivam Bali") -> Shivam Bali | I83: =IFERROR(__xludf.DUMMYFUNCTION("""COMPUTED_VALUE"""),45356.0) -> 45356 | J83: =IFERROR(__xludf.DUMMYFUNCTION("""COMPUTED_VALUE"""),"Nidhi Khedekar") -> Nidhi Khedekar | K83: =IFERROR(__xludf.DUMMYFUNCTION("""COMPUTED_VALUE"""),"Joined") -> Joined | L83: =IFERROR(__xludf.DUMMYFUNCTION("""COMPUTED_VALUE"""),"In Office") -> In Office | M83: =IFERROR(__xludf.DUMMYFUNCTION("""COMPUTED_VALUE"""),"vasudev.yadav@zupee.in") -> vasudev.yadav@zupee.in
A84: =IFERROR(__xludf.DUMMYFUNCTION("""COMPUTED_VALUE"""),45357.0) -> 45357 | B84: =IFERROR(__xludf.DUMMYFUNCTION("""COMPUTED_VALUE"""),"Aman") -> Aman | C84: =IFERROR(__xludf.DUMMYFUNCTION("""COMPUTED_VALUE"""),"Technology") -> Technology | D84: =IFERROR(__xludf.DUMMYFUNCTION("""COMPUTED_VALUE"""),7.988985535E9) -> 7988985535 | E84: =IFERROR(__xludf.DUMMYFUNCTION("""COMPUTED_VALUE"""),"Quality Assurance Engineer- 1 ") -> Quality Assurance Engineer- 1 | F84: =IFERROR(__xludf.DUMMYFUNCTION("""COMPUTED_VALUE"""),"Quality") -> Quality | G84: =IFERROR(__xludf.DUMMYFUNCTION("""COMPUTED_VALUE"""),"amanhans60@gmail.com") -> amanhans60@gmail.com | H84: =IFERROR(__xludf.DUMMYFUNCTION("""COMPUTED_VALUE"""),"Vishal Agarwal") -> Vishal Agarwal | I84: =IFERROR(__xludf.DUMMYFUNCTION("""COMPUTED_VALUE"""),45356.0) -> 45356 | J84: =IFERROR(__xludf.DUMMYFUNCTION("""COMPUTED_VALUE"""),"Mamta Pandey") -> Mamta Pandey | K84: =IFERROR(__xludf.DUMMYFUNCTION("""COMPUTED_VALUE"""),"Joined") -> Joined | L84: =IFERROR(__xludf.DUMMYFUNCTION("""COMPUTED_VALUE"""),"In Office") -> In Office
A85: =IFERROR(__xludf.DUMMYFUNCTION("""COMPUTED_VALUE"""),45362.0) -> 45362 | B85: =IFERROR(__xludf.DUMMYFUNCTION("""COMPUTED_VALUE"""),"Amit Mohanta") -> Amit Mohanta | C85: =IFERROR(__xludf.DUMMYFUNCTION("""COMPUTED_VALUE"""),"Product") -> Product | D85: =IFERROR(__xludf.DUMMYFUNCTION("""COMPUTED_VALUE"""),9.97155741E9) -> 9971557410 | E85: =IFERROR(__xludf.DUMMYFUNCTION("""COMPUTED_VALUE"""),"Senior 3D Animator") -> Senior 3D Animator | F85: =IFERROR(__xludf.DUMMYFUNCTION("""COMPUTED_VALUE"""),"Design") -> Design | G85: =IFERROR(__xludf.DUMMYFUNCTION("""COMPUTED_VALUE"""),"mohanta27@gmail.com") -> mohanta27@gmail.com | H85: =IFERROR(__xludf.DUMMYFUNCTION("""COMPUTED_VALUE"""),"Aarti Luthra") -> Aarti Luthra | I85: =IFERROR(__xludf.DUMMYFUNCTION("""COMPUTED_VALUE"""),45358.0) -> 45358 | J85: =IFERROR(__xludf.DUMMYFUNCTION("""COMPUTED_VALUE"""),"Naina") -> Naina | K85: =IFERROR(__xludf.DUMMYFUNCTION("""COMPUTED_VALUE"""),"Joined") -> Joined | L85: =IFERROR(__xludf.DUMMYFUNCTION("""COMPUTED_VALUE"""),"In Office") -> In Office | M85: =IFERROR(__xludf.DUMMYFUNCTION("""COMPUTED_VALUE"""),"amit.mohanta@zupee.in") -> amit.mohanta@zupee.in
A86: =IFERROR(__xludf.DUMMYFUNCTION("""COMPUTED_VALUE"""),45364.0) -> 45364 | B86: =IFERROR(__xludf.DUMMYFUNCTION("""COMPUTED_VALUE"""),"Suman Kumar") -> Suman Kumar | C86: =IFERROR(__xludf.DUMMYFUNCTION("""COMPUTED_VALUE"""),"Customer Experience") -> Customer Experience | D86: =IFERROR(__xludf.DUMMYFUNCTION("""COMPUTED_VALUE"""),9.015511336E9) -> 9015511336 | E86: =IFERROR(__xludf.DUMMYFUNCTION("""COMPUTED_VALUE"""),"Senior Executive- Customer Experience") -> Senior Executive- Customer Experience | F86: =IFERROR(__xludf.DUMMYFUNCTION("""COMPUTED_VALUE"""),"Customer Relation Management") -> Customer Relation Management | G86: =IFERROR(__xludf.DUMMYFUNCTION("""COMPUTED_VALUE"""),"sumankumar0112@gmail.com") -> sumankumar0112@gmail.com | H86: =IFERROR(__xludf.DUMMYFUNCTION("""COMPUTED_VALUE"""),"Shivam Bali") -> Shivam Bali | I86: =IFERROR(__xludf.DUMMYFUNCTION("""COMPUTED_VALUE"""),45363.0) -> 45363 | J86: =IFERROR(__xludf.DUMMYFUNCTION("""COMPUTED_VALUE"""),"Nidhi Khedekar") -> Nidhi Khedekar | K86: =IFERROR(__xludf.DUMMYFUNCTION("""COMPUTED_VALUE"""),"Joined") -> Joined | L86: =IFERROR(__xludf.DUMMYFUNCTION("""COMPUTED_VALUE"""),"In Office") -> In Office | M86: =IFERROR(__xludf.DUMMYFUNCTION("""COMPUTED_VALUE"""),"suman.kumar@zupee.in") -> suman.kumar@zupee.in
A87: =IFERROR(__xludf.DUMMYFUNCTION("""COMPUTED_VALUE"""),45385.0) -> 45385 | B87: =IFERROR(__xludf.DUMMYFUNCTION("""COMPUTED_VALUE"""),"Ankush Gupta") -> Ankush Gupta | C87: =IFERROR(__xludf.DUMMYFUNCTION("""COMPUTED_VALUE"""),"Analytics") -> Analytics | D87: =IFERROR(__xludf.DUMMYFUNCTION("""COMPUTED_VALUE"""),8.559983095E9) -> 8559983095 | E87: =IFERROR(__xludf.DUMMYFUNCTION("""COMPUTED_VALUE"""),"Senior Data Analyst") -> Senior Data Analyst | F87: =IFERROR(__xludf.DUMMYFUNCTION("""COMPUTED_VALUE"""),"Product Analytics") -> Product Analytics | G87: =IFERROR(__xludf.DUMMYFUNCTION("""COMPUTED_VALUE"""),"ankushguptash1997@gmail.com") -> ankushguptash1997@gmail.com | H87: =IFERROR(__xludf.DUMMYFUNCTION("""COMPUTED_VALUE"""),"Shwetank Anand") -> Shwetank Anand | I87: =IFERROR(__xludf.DUMMYFUNCTION("""COMPUTED_VALUE"""),45369.0) -> 45369 | J87: =IFERROR(__xludf.DUMMYFUNCTION("""COMPUTED_VALUE"""),"Nidhi Khedekar") -> Nidhi Khedekar | K87: =IFERROR(__xludf.DUMMYFUNCTION("""COMPUTED_VALUE"""),"Joined") -> Joined | L87: =IFERROR(__xludf.DUMMYFUNCTION("""COMPUTED_VALUE"""),"In Office") -> In Office | M87: =IFERROR(__xludf.DUMMYFUNCTION("""COMPUTED_VALUE"""),"ankush.gupta@zupee.in") -> ankush.gupta@zupee.in
A88: =IFERROR(__xludf.DUMMYFUNCTION("""COMPUTED_VALUE"""),45397.0) -> 45397 | B88: =IFERROR(__xludf.DUMMYFUNCTION("""COMPUTED_VALUE"""),"Pankaj Sharma") -> Pankaj Sharma | C88: =IFERROR(__xludf.DUMMYFUNCTION("""COMPUTED_VALUE"""),"Customer Experience") -> Customer Experience | D88: =IFERROR(__xludf.DUMMYFUNCTION("""COMPUTED_VALUE"""),7.007976868E9) -> 7007976868 | E88: =IFERROR(__xludf.DUMMYFUNCTION("""COMPUTED_VALUE"""),"Senior Fraud Analyst") -> Senior Fraud Analyst | F88: =IFERROR(__xludf.DUMMYFUNCTION("""COMPUTED_VALUE"""),"Fraud Risk Management ") -> Fraud Risk Management | G88: =IFERROR(__xludf.DUMMYFUNCTION("""COMPUTED_VALUE"""),"Pankajjshaarma@outlook.com") -> Pankajjshaarma@outlook.com | H88: =IFERROR(__xludf.DUMMYFUNCTION("""COMPUTED_VALUE"""),"Aman Khare") -> Aman Khare | I88: =IFERROR(__xludf.DUMMYFUNCTION("""COMPUTED_VALUE"""),45369.0) -> 45369 | J88: =IFERROR(__xludf.DUMMYFUNCTION("""COMPUTED_VALUE"""),"Nidhi Khedekar") -> Nidhi Khedekar | K88: =IFERROR(__xludf.DUMMYFUNCTION("""COMPUTED_VALUE"""),"Joined") -> Joined | L88: =IFERROR(__xludf.DUMMYFUNCTION("""COMPUTED_VALUE"""),"In Office") -> In Office | M88: =IFERROR(__xludf.DUMMYFUNCTION("""COMPUTED_VALUE"""),"pankaj.sharma@zupee.in") -> pankaj.sharma@zupee.in
A89: =IFERROR(__xludf.DUMMYFUNCTION("""COMPUTED_VALUE"""),45432.0) -> 45432 | B89: =IFERROR(__xludf.DUMMYFUNCTION("""COMPUTED_VALUE"""),"Shubham Gupta") -> Shubham Gupta | C89: =IFERROR(__xludf.DUMMYFUNCTION("""COMPUTED_VALUE"""),"Analytics") -> Analytics | D89: =IFERROR(__xludf.DUMMYFUNCTION("""COMPUTED_VALUE"""),8.005462446E9) -> 8005462446 | E89: =IFERROR(__xludf.DUMMYFUNCTION("""COMPUTED_VALUE"""),"Senior Data Analyst") -> Senior Data Analyst | F89: =IFERROR(__xludf.DUMMYFUNCTION("""COMPUTED_VALUE"""),"Product Analytics") -> Product Analytics | G89: =IFERROR(__xludf.DUMMYFUNCTION("""COMPUTED_VALUE"""),"reachshubham1997@gmail.com") -> reachshubham1997@gmail.com | H89: =IFERROR(__xludf.DUMMYFUNCTION("""COMPUTED_VALUE"""),"Raman Malik") -> Raman Malik | I89: =IFERROR(__xludf.DUMMYFUNCTION("""COMPUTED_VALUE"""),45370.0) -> 45370 | J89: =IFERROR(__xludf.DUMMYFUNCTION("""COMPUTED_VALUE"""),"Nidhi Khedekar") -> Nidhi Khedekar | K89: =IFERROR(__xludf.DUMMYFUNCTION("""COMPUTED_VALUE"""),"Joined") -> Joined | L89: =IFERROR(__xludf.DUMMYFUNCTION("""COMPUTED_VALUE"""),"In Office") -> In Office | M89: =IFERROR(__xludf.DUMMYFUNCTION("""COMPUTED_VALUE"""),"shubham.gupta@zupee.in") -> shubham.gupta@zupee.in
A90: =IFERROR(__xludf.DUMMYFUNCTION("""COMPUTED_VALUE"""),45433.0) -> 45433 | B90: =IFERROR(__xludf.DUMMYFUNCTION("""COMPUTED_VALUE"""),"Nikhil Jain") -> Nikhil Jain | C90: =IFERROR(__xludf.DUMMYFUNCTION("""COMPUTED_VALUE"""),"Analytics") -> Analytics | D90: =IFERROR(__xludf.DUMMYFUNCTION("""COMPUTED_VALUE"""),8.950085725E9) -> 8950085725 | E90: =IFERROR(__xludf.DUMMYFUNCTION("""COMPUTED_VALUE"""),"Senior Data Analyst") -> Senior Data Analyst | F90: =IFERROR(__xludf.DUMMYFUNCTION("""COMPUTED_VALUE"""),"Product Analytics") -> Product Analytics | G90: =IFERROR(__xludf.DUMMYFUNCTION("""COMPUTED_VALUE"""),"nikhil.jain1912@gmail.com") -> nikhil.jain1912@gmail.com | H90: =IFERROR(__xludf.DUMMYFUNCTION("""COMPUTED_VALUE"""),"Raman Malik") -> Raman Malik | I90: =IFERROR(__xludf.DUMMYFUNCTION("""COMPUTED_VALUE"""),45370.0) -> 45370 | J90: =IFERROR(__xludf.DUMMYFUNCTION("""COMPUTED_VALUE"""),"Mamta Pandey") -> Mamta Pandey | K90: =IFERROR(__xludf.DUMMYFUNCTION("""COMPUTED_VALUE"""),"Joined") -> Joined | L90: =IFERROR(__xludf.DUMMYFUNCTION("""COMPUTED_VALUE"""),"In Office") -> In Office | M90: =IFERROR(__xludf.DUMMYFUNCTION("""COMPUTED_VALUE"""),"nikhil.jain@zupee.in") -> nikhil.jain@zupee.in
A91: =IFERROR(__xludf.DUMMYFUNCTION("""COMPUTED_VALUE"""),45419.0) -> 45419 | B91: =IFERROR(__xludf.DUMMYFUNCTION("""COMPUTED_VALUE"""),"Chaitanya Kapoor") -> Chaitanya Kapoor | C91: =IFERROR(__xludf.DUMMYFUNCTION("""COMPUTED_VALUE"""),"Analytics") -> Analytics | D91: =IFERROR(__xludf.DUMMYFUNCTION("""COMPUTED_VALUE"""),9.811924922E9) -> 9811924922 | E91: =IFERROR(__xludf.DUMMYFUNCTION("""COMPUTED_VALUE"""),"Lead Data Analyst") -> Lead Data Analyst | F91: =IFERROR(__xludf.DUMMYFUNCTION("""COMPUTED_VALUE"""),"Product Analytics") -> Product Analytics | G91: =IFERROR(__xludf.DUMMYFUNCTION("""COMPUTED_VALUE"""),"chaitanya.kapoor@outlook.com") -> chaitanya.kapoor@outlook.com | H91: =IFERROR(__xludf.DUMMYFUNCTION("""COMPUTED_VALUE"""),"Shwetank Anand") -> Shwetank Anand | I91: =IFERROR(__xludf.DUMMYFUNCTION("""COMPUTED_VALUE"""),45371.0) -> 45371 | J91: =IFERROR(__xludf.DUMMYFUNCTION("""COMPUTED_VALUE"""),"Mamta Pandey") -> Mamta Pandey | K91: =IFERROR(__xludf.DUMMYFUNCTION("""COMPUTED_VALUE"""),"Joined") -> Joined | L91: =IFERROR(__xludf.DUMMYFUNCTION("""COMPUTED_VALUE"""),"In Office") -> In Office | M91: =IFERROR(__xludf.DUMMYFUNCTION("""COMPUTED_VALUE"""),"chaitanya.kapoor@zupee.in") -> chaitanya.kapoor@zupee.in
A92: =IFERROR(__xludf.DUMMYFUNCTION("""COMPUTED_VALUE"""),45397.0) -> 45397 | B92: =IFERROR(__xludf.DUMMYFUNCTION("""COMPUTED_VALUE"""),"Anurag Dwivedi") -> Anurag Dwivedi | C92: =IFERROR(__xludf.DUMMYFUNCTION("""COMPUTED_VALUE"""),"Customer Experience") -> Customer Experience | D92: =IFERROR(__xludf.DUMMYFUNCTION("""COMPUTED_VALUE"""),9.807225188E9) -> 9807225188 | E92: =IFERROR(__xludf.DUMMYFUNCTION("""COMPUTED_VALUE"""),"Senior Fraud Analyst") -> Senior Fraud Analyst | F92: =IFERROR(__xludf.DUMMYFUNCTION("""COMPUTED_VALUE"""),"Fraud Risk Management ") -> Fraud Risk Management | G92: =IFERROR(__xludf.DUMMYFUNCTION("""COMPUTED_VALUE"""),"anudwivedi31@gmail.com") -> anudwivedi31@gmail.com | H92: =IFERROR(__xludf.DUMMYFUNCTION("""COMPUTED_VALUE"""),"Aman Khare") -> Aman Khare | I92: =IFERROR(__xludf.DUMMYFUNCTION("""COMPUTED_VALUE"""),45377.0) -> 45377 | J92: =IFERROR(__xludf.DUMMYFUNCTION("""COMPUTED_VALUE"""),"Nidhi Khedekar") -> Nidhi Khedekar | K92: =IFERROR(__xludf.DUMMYFUNCTION("""COMPUTED_VALUE"""),"Joined") -> Joined | L92: =IFERROR(__xludf.DUMMYFUNCTION("""COMPUTED_VALUE"""),"In Office") -> In Office | M92: =IFERROR(__xludf.DUMMYFUNCTION("""COMPUTED_VALUE"""),"anurag.dwivedi@zupee.in") -> anurag.dwivedi@zupee.in
A93: =IFERROR(__xludf.DUMMYFUNCTION("""COMPUTED_VALUE"""),45385.0) -> 45385 | B93: =IFERROR(__xludf.DUMMYFUNCTION("""COMPUTED_VALUE"""),"Hemant Dandotiya") -> Hemant Dandotiya | C93: =IFERROR(__xludf.DUMMYFUNCTION("""COMPUTED_VALUE"""),"Product") -> Product | D93: =IFERROR(__xludf.DUMMYFUNCTION("""COMPUTED_VALUE"""),8.800327796E9) -> 8800327796 | E93: =IFERROR(__xludf.DUMMYFUNCTION("""COMPUTED_VALUE"""),"Senior 3D Game Artist") -> Senior 3D Game Artist | F93: =IFERROR(__xludf.DUMMYFUNCTION("""COMPUTED_VALUE"""),"Design") -> Design | G93: =IFERROR(__xludf.DUMMYFUNCTION("""COMPUTED_VALUE"""),"hemant.sharma010@gmail.com") -> hemant.sharma010@gmail.com | H93: =IFERROR(__xludf.DUMMYFUNCTION("""COMPUTED_VALUE"""),"Aarti Luthra") -> Aarti Luthra | I93: =IFERROR(__xludf.DUMMYFUNCTION("""COMPUTED_VALUE"""),45384.0) -> 45384 | J93: =IFERROR(__xludf.DUMMYFUNCTION("""COMPUTED_VALUE"""),"Naina") -> Naina | K93: =IFERROR(__xludf.DUMMYFUNCTION("""COMPUTED_VALUE"""),"Joined") -> Joined | L93: =IFERROR(__xludf.DUMMYFUNCTION("""COMPUTED_VALUE"""),"In Office") -> In Office | M93: =IFERROR(__xludf.DUMMYFUNCTION("""COMPUTED_VALUE"""),"hemant.dandotiya@zupee.in") -> hemant.dandotiya@zupee.in
A94: =IFERROR(__xludf.DUMMYFUNCTION("""COMPUTED_VALUE"""),45390.0) -> 45390 | B94: =IFERROR(__xludf.DUMMYFUNCTION("""COMPUTED_VALUE"""),"Divya") -> Divya | C94: =IFERROR(__xludf.DUMMYFUNCTION("""COMPUTED_VALUE"""),"Customer Experience") -> Customer Experience | D94: =IFERROR(__xludf.DUMMYFUNCTION("""COMPUTED_VALUE"""),7.88910877E9) -> 7889108770 | E94: =IFERROR(__xludf.DUMMYFUNCTION("""COMPUTED_VALUE"""),"Senior Executive – Customer Experience") -> Senior Executive – Customer Experience | F94: =IFERROR(__xludf.DUMMYFUNCTION("""COMPUTED_VALUE"""),"Customer Relation Management") -> Customer Relation Management | G94: =IFERROR(__xludf.DUMMYFUNCTION("""COMPUTED_VALUE"""),"dd8628083429@gmail.com") -> dd8628083429@gmail.com | H94: =IFERROR(__xludf.DUMMYFUNCTION("""COMPUTED_VALUE"""),"Shivam Bali") -> Shivam Bali | I94: =IFERROR(__xludf.DUMMYFUNCTION("""COMPUTED_VALUE"""),45386.0) -> 45386 | J94: =IFERROR(__xludf.DUMMYFUNCTION("""COMPUTED_VALUE"""),"Nidhi Khedekar") -> Nidhi Khedekar | K94: =IFERROR(__xludf.DUMMYFUNCTION("""COMPUTED_VALUE"""),"Joined") -> Joined | L94: =IFERROR(__xludf.DUMMYFUNCTION("""COMPUTED_VALUE"""),"Virtual") -> Virtual
A95: =IFERROR(__xludf.DUMMYFUNCTION("""COMPUTED_VALUE"""),45432.0) -> 45432 | B95: =IFERROR(__xludf.DUMMYFUNCTION("""COMPUTED_VALUE"""),"S Anand Babu") -> S Anand Babu | C95: =IFERROR(__xludf.DUMMYFUNCTION("""COMPUTED_VALUE"""),"HR") -> HR | D95: =IFERROR(__xludf.DUMMYFUNCTION("""COMPUTED_VALUE"""),7.09758945E9) -> 7097589450 | E95: =IFERROR(__xludf.DUMMYFUNCTION("""COMPUTED_VALUE"""),"Assistant Manager - Talent Acquisition") -> Assistant Manager - Talent Acquisition | F95: =IFERROR(__xludf.DUMMYFUNCTION("""COMPUTED_VALUE"""),"Human Resource") -> Human Resource | G95: =IFERROR(__xludf.DUMMYFUNCTION("""COMPUTED_VALUE"""),"john.sab72@gmail.com") -> john.sab72@gmail.com | H95: =IFERROR(__xludf.DUMMYFUNCTION("""COMPUTED_VALUE"""),"M Sangeetha") -> M Sangeetha | I95: =IFERROR(__xludf.DUMMYFUNCTION("""COMPUTED_VALUE"""),45386.0) -> 45386 | J95: =IFERROR(__xludf.DUMMYFUNCTION("""COMPUTED_VALUE"""),"Nidhi Khedekar") -> Nidhi Khedekar | K95: =IFERROR(__xludf.DUMMYFUNCTION("""COMPUTED_VALUE"""),"Offer Declined") -> Offer Declined | L95: =IFERROR(__xludf.DUMMYFUNCTION("""COMPUTED_VALUE"""),"In Office") -> In Office
A96: =IFERROR(__xludf.DUMMYFUNCTION("""COMPUTED_VALUE"""),45413.0) -> 45413 | B96: =IFERROR(__xludf.DUMMYFUNCTION("""COMPUTED_VALUE"""),"Satyam Singh") -> Satyam Singh | C96: =IFERROR(__xludf.DUMMYFUNCTION("""COMPUTED_VALUE"""),"Marketing") -> Marketing | D96: =IFERROR(__xludf.DUMMYFUNCTION("""COMPUTED_VALUE"""),9.528178911E9) -> 9528178911 | E96: =IFERROR(__xludf.DUMMYFUNCTION("""COMPUTED_VALUE"""),"SEO Executive") -> SEO Executive | F96: =IFERROR(__xludf.DUMMYFUNCTION("""COMPUTED_VALUE"""),"Digital Marketing") -> Digital Marketing | G96: =IFERROR(__xludf.DUMMYFUNCTION("""COMPUTED_VALUE"""),"career.satyamsingh@gmail.com") -> career.satyamsingh@gmail.com | H96: =IFERROR(__xludf.DUMMYFUNCTION("""COMPUTED_VALUE"""),"Lekhika Dhariyal ") -> Lekhika Dhariyal | I96: =IFERROR(__xludf.DUMMYFUNCTION("""COMPUTED_VALUE"""),45386.0) -> 45386 | J96: =IFERROR(__xludf.DUMMYFUNCTION("""COMPUTED_VALUE"""),"Naina") -> Naina | K96: =IFERROR(__xludf.DUMMYFUNCTION("""COMPUTED_VALUE"""),"Joined") -> Joined | L96: =IFERROR(__xludf.DUMMYFUNCTION("""COMPUTED_VALUE"""),"In Office") -> In Office | M96: =IFERROR(__xludf.DUMMYFUNCTION("""COMPUTED_VALUE"""),"satyam.singh@zupee.in") -> satyam.singh@zupee.in | N96: =IFERROR(__xludf.DUMMYFUNCTION("""COMPUTED_VALUE"""),"W56VYKG546") -> W56VYKG546
A97: =IFERROR(__xludf.DUMMYFUNCTION("""COMPUTED_VALUE"""),45397.0) -> 45397 | B97: =IFERROR(__xludf.DUMMYFUNCTION("""COMPUTED_VALUE"""),"Basilnath Samson Masabiel") -> Basilnath Samson Masabiel | C97: =IFERROR(__xludf.DUMMYFUNCTION("""COMPUTED_VALUE"""),"Customer Experience") -> Customer Experience | D97: =IFERROR(__xludf.DUMMYFUNCTION("""COMPUTED_VALUE"""),8.867140028E9) -> 8867140028 | E97: =IFERROR(__xludf.DUMMYFUNCTION("""COMPUTED_VALUE"""),"Senior Analyst – Process Excellence") -> Senior Analyst – Process Excellence | F97: =IFERROR(__xludf.DUMMYFUNCTION("""COMPUTED_VALUE"""),"Opex") -> Opex | G97: =IFERROR(__xludf.DUMMYFUNCTION("""COMPUTED_VALUE"""),"samsonbasilnath@gmail.com") -> samsonbasilnath@gmail.com | H97: =IFERROR(__xludf.DUMMYFUNCTION("""COMPUTED_VALUE"""),"Sumit Yadav") -> Sumit Yadav | I97: =IFERROR(__xludf.DUMMYFUNCTION("""COMPUTED_VALUE"""),45390.0) -> 45390 | J97: =IFERROR(__xludf.DUMMYFUNCTION("""COMPUTED_VALUE"""),"Nidhi Khedekar") -> Nidhi Khedekar | K97: =IFERROR(__xludf.DUMMYFUNCTION("""COMPUTED_VALUE"""),"Joined") -> Joined | L97: =IFERROR(__xludf.DUMMYFUNCTION("""COMPUTED_VALUE"""),"In Office") -> In Office | M97: =IFERROR(__xludf.DUMMYFUNCTION("""COMPUTED_VALUE"""),"basilnath.masabiel@zupee.in") -> basilnath.masabiel@zupee.in | N97: =IFERROR(__xludf.DUMMYFUNCTION("""COMPUTED_VALUE"""),"PW03VMJK") -> PW03VMJK
A98: =IFERROR(__xludf.DUMMYFUNCTION("""COMPUTED_VALUE"""),45446.0) -> 45446 | B98: =IFERROR(__xludf.DUMMYFUNCTION("""COMPUTED_VALUE"""),"Ankit Agarwal") -> Ankit Agarwal | C98: =IFERROR(__xludf.DUMMYFUNCTION("""COMPUTED_VALUE"""),"Technology") -> Technology | D98: =IFERROR(__xludf.DUMMYFUNCTION("""COMPUTED_VALUE"""),9.886146848E9) -> 9886146848 | E98: =IFERROR(__xludf.DUMMYFUNCTION("""COMPUTED_VALUE"""),"Staff Engineer") -> Staff Engineer | F98: =IFERROR(__xludf.DUMMYFUNCTION("""COMPUTED_VALUE"""),"Engineering") -> Engineering | G98: =IFERROR(__xludf.DUMMYFUNCTION("""COMPUTED_VALUE"""),"agrwl.ankit28@gmail.com") -> agrwl.ankit28@gmail.com | H98: =IFERROR(__xludf.DUMMYFUNCTION("""COMPUTED_VALUE"""),"Gaurav Sharma") -> Gaurav Sharma | I98: =IFERROR(__xludf.DUMMYFUNCTION("""COMPUTED_VALUE"""),45398.0) -> 45398 | J98: =IFERROR(__xludf.DUMMYFUNCTION("""COMPUTED_VALUE"""),"Rajneesh Yadav") -> Rajneesh Yadav | K98: =IFERROR(__xludf.DUMMYFUNCTION("""COMPUTED_VALUE"""),"Offer Declined") -> Offer Declined | L98: =IFERROR(__xludf.DUMMYFUNCTION("""COMPUTED_VALUE"""),"In Office") -> In Office
A99: =IFERROR(__xludf.DUMMYFUNCTION("""COMPUTED_VALUE"""),45427.0) -> 45427 | B99: =IFERROR(__xludf.DUMMYFUNCTION("""COMPUTED_VALUE"""),"Sanchi Gupta") -> Sanchi Gupta | C99: =IFERROR(__xludf.DUMMYFUNCTION("""COMPUTED_VALUE"""),"Marketing") -> Marketing | D99: =IFERROR(__xludf.DUMMYFUNCTION("""COMPUTED_VALUE"""),9.871183498E9) -> 9871183498 | E99: =IFERROR(__xludf.DUMMYFUNCTION("""COMPUTED_VALUE"""),"Senior SEO Content Writer") -> Senior SEO Content Writer | F99: =IFERROR(__xludf.DUMMYFUNCTION("""COMPUTED_VALUE"""),"Digital Marketing") -> Digital Marketing | G99: =IFERROR(__xludf.DUMMYFUNCTION("""COMPUTED_VALUE"""),"gupta.sanchi2050@gmail.com") -> gupta.sanchi2050@gmail.com | H99: =IFERROR(__xludf.DUMMYFUNCTION("""COMPUTED_VALUE"""),"Lekhika Dhariyal ") -> Lekhika Dhariyal | I99: =IFERROR(__xludf.DUMMYFUNCTION("""COMPUTED_VALUE"""),45398.0) -> 45398 | J99: =IFERROR(__xludf.DUMMYFUNCTION("""COMPUTED_VALUE"""),"Naina") -> Naina | K99: =IFERROR(__xludf.DUMMYFUNCTION("""COMPUTED_VALUE"""),"Joined") -> Joined | L99: =IFERROR(__xludf.DUMMYFUNCTION("""COMPUTED_VALUE"""),"In Office") -> In Office | M99: =IFERROR(__xludf.DUMMYFUNCTION("""COMPUTED_VALUE"""),"sanchi.gupta@zupee.in") -> sanchi.gupta@zupee.in | N99: =IFERROR(__xludf.DUMMYFUNCTION("""COMPUTED_VALUE"""),"559W234") -> 559W234
A100: =IFERROR(__xludf.DUMMYFUNCTION("""COMPUTED_VALUE"""),45432.0) -> 45432 | B100: =IFERROR(__xludf.DUMMYFUNCTION("""COMPUTED_VALUE"""),"Sneha Kumar") -> Sneha Kumar | C100: =IFERROR(__xludf.DUMMYFUNCTION("""COMPUTED_VALUE"""),"Marketing") -> Marketing | D100: =IFERROR(__xludf.DUMMYFUNCTION("""COMPUTED_VALUE"""),9.873180141E9) -> 9873180141 | E100: =IFERROR(__xludf.DUMMYFUNCTION("""COMPUTED_VALUE"""),"Senior Manager- Brand Marketing") -> Senior Manager- Brand Marketing | F100: =IFERROR(__xludf.DUMMYFUNCTION("""COMPUTED_VALUE"""),"Brand Marketing") -> Brand Marketing | G100: =IFERROR(__xludf.DUMMYFUNCTION("""COMPUTED_VALUE"""),"p17snehak@iima.ac.in") -> p17snehak@iima.ac.in | H100: =IFERROR(__xludf.DUMMYFUNCTION("""COMPUTED_VALUE"""),"Katha Pankaj Tara") -> Katha Pankaj Tara | I100: =IFERROR(__xludf.DUMMYFUNCTION("""COMPUTED_VALUE"""),45398.0) -> 45398 | J100: =IFERROR(__xludf.DUMMYFUNCTION("""COMPUTED_VALUE"""),"Rajneesh Yadav") -> Rajneesh Yadav | K100: =IFERROR(__xludf.DUMMYFUNCTION("""COMPUTED_VALUE"""),"Offer Declined") -> Offer Declined | L100: =IFERROR(__xludf.DUMMYFUNCTION("""COMPUTED_VALUE"""),"In Office") -> In Office
...

Sheet DMKT-Actv
A1: Full Name | B1: Email ID | C1: Designation | D1: Department | E1: Reporting Manager | F1: Status
A2: Babita Sharma | B2: babita.sharma@zupee.in | C2: Marketing Designer | D2: Brand Marketing | E2: aaditya.singh@zupee.in | F2: =VLOOKUP(B2,'Off-Boarding'!B:B,1,0) -> babita.sharma@zupee.in
A3: Arif Jamal | B3: arif.jamal@zupee.in | C3: Marketing Designer | D3: Brand Marketing | E3: aaditya.singh@zupee.in | F3: =VLOOKUP(B3,'Off-Boarding'!B:B,1,0) -> arif.jamal@zupee.in
A4: Aaditya | B4: aaditya.singh@zupee.in | C4: Lead Marketing Designer | D4: Brand Marketing | E4: harshil.dhawan@zupee.in | F4: =VLOOKUP(B4,'Off-Boarding'!B:B,1,0) -> aaditya.singh@zupee.in
A5: Ankita Jugran | B5: ankita.jugran@zupee.in | C5: Marketing Designer | D5: Brand Marketing | E5: aaditya.singh@zupee.in | F5: =VLOOKUP(B5,'Off-Boarding'!B:B,1,0) -> #N/A
A6: Katha Pankaj Tara | B6: katha.tara@zupee.in | C6: VP - Brand Marketing | D6: Brand Marketing | E6: akanksha.dhamija@zupee.in | F6: =VLOOKUP(B6,'Off-Boarding'!B:B,1,0) -> #N/A
A7: Harsha Ratnam | B7: harsha.ratnam@zupee.in | C7: Sr. Marketing Designer | D7: Brand Marketing | E7: harshil.dhawan@zupee.in | F7: =VLOOKUP(B7,'Off-Boarding'!B:B,1,0) -> harsha.ratnam@zupee.in
A8: Manoj Rane | B8: manoj.rane@zupee.in | C8: Assistant Manager - 2D Animator | D8: Brand Marketing | E8: rijul.sehgal@zupee.in | F8: =VLOOKUP(B8,'Off-Boarding'!B:B,1,0) -> manoj.rane@zupee.in
A9: Khushali Bagga | B9: khushali.bagga@zupee.in | C9: Senior Manager - Content & Social | D9: Brand Marketing | E9: katha.tara@zupee.in | F9: =VLOOKUP(B9,'Off-Boarding'!B:B,1,0) -> khushali.bagga@zupee.in
A10: Pratik Aswal | B10: pratik.aswal@zupee.in | C10: Assistant Manager - Content & Social | D10: Brand Marketing | E10: khushali.bagga@zupee.in | F10: =VLOOKUP(B10,'Off-Boarding'!B:B,1,0) -> #N/A
A11: Mukesh Kumar Maurya | B11: mukesh.maurya@zupee.in | C11: Senior Motion Graphic Designer | D11: Brand Marketing | E11: rijul.sehgal@zupee.in | F11: =VLOOKUP(B11,'Off-Boarding'!B:B,1,0) -> #N/A
A12: Himanshu Thakur | B12: himanshu.thakur@zupee.in | C12: Senior Motion Graphic Designer | D12: Brand Marketing | E12: rijul.sehgal@zupee.in | F12: =VLOOKUP(B12,'Off-Boarding'!B:B,1,0) -> #N/A
A13: Ankit Vikram | B13: ankit.vikram@zupee.in | C13: Content Writer | D13: Brand Marketing | E13: khushali.bagga@zupee.in | F13: =VLOOKUP(B13,'Off-Boarding'!B:B,1,0) -> #N/A
... A27: Rahul Emmanuel | B27: rahul.emmanuel@zupee.in | C27: Video Editor | D27: Brand Marketing | E27: katha.tara@zupee.in | F27: =VLOOKUP(B27,'Off-Boarding'!B:B,1,0) -> rahul.emmanuel@zupee.in

Sheet NJ_Laptop Data
A1: =IFERROR(__xludf.DUMMYFUNCTION("IMPORTRANGE(""1KkHmVdwdsro943TMhaCM6k6czUkQym_XXJCAzLQO7Po"",""Sheet1!A:N"")"),"") | B1: =IFERROR(__xludf.DUMMYFUNCTION("""COMPUTED_VALUE"""),"Name") -> Name | C1: =IFERROR(__xludf.DUMMYFUNCTION("""COMPUTED_VALUE"""),"Email-Id") -> Email-Id | D1: =IFERROR(__xludf.DUMMYFUNCTION("""COMPUTED_VALUE"""),"Phone Number") -> Phone Number | E1: =IFERROR(__xludf.DUMMYFUNCTION("""COMPUTED_VALUE"""),"DOJ") -> DOJ | F1: =IFERROR(__xludf.DUMMYFUNCTION("""COMPUTED_VALUE"""),"Business") -> Business | G1: =IFERROR(__xludf.DUMMYFUNCTION("""COMPUTED_VALUE"""),"Address") -> Address | H1: =IFERROR(__xludf.DUMMYFUNCTION("""COMPUTED_VALUE"""),"IT Assets") -> IT Assets | I1: =IFERROR(__xludf.DUMMYFUNCTION("""COMPUTED_VALUE"""),"Role") -> Role | J1: =IFERROR(__xludf.DUMMYFUNCTION("""COMPUTED_VALUE"""),"Department") -> Department | K1: =IFERROR(__xludf.DUMMYFUNCTION("""COMPUTED_VALUE"""),"Reporting Manager") -> Reporting Manager | L1: =IFERROR(__xludf.DUMMYFUNCTION("""COMPUTED_VALUE"""),"Laptop Dispatched") -> Laptop Dispatched | M1: =IFERROR(__xludf.DUMMYFUNCTION("""COMPUTED_VALUE"""),"Laptop Received") -> Laptop Received | N1: =IFERROR(__xludf.DUMMYFUNCTION("""COMPUTED_VALUE"""),"Consignment Number") -> Consignment Number
A2: =IFERROR(__xludf.DUMMYFUNCTION("""COMPUTED_VALUE"""),1.0) -> 1 | B2: =IFERROR(__xludf.DUMMYFUNCTION("""COMPUTED_VALUE"""),"Deepak Rawat") -> Deepak Rawat | C2: =IFERROR(__xludf.DUMMYFUNCTION("""COMPUTED_VALUE"""),"deepak.archana21@gmail.com") -> deepak.archana21@gmail.com | D2: =IFERROR(__xludf.DUMMYFUNCTION("""COMPUTED_VALUE"""),9.811007016E9) -> 9811007016 | E2: =IFERROR(__xludf.DUMMYFUNCTION("""COMPUTED_VALUE"""),"5th Jan'22") -> 5th Jan'22 | G2: =IFERROR(__xludf.DUMMYFUNCTION("""COMPUTED_VALUE"""),"Flat no 202, Krishna nagar, Bagu, Vijay nagar by pass, behind HP petrol pump, Ghaziabad. Pincode 201009.") -> Flat no 202, Krishna nagar, Bagu, Vijay nagar by pass, behind HP petrol pump, Ghaziabad. Pincode 201009. | H2: =IFERROR(__xludf.DUMMYFUNCTION("""COMPUTED_VALUE"""),"Windows Laptop") -> Windows Laptop | I2: =IFERROR(__xludf.DUMMYFUNCTION("""COMPUTED_VALUE"""),"Customer Care Executive") -> Customer Care Executive | L2: =IFERROR(__xludf.DUMMYFUNCTION("""COMPUTED_VALUE"""),"Delivered") -> Delivered | M2: =IFERROR(__xludf.DUMMYFUNCTION("""COMPUTED_VALUE"""),"Delivered") -> Delivered
A3: =IFERROR(__xludf.DUMMYFUNCTION("""COMPUTED_VALUE"""),2.0) -> 2 | B3: =IFERROR(__xludf.DUMMYFUNCTION("""COMPUTED_VALUE"""),"Umair Illiyas") -> Umair Illiyas | C3: =IFERROR(__xludf.DUMMYFUNCTION("""COMPUTED_VALUE"""),"umairiliyaskhan@gmail.com") -> umairiliyaskhan@gmail.com | D3: =IFERROR(__xludf.DUMMYFUNCTION("""COMPUTED_VALUE"""),7.417728435E9) -> 7417728435 | E3: =IFERROR(__xludf.DUMMYFUNCTION("""COMPUTED_VALUE"""),"5th Jan'22") -> 5th Jan'22 | G3: =IFERROR(__xludf.DUMMYFUNCTION("""COMPUTED_VALUE"""),"Mohalla Mohan, Nadrai Gate, Kasganj Pin code: 207123""") -> Mohalla Mohan, Nadrai Gate, Kasganj Pin code: 207123" | H3: =IFERROR(__xludf.DUMMYFUNCTION("""COMPUTED_VALUE"""),"Windows Laptop") -> Windows Laptop | I3: =IFERROR(__xludf.DUMMYFUNCTION("""COMPUTED_VALUE"""),"Customer Care Executive") -> Customer Care Executive | L3: =IFERROR(__xludf.DUMMYFUNCTION("""COMPUTED_VALUE"""),"Delivered") -> Delivered | M3: =IFERROR(__xludf.DUMMYFUNCTION("""COMPUTED_VALUE"""),"Delivered") -> Delivered
A4: =IFERROR(__xludf.DUMMYFUNCTION("""COMPUTED_VALUE"""),3.0) -> 3 | B4: =IFERROR(__xludf.DUMMYFUNCTION("""COMPUTED_VALUE"""),"Shankhaneel Saikia") -> Shankhaneel Saikia | C4: =IFERROR(__xludf.DUMMYFUNCTION("""COMPUTED_VALUE"""),"saikiashankhaneel@gmail.com ") -> saikiashankhaneel@gmail.com | D4: =IFERROR(__xludf.DUMMYFUNCTION("""COMPUTED_VALUE"""),8.447895709E9) -> 8447895709 | E4: =IFERROR(__xludf.DUMMYFUNCTION("""COMPUTED_VALUE"""),"5th Jan'22") -> 5th Jan'22 | G4: =IFERROR(__xludf.DUMMYFUNCTION("""COMPUTED_VALUE"""),"A-1/1,Hahnemann Enclave , Plot-40,Sector-6,Dwarka,New Delhi-110075") -> A-1/1,Hahnemann Enclave , Plot-40,Sector-6,Dwarka,New Delhi-110075 | H4: =IFERROR(__xludf.DUMMYFUNCTION("""COMPUTED_VALUE"""),"Windows Laptop") -> Windows Laptop | I4: =IFERROR(__xludf.DUMMYFUNCTION("""COMPUTED_VALUE"""),"Customer Care Executive") -> Customer Care Executive | L4: =IFERROR(__xludf.DUMMYFUNCTION("""COMPUTED_VALUE"""),"Delivered") -> Delivered | M4: =IFERROR(__xludf.DUMMYFUNCTION("""COMPUTED_VALUE"""),"Delivered") -> Delivered
A5: =IFERROR(__xludf.DUMMYFUNCTION("""COMPUTED_VALUE"""),4.0) -> 4 | B5: =IFERROR(__xludf.DUMMYFUNCTION("""COMPUTED_VALUE"""),"Sayantima Paul") -> Sayantima Paul | C5: =IFERROR(__xludf.DUMMYFUNCTION("""COMPUTED_VALUE"""),"shreyapaul1282@gmail.com") -> shreyapaul1282@gmail.com | D5: =IFERROR(__xludf.DUMMYFUNCTION("""COMPUTED_VALUE"""),9.354010122E9) -> 9354010122 | E5: =IFERROR(__xludf.DUMMYFUNCTION("""COMPUTED_VALUE"""),"5th Jan'22") -> 5th Jan'22 | G5: =IFERROR(__xludf.DUMMYFUNCTION("""COMPUTED_VALUE"""),"Flat no 201 plot no 100 3rd floor Tushar apartment 16 Raj bagh sahibabad ghaziabad") -> Flat no 201 plot no 100 3rd floor Tushar apartment 16 Raj bagh sahibabad ghaziabad | H5: =IFERROR(__xludf.DUMMYFUNCTION("""COMPUTED_VALUE"""),"Windows Laptop") -> Windows Laptop | I5: =IFERROR(__xludf.DUMMYFUNCTION("""COMPUTED_VALUE"""),"Customer Care Executive") -> Customer Care Executive | L5: =IFERROR(__xludf.DUMMYFUNCTION("""COMPUTED_VALUE"""),"Delivered") -> Delivered | M5: =IFERROR(__xludf.DUMMYFUNCTION("""COMPUTED_VALUE"""),"Delivered") -> Delivered
A6: =IFERROR(__xludf.DUMMYFUNCTION("""COMPUTED_VALUE"""),5.0) -> 5 | B6: =IFERROR(__xludf.DUMMYFUNCTION("""COMPUTED_VALUE"""),"Amit Kumar Shukla") -> Amit Kumar Shukla | C6: =IFERROR(__xludf.DUMMYFUNCTION("""COMPUTED_VALUE"""),"amit.shukla072000@gmail.com") -> amit.shukla072000@gmail.com | D6: =IFERROR(__xludf.DUMMYFUNCTION("""COMPUTED_VALUE"""),9.630868006E9) -> 9630868006 | E6: =IFERROR(__xludf.DUMMYFUNCTION("""COMPUTED_VALUE"""),"5th Jan'22") -> 5th Jan'22 | G6: =IFERROR(__xludf.DUMMYFUNCTION("""COMPUTED_VALUE"""),"50, Amaha Panditan, Ward no 2, Hanumana , District :- Rewa, Madhya Pradesh Pin code:- 486335") -> 50, Amaha Panditan, Ward no 2, Hanumana , District :- Rewa, Madhya Pradesh Pin code:- 486335 | H6: =IFERROR(__xludf.DUMMYFUNCTION("""COMPUTED_VALUE"""),"Windows Laptop") -> Windows Laptop | I6: =IFERROR(__xludf.DUMMYFUNCTION("""COMPUTED_VALUE"""),"Devops Intern") -> Devops Intern | L6: =IFERROR(__xludf.DUMMYFUNCTION("""COMPUTED_VALUE"""),"Delivered") -> Delivered | M6: =IFERROR(__xludf.DUMMYFUNCTION("""COMPUTED_VALUE"""),"Delivered") -> Delivered
A7: =IFERROR(__xludf.DUMMYFUNCTION("""COMPUTED_VALUE"""),6.0) -> 6 | B7: =IFERROR(__xludf.DUMMYFUNCTION("""COMPUTED_VALUE"""),"Rahul Kashyap ") -> Rahul Kashyap | C7: =IFERROR(__xludf.DUMMYFUNCTION("""COMPUTED_VALUE"""),"rahul181020@gmail.com") -> rahul181020@gmail.com | D7: =IFERROR(__xludf.DUMMYFUNCTION("""COMPUTED_VALUE"""),6.353884503E9) -> 6353884503 | E7: =IFERROR(__xludf.DUMMYFUNCTION("""COMPUTED_VALUE"""),"5th Jan'22") -> 5th Jan'22 | G7: =IFERROR(__xludf.DUMMYFUNCTION("""COMPUTED_VALUE"""),"Block No: 149/1773 Dhiraj Housing, Haripura, Near Seventh-Day School, Maninagar(East), Ahmedabad-380008") -> Block No: 149/1773 Dhiraj Housing, Haripura, Near Seventh-Day School, Maninagar(East), Ahmedabad-380008 | H7: =IFERROR(__xludf.DUMMYFUNCTION("""COMPUTED_VALUE"""),"Windows Laptop") -> Windows Laptop | I7: =IFERROR(__xludf.DUMMYFUNCTION("""COMPUTED_VALUE"""),"Devops Intern") -> Devops Intern | L7: =IFERROR(__xludf.DUMMYFUNCTION("""COMPUTED_VALUE"""),"Delivered") -> Delivered | M7: =IFERROR(__xludf.DUMMYFUNCTION("""COMPUTED_VALUE"""),"Delivered") -> Delivered
A8: =IFERROR(__xludf.DUMMYFUNCTION("""COMPUTED_VALUE"""),7.0) -> 7 | B8: =IFERROR(__xludf.DUMMYFUNCTION("""COMPUTED_VALUE"""),"Ramkunwar Megwal ") -> Ramkunwar Megwal | C8: =IFERROR(__xludf.DUMMYFUNCTION("""COMPUTED_VALUE"""),"ramkunwarboo@gmail.com") -> ramkunwarboo@gmail.com | D8: =IFERROR(__xludf.DUMMYFUNCTION("""COMPUTED_VALUE"""),7.357697983E9) -> 7357697983 | E8: =IFERROR(__xludf.DUMMYFUNCTION("""COMPUTED_VALUE"""),"5th Jan'22") -> 5th Jan'22 | G8: =IFERROR(__xludf.DUMMYFUNCTION("""COMPUTED_VALUE"""),"Boonarvatan Nagaur Rajasthan Pincode 341028") -> Boonarvatan Nagaur Rajasthan Pincode 341028 | H8: =IFERROR(__xludf.DUMMYFUNCTION("""COMPUTED_VALUE"""),"Windows Laptop") -> Windows Laptop | I8: =IFERROR(__xludf.DUMMYFUNCTION("""COMPUTED_VALUE"""),"Devops Intern") -> Devops Intern | L8: =IFERROR(__xludf.DUMMYFUNCTION("""COMPUTED_VALUE"""),"delivered") -> delivered | M8: =IFERROR(__xludf.DUMMYFUNCTION("""COMPUTED_VALUE"""),"Delivered") -> Delivered
A9: =IFERROR(__xludf.DUMMYFUNCTION("""COMPUTED_VALUE"""),8.0) -> 8 | B9: =IFERROR(__xludf.DUMMYFUNCTION("""COMPUTED_VALUE"""),"Karan Bhyana") -> Karan Bhyana | C9: =IFERROR(__xludf.DUMMYFUNCTION("""COMPUTED_VALUE"""),"kbhyana@gmail.com") -> kbhyana@gmail.com | D9: =IFERROR(__xludf.DUMMYFUNCTION("""COMPUTED_VALUE"""),9.560755018E9) -> 9560755018 | E9: =IFERROR(__xludf.DUMMYFUNCTION("""COMPUTED_VALUE"""),"5th Jan'22") -> 5th Jan'22 | G9: =IFERROR(__xludf.DUMMYFUNCTION("""COMPUTED_VALUE"""),"B-205 Ground Floor Yojna Vihar Delhi-110092 Near Yamuna Sports complex Gate number 3") -> B-205 Ground Floor Yojna Vihar Delhi-110092 Near Yamuna Sports complex Gate number 3 | H9: =IFERROR(__xludf.DUMMYFUNCTION("""COMPUTED_VALUE"""),"MacBook ") -> MacBook | I9: =IFERROR(__xludf.DUMMYFUNCTION("""COMPUTED_VALUE"""),"Data Analyst") -> Data Analyst | L9: =IFERROR(__xludf.DUMMYFUNCTION("""COMPUTED_VALUE"""),"Delivered") -> Delivered | M9: =IFERROR(__xludf.DUMMYFUNCTION("""COMPUTED_VALUE"""),"Delivered") -> Delivered
A10: =IFERROR(__xludf.DUMMYFUNCTION("""COMPUTED_VALUE"""),9.0) -> 9 | B10: =IFERROR(__xludf.DUMMYFUNCTION("""COMPUTED_VALUE"""),"Siddharth Jain") -> Siddharth Jain | C10: =IFERROR(__xludf.DUMMYFUNCTION("""COMPUTED_VALUE"""),"jainsiddharth9396@gmail.com") -> jainsiddharth9396@gmail.com | D10: =IFERROR(__xludf.DUMMYFUNCTION("""COMPUTED_VALUE"""),8.766210814E9) -> 8766210814 | E10: =IFERROR(__xludf.DUMMYFUNCTION("""COMPUTED_VALUE"""),"6th Jan'22") -> 6th Jan'22 | G10: =IFERROR(__xludf.DUMMYFUNCTION("""COMPUTED_VALUE"""),"Address : Flat No. 34, Supreme Enclave Appartments, Mayur Vihar Phase 1, New Delhi 110091") -> Address : Flat No. 34, Supreme Enclave Appartments, Mayur Vihar Phase 1, New Delhi 110091 | H10: =IFERROR(__xludf.DUMMYFUNCTION("""COMPUTED_VALUE"""),"Windows Laptop") -> Windows Laptop | I10: =IFERROR(__xludf.DUMMYFUNCTION("""COMPUTED_VALUE"""),"Customer Care Executive") -> Customer Care Executive | L10: =IFERROR(__xludf.DUMMYFUNCTION("""COMPUTED_VALUE"""),"Delivered") -> Delivered | M10: =IFERROR(__xludf.DUMMYFUNCTION("""COMPUTED_VALUE"""),"Delivered") -> Delivered
A11: =IFERROR(__xludf.DUMMYFUNCTION("""COMPUTED_VALUE"""),10.0) -> 10 | B11: =IFERROR(__xludf.DUMMYFUNCTION("""COMPUTED_VALUE"""),"Ayushi Sharma") -> Ayushi Sharma | C11: =IFERROR(__xludf.DUMMYFUNCTION("""COMPUTED_VALUE"""),"ayuships33@gmail.com") -> ayuships33@gmail.com | D11: =IFERROR(__xludf.DUMMYFUNCTION("""COMPUTED_VALUE"""),7.348803275E9) -> 7348803275 | E11: =IFERROR(__xludf.DUMMYFUNCTION("""COMPUTED_VALUE"""),"6th Jan'22") -> 6th Jan'22 | G11: =IFERROR(__xludf.DUMMYFUNCTION("""COMPUTED_VALUE"""),"802, Block 2, Suncity Apartment, Near Sarjapura signal, Ibblur village, Bangalore, Karnataka 560103") -> 802, Block 2, Suncity Apartment, Near Sarjapura signal, Ibblur village, Bangalore, Karnataka 560103 | H11: =IFERROR(__xludf.DUMMYFUNCTION("""COMPUTED_VALUE"""),"Mac Book ") -> Mac Book | I11: =IFERROR(__xludf.DUMMYFUNCTION("""COMPUTED_VALUE"""),"SDE 1 (Backend)") -> SDE 1 (Backend) | L11: =IFERROR(__xludf.DUMMYFUNCTION("""COMPUTED_VALUE"""),"Delivered") -> Delivered | M11: =IFERROR(__xludf.DUMMYFUNCTION("""COMPUTED_VALUE"""),"Delivered") -> Delivered
A12: =IFERROR(__xludf.DUMMYFUNCTION("""COMPUTED_VALUE"""),11.0) -> 11 | B12: =IFERROR(__xludf.DUMMYFUNCTION("""COMPUTED_VALUE"""),"Ankita Pradhan") -> Ankita Pradhan | C12: =IFERROR(__xludf.DUMMYFUNCTION("""COMPUTED_VALUE"""),"ankitapradhan77@gmail.com") -> ankitapradhan77@gmail.com | D12: =IFERROR(__xludf.DUMMYFUNCTION("""COMPUTED_VALUE"""),9.981952881E9) -> 9981952881 | E12: =IFERROR(__xludf.DUMMYFUNCTION("""COMPUTED_VALUE"""),"15th Jan'22") -> 15th Jan'22 | G12: =IFERROR(__xludf.DUMMYFUNCTION("""COMPUTED_VALUE"""),"B119, 3rd floor, south city 1. Near signature tower, Gurgaon 122001") -> B119, 3rd floor, south city 1. Near signature tower, Gurgaon 122001 | H12: =IFERROR(__xludf.DUMMYFUNCTION("""COMPUTED_VALUE"""),"Windows Laptop") -> Windows Laptop | I12: =IFERROR(__xludf.DUMMYFUNCTION("""COMPUTED_VALUE"""),"Customer Care Executive") -> Customer Care Executive | L12: =IFERROR(__xludf.DUMMYFUNCTION("""COMPUTED_VALUE"""),"Delivered") -> Delivered | M12: =IFERROR(__xludf.DUMMYFUNCTION("""COMPUTED_VALUE"""),"Delivered") -> Delivered
A13: =IFERROR(__xludf.DUMMYFUNCTION("""COMPUTED_VALUE"""),12.0) -> 12 | B13: =IFERROR(__xludf.DUMMYFUNCTION("""COMPUTED_VALUE"""),"Priya Vadan") -> Priya Vadan | C13: =IFERROR(__xludf.DUMMYFUNCTION("""COMPUTED_VALUE"""),"prvadan@gmail.com") -> prvadan@gmail.com | D13: =IFERROR(__xludf.DUMMYFUNCTION("""COMPUTED_VALUE"""),9.873418906E9) -> 9873418906 | E13: =IFERROR(__xludf.DUMMYFUNCTION("""COMPUTED_VALUE"""),"15th Jan'22") -> 15th Jan'22 | G13: =IFERROR(__xludf.DUMMYFUNCTION("""COMPUTED_VALUE"""),"House no 41 Panchsheel park, near sahibabad fire station Sahibabad Ghaziabad 201005") -> House no 41 Panchsheel park, near sahibabad fire station Sahibabad Ghaziabad 201005 | H13: =IFERROR(__xludf.DUMMYFUNCTION("""COMPUTED_VALUE"""),"Windows Laptop") -> Windows Laptop | I13: =IFERROR(__xludf.DUMMYFUNCTION("""COMPUTED_VALUE"""),"Customer Care Executive") -> Customer Care Executive | L13: =IFERROR(__xludf.DUMMYFUNCTION("""COMPUTED_VALUE"""),"delivered") -> delivered | M13: =IFERROR(__xludf.DUMMYFUNCTION("""COMPUTED_VALUE"""),"delivered") -> delivered
A14: =IFERROR(__xludf.DUMMYFUNCTION("""COMPUTED_VALUE"""),13.0) -> 13 | B14: =IFERROR(__xludf.DUMMYFUNCTION("""COMPUTED_VALUE"""),"Pankhuri Mittal") -> Pankhuri Mittal | C14: =IFERROR(__xludf.DUMMYFUNCTION("""COMPUTED_VALUE"""),"Pankhu.mittal@gmail.com ") -> Pankhu.mittal@gmail.com | D14: =IFERROR(__xludf.DUMMYFUNCTION("""COMPUTED_VALUE"""),8.979164889E9) -> 8979164889 | E14: =IFERROR(__xludf.DUMMYFUNCTION("""COMPUTED_VALUE"""),"15th Jan'22") -> 15th Jan'22 | G14: =IFERROR(__xludf.DUMMYFUNCTION("""COMPUTED_VALUE"""),"Ground Floor, D6/408, Chutrakoot scheme, Jaipur, 302021") -> Ground Floor, D6/408, Chutrakoot scheme, Jaipur, 302021 | H14: =IFERROR(__xludf.DUMMYFUNCTION("""COMPUTED_VALUE"""),"Windows Laptop") -> Windows Laptop | I14: =IFERROR(__xludf.DUMMYFUNCTION("""COMPUTED_VALUE"""),"Customer Care Executive") -> Customer Care Executive | L14: =IFERROR(__xludf.DUMMYFUNCTION("""COMPUTED_VALUE"""),"Delivered") -> Delivered | M14: =IFERROR(__xludf.DUMMYFUNCTION("""COMPUTED_VALUE"""),"Delivered") -> Delivered
A15: =IFERROR(__xludf.DUMMYFUNCTION("""COMPUTED_VALUE"""),14.0) -> 14 | B15: =IFERROR(__xludf.DUMMYFUNCTION("""COMPUTED_VALUE"""),"Mohit Kaushik") -> Mohit Kaushik | C15: =IFERROR(__xludf.DUMMYFUNCTION("""COMPUTED_VALUE""")," mohitkaushikj133@gmail.com") -> mohitkaushikj133@gmail.com | D15: =IFERROR(__xludf.DUMMYFUNCTION("""COMPUTED_VALUE"""),9.068240907E9) -> 9068240907 | E15: =IFERROR(__xludf.DUMMYFUNCTION("""COMPUTED_VALUE"""),"10th Jan'22") -> 10th Jan'22 | G15: =IFERROR(__xludf.DUMMYFUNCTION("""COMPUTED_VALUE"""),"78, kherli hafizpur, Gautam Buddha Nagar, Uttar Pradesh -203202 ") -> 78, kherli hafizpur, Gautam Buddha Nagar, Uttar Pradesh -203202 | H15: =IFERROR(__xludf.DUMMYFUNCTION("""COMPUTED_VALUE"""),"Macbook + Mobile Phone") -> Macbook + Mobile Phone | I15: =IFERROR(__xludf.DUMMYFUNCTION("""COMPUTED_VALUE"""),"SDE 1 (Backend)") -> SDE 1 (Backend) | L15: =IFERROR(__xludf.DUMMYFUNCTION("""COMPUTED_VALUE"""),"Delivered") -> Delivered | M15: =IFERROR(__xludf.DUMMYFUNCTION("""COMPUTED_VALUE"""),"Delivered") -> Delivered
A16: =IFERROR(__xludf.DUMMYFUNCTION("""COMPUTED_VALUE"""),15.0) -> 15 | B16: =IFERROR(__xludf.DUMMYFUNCTION("""COMPUTED_VALUE"""),"Priyanka") -> Priyanka | C16: =IFERROR(__xludf.DUMMYFUNCTION("""COMPUTED_VALUE"""),"priyankagangwani97@gmail.com") -> priyankagangwani97@gmail.com | D16: =IFERROR(__xludf.DUMMYFUNCTION("""COMPUTED_VALUE"""),8.604721007E9) -> 8604721007 | E16: =IFERROR(__xludf.DUMMYFUNCTION("""COMPUTED_VALUE"""),"17th Jan'22") -> 17th Jan'22 | G16: =IFERROR(__xludf.DUMMYFUNCTION("""COMPUTED_VALUE"""),"126/94-A H block Govind Nagar, kanpur,UP") -> 126/94-A H block Govind Nagar, kanpur,UP | H16: =IFERROR(__xludf.DUMMYFUNCTION("""COMPUTED_VALUE"""),"Windows Laptop") -> Windows Laptop | I16: =IFERROR(__xludf.DUMMYFUNCTION("""COMPUTED_VALUE"""),"Customer Care Executive") -> Customer Care Executive | L16: =IFERROR(__xludf.DUMMYFUNCTION("""COMPUTED_VALUE"""),"delivered") -> delivered | M16: =IFERROR(__xludf.DUMMYFUNCTION("""COMPUTED_VALUE"""),"delivered") -> delivered
A17: =IFERROR(__xludf.DUMMYFUNCTION("""COMPUTED_VALUE"""),16.0) -> 16 | B17: =IFERROR(__xludf.DUMMYFUNCTION("""COMPUTED_VALUE"""),"Simran Verma") -> Simran Verma | C17: =IFERROR(__xludf.DUMMYFUNCTION("""COMPUTED_VALUE"""),"vermasimran2014@gmail.com") -> vermasimran2014@gmail.com | D17: =IFERROR(__xludf.DUMMYFUNCTION("""COMPUTED_VALUE"""),9.589522192E9) -> 9589522192 | E17: =IFERROR(__xludf.DUMMYFUNCTION("""COMPUTED_VALUE"""),"17th Jan'22") -> 17th Jan'22 | G17: =IFERROR(__xludf.DUMMYFUNCTION("""COMPUTED_VALUE"""),"H. No. 18, National Colony, Rampur, Jabalpur M.P - 482008") -> H. No. 18, National Colony, Rampur, Jabalpur M.P - 482008 | H17: =IFERROR(__xludf.DUMMYFUNCTION("""COMPUTED_VALUE"""),"Windows Laptop") -> Windows Laptop | I17: =IFERROR(__xludf.DUMMYFUNCTION("""COMPUTED_VALUE"""),"Customer Care Executive") -> Customer Care Executive | L17: =IFERROR(__xludf.DUMMYFUNCTION("""COMPUTED_VALUE"""),"delivered") -> delivered | M17: =IFERROR(__xludf.DUMMYFUNCTION("""COMPUTED_VALUE"""),"delivered") -> delivered
A20: =IFERROR(__xludf.DUMMYFUNCTION("""COMPUTED_VALUE"""),17.0) -> 17 | B20: =IFERROR(__xludf.DUMMYFUNCTION("""COMPUTED_VALUE"""),"AAYUSHI SIDDHI BHATTA") -> AAYUSHI SIDDHI BHATTA | C20: =IFERROR(__xludf.DUMMYFUNCTION("""COMPUTED_VALUE"""),"aayushi.work08@gmail.com") -> aayushi.work08@gmail.com | D20: =IFERROR(__xludf.DUMMYFUNCTION("""COMPUTED_VALUE"""),8.696645915E9) -> 8696645915 | E20: =IFERROR(__xludf.DUMMYFUNCTION("""COMPUTED_VALUE"""),"17th Jan'22") -> 17th Jan'22 | G20: =IFERROR(__xludf.DUMMYFUNCTION("""COMPUTED_VALUE"""),"4th floor,plot no. 188, Mahadev apartments, pocket -1 ,Dwarka Sector 23") -> 4th floor,plot no. 188, Mahadev apartments, pocket -1 ,Dwarka Sector 23 | H20: =IFERROR(__xludf.DUMMYFUNCTION("""COMPUTED_VALUE"""),"Windows Laptop") -> Windows Laptop | I20: =IFERROR(__xludf.DUMMYFUNCTION("""COMPUTED_VALUE"""),"Customer Care Executive") -> Customer Care Executive | L20: =IFERROR(__xludf.DUMMYFUNCTION("""COMPUTED_VALUE"""),"Dispatched") -> Dispatched | M20: =IFERROR(__xludf.DUMMYFUNCTION("""COMPUTED_VALUE"""),"Delivered") -> Delivered
A21: =IFERROR(__xludf.DUMMYFUNCTION("""COMPUTED_VALUE"""),18.0) -> 18 | B21: =IFERROR(__xludf.DUMMYFUNCTION("""COMPUTED_VALUE"""),"Kalpriksh Bist") -> Kalpriksh Bist | C21: =IFERROR(__xludf.DUMMYFUNCTION("""COMPUTED_VALUE"""),"kalprikshbist@gmail.com") -> kalprikshbist@gmail.com | D21: =IFERROR(__xludf.DUMMYFUNCTION("""COMPUTED_VALUE"""),8.448121484E9) -> 8448121484 | E21: =IFERROR(__xludf.DUMMYFUNCTION("""COMPUTED_VALUE"""),"12th Jan'22") -> 12th Jan'22 | G21: =IFERROR(__xludf.DUMMYFUNCTION("""COMPUTED_VALUE"""),"J302, Amrapali Sapphire, Sec 45 Noida") -> J302, Amrapali Sapphire, Sec 45 Noida | H21: =IFERROR(__xludf.DUMMYFUNCTION("""COMPUTED_VALUE"""),"Monitor + Mac Laptop") -> Monitor + Mac Laptop | I21: =IFERROR(__xludf.DUMMYFUNCTION("""COMPUTED_VALUE"""),"Data Analyst") -> Data Analyst | L21: =IFERROR(__xludf.DUMMYFUNCTION("""COMPUTED_VALUE"""),"Delivered") -> Delivered | M21: =IFERROR(__xludf.DUMMYFUNCTION("""COMPUTED_VALUE"""),"Delivered") -> Delivered
A22: =IFERROR(__xludf.DUMMYFUNCTION("""COMPUTED_VALUE"""),20.0) -> 20 | B22: =IFERROR(__xludf.DUMMYFUNCTION("""COMPUTED_VALUE"""),"Prarabdh sharma") -> Prarabdh sharma | C22: =IFERROR(__xludf.DUMMYFUNCTION("""COMPUTED_VALUE"""),"Prarabdhsr4@gmail.com") -> Prarabdhsr4@gmail.com | D22: =IFERROR(__xludf.DUMMYFUNCTION("""COMPUTED_VALUE"""),8.572873505E9) -> 8572873505 | E22: =IFERROR(__xludf.DUMMYFUNCTION("""COMPUTED_VALUE"""),44578.0) -> 44578 | G22: =IFERROR(__xludf.DUMMYFUNCTION("""COMPUTED_VALUE"""),"473-A, phase-1, jaggi garden, ambala city haryana, 134007") -> 473-A, phase-1, jaggi garden, ambala city haryana, 134007 | H22: =IFERROR(__xludf.DUMMYFUNCTION("""COMPUTED_VALUE"""),"Windows Laptop") -> Windows Laptop | I22: =IFERROR(__xludf.DUMMYFUNCTION("""COMPUTED_VALUE"""),"Customer Care Executive") -> Customer Care Executive | L22: =IFERROR(__xludf.DUMMYFUNCTION("""COMPUTED_VALUE"""),"Dispatched") -> Dispatched | M22: =IFERROR(__xludf.DUMMYFUNCTION("""COMPUTED_VALUE"""),"Delivered") -> Delivered
A23: =IFERROR(__xludf.DUMMYFUNCTION("""COMPUTED_VALUE"""),21.0) -> 21 | B23: =IFERROR(__xludf.DUMMYFUNCTION("""COMPUTED_VALUE"""),"DIVYA KHARE") -> DIVYA KHARE | C23: =IFERROR(__xludf.DUMMYFUNCTION("""COMPUTED_VALUE"""),"divyakhare85@gmail.com") -> divyakhare85@gmail.com | D23: =IFERROR(__xludf.DUMMYFUNCTION("""COMPUTED_VALUE"""),8.054867578E9) -> 8054867578 | E23: =IFERROR(__xludf.DUMMYFUNCTION("""COMPUTED_VALUE"""),44578.0) -> 44578 | G23: =IFERROR(__xludf.DUMMYFUNCTION("""COMPUTED_VALUE"""),"128/222, K-BLOCK, KIDWAI NAGAR,KANPUR, UTTAR PRADESH, PIN CODE- 208011") -> 128/222, K-BLOCK, KIDWAI NAGAR,KANPUR, UTTAR PRADESH, PIN CODE- 208011 | H23: =IFERROR(__xludf.DUMMYFUNCTION("""COMPUTED_VALUE"""),"Windows Laptop") -> Windows Laptop | I23: =IFERROR(__xludf.DUMMYFUNCTION("""COMPUTED_VALUE"""),"Customer Care Executive") -> Customer Care Executive | L23: =IFERROR(__xludf.DUMMYFUNCTION("""COMPUTED_VALUE"""),"Dispatched") -> Dispatched | M23: =IFERROR(__xludf.DUMMYFUNCTION("""COMPUTED_VALUE"""),"Delivered") -> Delivered
A24: =IFERROR(__xludf.DUMMYFUNCTION("""COMPUTED_VALUE"""),22.0) -> 22 | B24: =IFERROR(__xludf.DUMMYFUNCTION("""COMPUTED_VALUE"""),"Annu Nirmal") -> Annu Nirmal | C24: =IFERROR(__xludf.DUMMYFUNCTION("""COMPUTED_VALUE"""),"nirmalannu@gmail.com") -> nirmalannu@gmail.com | D24: =IFERROR(__xludf.DUMMYFUNCTION("""COMPUTED_VALUE"""),"96545 82774") -> 96545 82774 | E24: =IFERROR(__xludf.DUMMYFUNCTION("""COMPUTED_VALUE"""),44585.0) -> 44585 | G24: =IFERROR(__xludf.DUMMYFUNCTION("""COMPUTED_VALUE"""),"H. No. 1159, GF, Orchid Island, Sector - 51, Gurugram 122001") -> H. No. 1159, GF, Orchid Island, Sector - 51, Gurugram 122001 | H24: =IFERROR(__xludf.DUMMYFUNCTION("""COMPUTED_VALUE"""),"Macbook + Mobile Phone") -> Macbook + Mobile Phone | I24: =IFERROR(__xludf.DUMMYFUNCTION("""COMPUTED_VALUE"""),"Senior Software Engineer") -> Senior Software Engineer | L24: =IFERROR(__xludf.DUMMYFUNCTION("""COMPUTED_VALUE"""),"Dispatched") -> Dispatched | M24: =IFERROR(__xludf.DUMMYFUNCTION("""COMPUTED_VALUE"""),"Delivered") -> Delivered
A25: =IFERROR(__xludf.DUMMYFUNCTION("""COMPUTED_VALUE"""),23.0) -> 23 | B25: =IFERROR(__xludf.DUMMYFUNCTION("""COMPUTED_VALUE"""),"Abhishek Garg") -> Abhishek Garg | C25: =IFERROR(__xludf.DUMMYFUNCTION("""COMPUTED_VALUE"""),"gargiiabhishek823@gmail.com") -> gargiiabhishek823@gmail.com | D25: =IFERROR(__xludf.DUMMYFUNCTION("""COMPUTED_VALUE"""),9.711603839E9) -> 9711603839 | E25: =IFERROR(__xludf.DUMMYFUNCTION("""COMPUTED_VALUE"""),44585.0) -> 44585 | G25: =IFERROR(__xludf.DUMMYFUNCTION("""COMPUTED_VALUE"""),"C4H/ 165C, Janakpuri, New Delhi") -> C4H/ 165C, Janakpuri, New Delhi | H25: =IFERROR(__xludf.DUMMYFUNCTION("""COMPUTED_VALUE"""),"Macbook + Mobile Phone") -> Macbook + Mobile Phone | I25: =IFERROR(__xludf.DUMMYFUNCTION("""COMPUTED_VALUE"""),"SDET") -> SDET
A26: =IFERROR(__xludf.DUMMYFUNCTION("""COMPUTED_VALUE"""),24.0) -> 24 | B26: =IFERROR(__xludf.DUMMYFUNCTION("""COMPUTED_VALUE"""),"Hitesh Vats") -> Hitesh Vats | C26: =IFERROR(__xludf.DUMMYFUNCTION("""COMPUTED_VALUE"""),"vatshitesh8@gmail.com") -> vatshitesh8@gmail.com | D26: =IFERROR(__xludf.DUMMYFUNCTION("""COMPUTED_VALUE"""),8.800274005E9) -> 8800274005 | E26: =IFERROR(__xludf.DUMMYFUNCTION("""COMPUTED_VALUE"""),44580.0) -> 44580 | G26: =IFERROR(__xludf.DUMMYFUNCTION("""COMPUTED_VALUE"""),"T4/104, Aagman Society, Sector 70 IMT, Faridabad - 121004") -> T4/104, Aagman Society, Sector 70 IMT, Faridabad - 121004 | H26: =IFERROR(__xludf.DUMMYFUNCTION("""COMPUTED_VALUE"""),"Windows Laptop") -> Windows Laptop | I26: =IFERROR(__xludf.DUMMYFUNCTION("""COMPUTED_VALUE"""),"Manager - Finance") -> Manager - Finance | L26: =IFERROR(__xludf.DUMMYFUNCTION("""COMPUTED_VALUE"""),"Dispatched") -> Dispatched | M26: =IFERROR(__xludf.DUMMYFUNCTION("""COMPUTED_VALUE"""),"Delivered") -> Delivered
A27: =IFERROR(__xludf.DUMMYFUNCTION("""COMPUTED_VALUE"""),25.0) -> 25 | B27: =IFERROR(__xludf.DUMMYFUNCTION("""COMPUTED_VALUE"""),"Akash Kumar Chauhan") -> Akash Kumar Chauhan | C27: =IFERROR(__xludf.DUMMYFUNCTION("""COMPUTED_VALUE"""),"akashchauhan5891@gmail.com") -> akashchauhan5891@gmail.com | D27: =IFERROR(__xludf.DUMMYFUNCTION("""COMPUTED_VALUE"""),"7202077483 / 7202077483") -> 7202077483 / 7202077483 | E27: =IFERROR(__xludf.DUMMYFUNCTION("""COMPUTED_VALUE"""),44580.0) -> 44580 | G27: =IFERROR(__xludf.DUMMYFUNCTION("""COMPUTED_VALUE"""),"Ecom Express Limited Khasra 40/25/1,21/1/2, 22,23,23/1,49/1/1, 1/2,2,3,4/1, 50/4, Min 5/1, 5/2 Sidhrawali Village, Tahsil Manesar, District Gurgaon, Haryana- 122413, India") -> Ecom Express Limited Khasra 40/25/1,21/1/2, 22,23,23/1,49/1/1, 1/2,2,3,4/1, 50/4, Min 5/1, 5/2 Sidhrawali Village, Tahsil Manesar, District Gurgaon, Haryana- 122413, India | H27: =IFERROR(__xludf.DUMMYFUNCTION("""COMPUTED_VALUE"""),"Windows Laptop") -> Windows Laptop | I27: =IFERROR(__xludf.DUMMYFUNCTION("""COMPUTED_VALUE"""),"Executive - Administration & Procurement") -> Executive - Administration & Procurement | L27: =IFERROR(__xludf.DUMMYFUNCTION("""COMPUTED_VALUE"""),"Employee will be picking it up from office only on 19th Jan") -> Employee will be picking it up from office only on 19th Jan | M27: =IFERROR(__xludf.DUMMYFUNCTION("""COMPUTED_VALUE"""),"NA") -> NA
A28: =IFERROR(__xludf.DUMMYFUNCTION("""COMPUTED_VALUE"""),26.0) -> 26 | B28: =IFERROR(__xludf.DUMMYFUNCTION("""COMPUTED_VALUE"""),"Abhinav Venkat") -> Abhinav Venkat | C28: =IFERROR(__xludf.DUMMYFUNCTION("""COMPUTED_VALUE"""),"abhinav.venkat@icloud.com") -> abhinav.venkat@icloud.com | D28: =IFERROR(__xludf.DUMMYFUNCTION("""COMPUTED_VALUE"""),"98848 36501") -> 98848 36501 | E28: =IFERROR(__xludf.DUMMYFUNCTION("""COMPUTED_VALUE"""),"Already joined") -> Already joined | G28: =IFERROR(__xludf.DUMMYFUNCTION("""COMPUTED_VALUE"""),"Villa #5, Casa Grande Versailles Amar, Uthandi, Chennai, 600119, Tamil Nadu, India") -> Villa #5, Casa Grande Versailles Amar, Uthandi, Chennai, 600119, Tamil Nadu, India | H28: =IFERROR(__xludf.DUMMYFUNCTION("""COMPUTED_VALUE"""),"Macbook 13"" Pro") -> Macbook 13" Pro | I28: =IFERROR(__xludf.DUMMYFUNCTION("""COMPUTED_VALUE"""),"Consulting Partner") -> Consulting Partner | L28: =IFERROR(__xludf.DUMMYFUNCTION("""COMPUTED_VALUE"""),"Dispatched") -> Dispatched | M28: =IFERROR(__xludf.DUMMYFUNCTION("""COMPUTED_VALUE"""),"Delivered") -> Delivered
A29: =IFERROR(__xludf.DUMMYFUNCTION("""COMPUTED_VALUE"""),27.0) -> 27 | B29: =IFERROR(__xludf.DUMMYFUNCTION("""COMPUTED_VALUE"""),"Shubham Kumar") -> Shubham Kumar | C29: =IFERROR(__xludf.DUMMYFUNCTION("""COMPUTED_VALUE"""),"shubhamkr75@gmail.com") -> shubhamkr75@gmail.com | D29: =IFERROR(__xludf.DUMMYFUNCTION("""COMPUTED_VALUE"""),8.29277426E9) -> 8292774260 | E29: =IFERROR(__xludf.DUMMYFUNCTION("""COMPUTED_VALUE"""),44585.0) -> 44585 | G29: =IFERROR(__xludf.DUMMYFUNCTION("""COMPUTED_VALUE"""),"Opp. Samay Hospital, saguna more, danapur cantt, Patna, 801503. Landmark - near Samay Hospital") -> Opp. Samay Hospital, saguna more, danapur cantt, Patna, 801503. Landmark - near Samay Hospital | H29: =IFERROR(__xludf.DUMMYFUNCTION("""COMPUTED_VALUE"""),"Macbook + Mobile Phone") -> Macbook + Mobile Phone | I29: =IFERROR(__xludf.DUMMYFUNCTION("""COMPUTED_VALUE"""),"Software Engineer") -> Software Engineer | L29: =IFERROR(__xludf.DUMMYFUNCTION("""COMPUTED_VALUE"""),"Dispatched") -> Dispatched | M29: =IFERROR(__xludf.DUMMYFUNCTION("""COMPUTED_VALUE"""),"Delivered") -> Delivered
A30: =IFERROR(__xludf.DUMMYFUNCTION("""COMPUTED_VALUE"""),28.0) -> 28 | B30: =IFERROR(__xludf.DUMMYFUNCTION("""COMPUTED_VALUE"""),"Santosh Arjun Auti") -> Santosh Arjun Auti | C30: =IFERROR(__xludf.DUMMYFUNCTION("""COMPUTED_VALUE"""),"santoshauti1991@gmail.com") -> santoshauti1991@gmail.com | D30: =IFERROR(__xludf.DUMMYFUNCTION("""COMPUTED_VALUE"""),9.96007134E9) -> 9960071340 | E30: =IFERROR(__xludf.DUMMYFUNCTION("""COMPUTED_VALUE"""),44586.0) -> 44586 | G30: =IFERROR(__xludf.DUMMYFUNCTION("""COMPUTED_VALUE"""),"C/503, Phase 2, Dwarka suncrest society, Near Hyderabadi house, Kokane chowk, Rahatani, Pune- 411027") -> C/503, Phase 2, Dwarka suncrest society, Near Hyderabadi house, Kokane chowk, Rahatani, Pune- 411027 | H30: =IFERROR(__xludf.DUMMYFUNCTION("""COMPUTED_VALUE"""),"Macbook 13"" Pro") -> Macbook 13" Pro | I30: =IFERROR(__xludf.DUMMYFUNCTION("""COMPUTED_VALUE"""),"Technical Product Manager") -> Technical Product Manager | L30: =IFERROR(__xludf.DUMMYFUNCTION("""COMPUTED_VALUE"""),"Dispatched") -> Dispatched | M30: =IFERROR(__xludf.DUMMYFUNCTION("""COMPUTED_VALUE"""),"Delivered") -> Delivered | N30: =IFERROR(__xludf.DUMMYFUNCTION("""COMPUTED_VALUE"""),"Offer Drop - laptop to be picked up") -> Offer Drop - laptop to be picked up
A31: =IFERROR(__xludf.DUMMYFUNCTION("""COMPUTED_VALUE"""),29.0) -> 29 | B31: =IFERROR(__xludf.DUMMYFUNCTION("""COMPUTED_VALUE"""),"Kritika Kapoor") -> Kritika Kapoor | C31: =IFERROR(__xludf.DUMMYFUNCTION("""COMPUTED_VALUE"""),"kritikakapoor14@outlook.com") -> kritikakapoor14@outlook.com | D31: =IFERROR(__xludf.DUMMYFUNCTION("""COMPUTED_VALUE"""),"9034575564 / 8810286386/ 9518444301") -> 9034575564 / 8810286386/ 9518444301 | E31: =IFERROR(__xludf.DUMMYFUNCTION("""COMPUTED_VALUE"""),44588.0) -> 44588 | G31: =IFERROR(__xludf.DUMMYFUNCTION("""COMPUTED_VALUE"""),"C/0 Nakul Sharma, Crimpton Equipment Pvt Ltd, LGF-26, Panchsheel Square, Crossings Republik, Opposite IGL CNG Pump, Ghaziabad, Uttar Pradesh - 201009") -> C/0 Nakul Sharma, Crimpton Equipment Pvt Ltd, LGF-26, Panchsheel Square, Crossings Republik, Opposite IGL CNG Pump, Ghaziabad, Uttar Pradesh - 201009 | H31: =IFERROR(__xludf.DUMMYFUNCTION("""COMPUTED_VALUE"""),"Macbook + Mobile Phone + wireless Mouse") -> Macbook + Mobile Phone + wireless Mouse | I31: =IFERROR(__xludf.DUMMYFUNCTION("""COMPUTED_VALUE"""),"Sr. SDET") -> Sr. SDET | L31: =IFERROR(__xludf.DUMMYFUNCTION("""COMPUTED_VALUE"""),"Dispatched") -> Dispatched | M31: =IFERROR(__xludf.DUMMYFUNCTION("""COMPUTED_VALUE"""),"Delivered") -> Delivered
A32: =IFERROR(__xludf.DUMMYFUNCTION("""COMPUTED_VALUE"""),30.0) -> 30 | B32: =IFERROR(__xludf.DUMMYFUNCTION("""COMPUTED_VALUE"""),"Vigneshwaran Baskaran") -> Vigneshwaran Baskaran | C32: =IFERROR(__xludf.DUMMYFUNCTION("""COMPUTED_VALUE"""),"inboxmeatvigneshwaran.baskaran@gmail.com") -> inboxmeatvigneshwaran.baskaran@gmail.com | D32: =IFERROR(__xludf.DUMMYFUNCTION("""COMPUTED_VALUE"""),9.176347427E9) -> 9176347427 | E32: =IFERROR(__xludf.DUMMYFUNCTION("""COMPUTED_VALUE"""),44585.0) -> 44585 | G32: =IFERROR(__xludf.DUMMYFUNCTION("""COMPUTED_VALUE"""),"C-15, Abinayam phase-1, 2nd Avenue sakthi nagar, Nolambur, Chennai - 600095") -> C-15, Abinayam phase-1, 2nd Avenue sakthi nagar, Nolambur, Chennai - 600095 | H32: =IFERROR(__xludf.DUMMYFUNCTION("""COMPUTED_VALUE"""),"Macbook + Mobile Phone + wireless Mouse") -> Macbook + Mobile Phone + wireless Mouse | I32: =IFERROR(__xludf.DUMMYFUNCTION("""COMPUTED_VALUE"""),"Sr. SDET") -> Sr. SDET | L32: =IFERROR(__xludf.DUMMYFUNCTION("""COMPUTED_VALUE"""),"Dispatched") -> Dispatched | M32: =IFERROR(__xludf.DUMMYFUNCTION("""COMPUTED_VALUE"""),"Delivered") -> Delivered | N32: =IFERROR(__xludf.DUMMYFUNCTION("""COMPUTED_VALUE"""),"Offer Drop - laptop to be picked up") -> Offer Drop - laptop to be picked up
A33: =IFERROR(__xludf.DUMMYFUNCTION("""COMPUTED_VALUE"""),31.0) -> 31 | B33: =IFERROR(__xludf.DUMMYFUNCTION("""COMPUTED_VALUE"""),"Abhinav Srivastava") -> Abhinav Srivastava | C33: =IFERROR(__xludf.DUMMYFUNCTION("""COMPUTED_VALUE"""),"abhinavsrivastava170@gmail.com") -> abhinavsrivastava170@gmail.com | D33: =IFERROR(__xludf.DUMMYFUNCTION("""COMPUTED_VALUE"""),9.58236164E9) -> 9582361640 | E33: =IFERROR(__xludf.DUMMYFUNCTION("""COMPUTED_VALUE"""),44585.0) -> 44585 | G33: =IFERROR(__xludf.DUMMYFUNCTION("""COMPUTED_VALUE"""),"B-445 Raja Ji Puram, Lucknow, Uttar Pradesh. Pin Code-226017") -> B-445 Raja Ji Puram, Lucknow, Uttar Pradesh. Pin Code-226017 | H33: =IFERROR(__xludf.DUMMYFUNCTION("""COMPUTED_VALUE"""),"Windows Laptop + Headphone + Mouse") -> Windows Laptop + Headphone + Mouse | I33: =IFERROR(__xludf.DUMMYFUNCTION("""COMPUTED_VALUE"""),"Data Engineer") -> Data Engineer | L33: =IFERROR(__xludf.DUMMYFUNCTION("""COMPUTED_VALUE"""),"Dispatched") -> Dispatched | M33: =IFERROR(__xludf.DUMMYFUNCTION("""COMPUTED_VALUE"""),"Delivered") -> Delivered
A34: =IFERROR(__xludf.DUMMYFUNCTION("""COMPUTED_VALUE"""),32.0) -> 32 | B34: =IFERROR(__xludf.DUMMYFUNCTION("""COMPUTED_VALUE"""),"Reyansh Mishra") -> Reyansh Mishra | C34: =IFERROR(__xludf.DUMMYFUNCTION("""COMPUTED_VALUE"""),"reyanshmishra@outlook.com") -> reyanshmishra@outlook.com | D34: =IFERROR(__xludf.DUMMYFUNCTION("""COMPUTED_VALUE"""),9.321910353E9) -> 9321910353 | E34: =IFERROR(__xludf.DUMMYFUNCTION("""COMPUTED_VALUE"""),44599.0) -> 44599 | G34: =IFERROR(__xludf.DUMMYFUNCTION("""COMPUTED_VALUE"""),"703, A Wing, Paradigm Twinstar, near Ritu Glorius, near Orange Hospital, Ramdev Park, Mira Road East 401107") -> 703, A Wing, Paradigm Twinstar, near Ritu Glorius, near Orange Hospital, Ramdev Park, Mira Road East 401107 | H34: =IFERROR(__xludf.DUMMYFUNCTION("""COMPUTED_VALUE"""),"Macbook + Mobile Phone") -> Macbook + Mobile Phone | I34: =IFERROR(__xludf.DUMMYFUNCTION("""COMPUTED_VALUE"""),"Senior Software Engineer") -> Senior Software Engineer | L34: =IFERROR(__xludf.DUMMYFUNCTION("""COMPUTED_VALUE"""),"Dispatched") -> Dispatched | M34: =IFERROR(__xludf.DUMMYFUNCTION("""COMPUTED_VALUE"""),"Delivered") -> Delivered
A35: =IFERROR(__xludf.DUMMYFUNCTION("""COMPUTED_VALUE"""),33.0) -> 33 | B35: =IFERROR(__xludf.DUMMYFUNCTION("""COMPUTED_VALUE"""),"Ritika Gola") -> Ritika Gola | C35: =IFERROR(__xludf.DUMMYFUNCTION("""COMPUTED_VALUE"""),"ritikagola08@gmail.com") -> ritikagola08@gmail.com | D35: =IFERROR(__xludf.DUMMYFUNCTION("""COMPUTED_VALUE"""),"98993 27662") -> 98993 27662 | E35: =IFERROR(__xludf.DUMMYFUNCTION("""COMPUTED_VALUE"""),44593.0) -> 44593 | G35: =IFERROR(__xludf.DUMMYFUNCTION("""COMPUTED_VALUE"""),"C-2/226 yamuna vihar delhi 53") -> C-2/226 yamuna vihar delhi 53 | H35: =IFERROR(__xludf.DUMMYFUNCTION("""COMPUTED_VALUE"""),"Windows laptop") -> Windows laptop | I35: =IFERROR(__xludf.DUMMYFUNCTION("""COMPUTED_VALUE"""),"Executive - Customer Experience") -> Executive - Customer Experience | L35: =IFERROR(__xludf.DUMMYFUNCTION("""COMPUTED_VALUE"""),"Dispatched") -> Dispatched | M35: =IFERROR(__xludf.DUMMYFUNCTION("""COMPUTED_VALUE"""),"Delivered") -> Delivered
A36: =IFERROR(__xludf.DUMMYFUNCTION("""COMPUTED_VALUE"""),34.0) -> 34 | B36: =IFERROR(__xludf.DUMMYFUNCTION("""COMPUTED_VALUE"""),"Nikhil Kumar Gupta") -> Nikhil Kumar Gupta | C36: =IFERROR(__xludf.DUMMYFUNCTION("""COMPUTED_VALUE"""),"guptanikhil1503@gmail.com") -> guptanikhil1503@gmail.com | D36: =IFERROR(__xludf.DUMMYFUNCTION("""COMPUTED_VALUE"""),9.910930975E9) -> 9910930975 | E36: =IFERROR(__xludf.DUMMYFUNCTION("""COMPUTED_VALUE"""),44593.0) -> 44593 | G36: =IFERROR(__xludf.DUMMYFUNCTION("""COMPUTED_VALUE"""),"201, A-Block 5th Avenue Alwanaka, Manjhalpur Vadodara Gujrat Pincode:- 390011") -> 201, A-Block 5th Avenue Alwanaka, Manjhalpur Vadodara Gujrat Pincode:- 390011 | H36: =IFERROR(__xludf.DUMMYFUNCTION("""COMPUTED_VALUE"""),"Macbook + Mobile Phone") -> Macbook + Mobile Phone | I36: =IFERROR(__xludf.DUMMYFUNCTION("""COMPUTED_VALUE"""),"DevOps Engineer") -> DevOps Engineer | L36: =IFERROR(__xludf.DUMMYFUNCTION("""COMPUTED_VALUE"""),"Dispatched") -> Dispatched | M36: =IFERROR(__xludf.DUMMYFUNCTION("""COMPUTED_VALUE"""),"Delivered") -> Delivered
A37: =IFERROR(__xludf.DUMMYFUNCTION("""COMPUTED_VALUE"""),35.0) -> 35 | B37: =IFERROR(__xludf.DUMMYFUNCTION("""COMPUTED_VALUE"""),"Vidhi Arora") -> Vidhi Arora | C37: =IFERROR(__xludf.DUMMYFUNCTION("""COMPUTED_VALUE"""),"aroravidhi01@gmail.com") -> aroravidhi01@gmail.com | D37: =IFERROR(__xludf.DUMMYFUNCTION("""COMPUTED_VALUE"""),7.00990541E9) -> 7009905410 | E37: =IFERROR(__xludf.DUMMYFUNCTION("""COMPUTED_VALUE"""),44606.0) -> 44606 | G37: =IFERROR(__xludf.DUMMYFUNCTION("""COMPUTED_VALUE"""),"Second Floor, Street No.2 , Court Colony near Sanjivani Hospital, Sirsa, Haryana. Pincode - 125055") -> Second Floor, Street No.2 , Court Colony near Sanjivani Hospital, Sirsa, Haryana. Pincode - 125055 | H37: =IFERROR(__xludf.DUMMYFUNCTION("""COMPUTED_VALUE"""),"Macbook + Mobile Phone") -> Macbook + Mobile Phone | I37: =IFERROR(__xludf.DUMMYFUNCTION("""COMPUTED_VALUE"""),"SDET") -> SDET | L37: =IFERROR(__xludf.DUMMYFUNCTION("""COMPUTED_VALUE"""),"Dispatched") -> Dispatched | M37: =IFERROR(__xludf.DUMMYFUNCTION("""COMPUTED_VALUE"""),"Delivered") -> Delivered
A38: =IFERROR(__xludf.DUMMYFUNCTION("""COMPUTED_VALUE"""),36.0) -> 36 | B38: =IFERROR(__xludf.DUMMYFUNCTION("""COMPUTED_VALUE"""),"Deeplata Singh") -> Deeplata Singh | C38: =IFERROR(__xludf.DUMMYFUNCTION("""COMPUTED_VALUE"""),"deeptisingh151090@gmail.com") -> deeptisingh151090@gmail.com | D38: =IFERROR(__xludf.DUMMYFUNCTION("""COMPUTED_VALUE"""),9.580846113E9) -> 9580846113 | E38: =IFERROR(__xludf.DUMMYFUNCTION("""COMPUTED_VALUE"""),44593.0) -> 44593 | G38: =IFERROR(__xludf.DUMMYFUNCTION("""COMPUTED_VALUE"""),"555/J/317-10 RAM PRASAD KHERA ALAMBAGH BEHIND CENTRAL BANK OF INDIA LUCKNOW UP - 226005") -> 555/J/317-10 RAM PRASAD KHERA ALAMBAGH BEHIND CENTRAL BANK OF INDIA LUCKNOW UP - 226005 | H38: =IFERROR(__xludf.DUMMYFUNCTION("""COMPUTED_VALUE"""),"Windows Laptop") -> Windows Laptop | I38: =IFERROR(__xludf.DUMMYFUNCTION("""COMPUTED_VALUE"""),"Executive - Customer Experience") -> Executive - Customer Experience | L38: =IFERROR(__xludf.DUMMYFUNCTION("""COMPUTED_VALUE"""),"Dispatched") -> Dispatched | M38: =IFERROR(__xludf.DUMMYFUNCTION("""COMPUTED_VALUE"""),"Delivered") -> Delivered
